Workbook

Sheet INFO TIENDAS
A1: CR | B1: ZONA | C1: DEPARTAMENTO | D1: MUN | E1: UPZ/COMUNA | F1: ESTRATO | G1: NAME | H1: ARRENDADOR | I1: TIPO DE LOCAL | J1: AREA | K1: VT | L1: ET | M1: FECHA APE | N1: DIA | O1: DIAS OP | P1: DIAS MES | Q1: MESOP | R1: TR15MIN | S1: Y | T1: X | U1: TRAFICO UM | V1: TRU6 | W1: TICKET UM | X1: TICKET U6M | Y1: VENTAS OUM | Z1: VU6M | AA1: CONTRIBUCION UM | AB1: CONTRIBUCION U6M | AC1: MARGEN UM | AD1: MARGEN U6M | AE1: RENTA | AF1: RU6M | AG1: %Batting | AH1: GENERADOR | AI1: ESTADO | AJ1: SEG26 | AK1: TIE26 | AL1: ME | AM1: COSTO M2 | AN1: TE | AO1: PTH
A2: 50WHX | B2: Centro Norte | C2: Distrito Capital | D2: Bogotá | E2: LOS CEDROS | F2: 5 | G2: 140 | H2: 0 | I2: Esquinero | J2: 177.38 | K2: 163 | L2: 3034 | M2: 0 | N2: 40514 | O2: 2 | P2: 30 | Q2: 31 | R2: 115 | S2: 4.7229 | T2: -74.044754 | U2: =_xlfn.XLOOKUP(A2,'BD UM'!A:A,'BD UM'!B:B) -> 22077 | V2: =_xlfn.XLOOKUP(A2,'BD U6M'!A:A,'BD U6M'!B:B) -> 18642.833 | W2: =_xlfn.XLOOKUP(A2,'BD UM'!A:A,'BD UM'!C:C) -> 11072.6 | X2: =_xlfn.XLOOKUP(A2,'BD U6M'!A:A,'BD U6M'!C:C) -> 11161.2 | Y2: =_xlfn.XLOOKUP(A2,'BD UM'!A:A,'BD UM'!D:D) -> 244450.15 | Z2: =_xlfn.XLOOKUP(A2,'BD U6M'!A:A,'BD U6M'!D:D) -> 208076.68 | AA2: =_xlfn.XLOOKUP(A2,'BD UM'!A:A,'BD UM'!E:E) -> 24670.567 | AB2: =_xlfn.XLOOKUP(A2,'BD U6M'!A:A,'BD U6M'!E:E) -> 14864.344 | AC2: =_xlfn.XLOOKUP(A2,'BD UM'!A:A,'BD UM'!F:F) -> 94683.375 | AD2: =_xlfn.XLOOKUP(A2,'BD U6M'!A:A,'BD U6M'!F:F) -> 77364.549 | AE2: =_xlfn.XLOOKUP(A2,'BD UM'!A:A,'BD UM'!G:G) -> 11964.614 | AF2: =_xlfn.XLOOKUP(A2,'BD U6M'!A:A,'BD U6M'!G:G) -> 11701.896 | AG2: =_xlfn.XLOOKUP(A2,'BD UM'!A:A,'BD UM'!H:H) -> 0 | AH2: BAJA DENSIDAD | AI2: ABIERTA | AJ2: BASE | AK2: TMCB | AL2: 232000 | AM2: 64.51 | AN2: PT | AO2: Alto
A3: 505ST | B3: Centro Sur | C3: Distrito Capital | D3: Bogotá | E3: LAS NIEVES | F3: 3 | G3: 724 | H3: CONSTRUCTORA COLPATRIA S.A.S | I3: Esquinero | J3: 111.57 | K3: 1589 | L3: 3640 | M3: 116 | N3: 45535 | O3: 31 | P3: 1 | Q3: 31 | R3: 24 | S3: 4.610195 | T3: -74.07075 | U3: =_xlfn.XLOOKUP(A3,'BD UM'!A:A,'BD UM'!B:B) -> 21529 | V3: =_xlfn.XLOOKUP(A3,'BD U6M'!A:A,'BD U6M'!B:B) -> 22400.667 | W3: =_xlfn.XLOOKUP(A3,'BD UM'!A:A,'BD UM'!C:C) -> 11000.6 | X3: =_xlfn.XLOOKUP(A3,'BD U6M'!A:A,'BD U6M'!C:C) -> 11195.9 | Y3: =_xlfn.XLOOKUP(A3,'BD UM'!A:A,'BD UM'!D:D) -> 236831.95 | Z3: =_xlfn.XLOOKUP(A3,'BD U6M'!A:A,'BD U6M'!D:D) -> 250796.24 | AA3: =_xlfn.XLOOKUP(A3,'BD UM'!A:A,'BD UM'!E:E) -> 23309.78 | AB3: =_xlfn.XLOOKUP(A3,'BD U6M'!A:A,'BD U6M'!E:E) -> 24111.698 | AC3: =_xlfn.XLOOKUP(A3,'BD UM'!A:A,'BD UM'!F:F) -> 86702.55 | AD3: =_xlfn.XLOOKUP(A3,'BD U6M'!A:A,'BD U6M'!F:F) -> 89892.042 | AE3: =_xlfn.XLOOKUP(A3,'BD UM'!A:A,'BD UM'!G:G) -> 10652.709 | AF3: =_xlfn.XLOOKUP(A3,'BD U6M'!A:A,'BD U6M'!G:G) -> 10468.454 | AG3: =_xlfn.XLOOKUP(A3,'BD UM'!A:A,'BD UM'!H:H) -> 0 | AH3: ADMINISTRATIVO | AI3: ABIERTA | AJ3: BASE | AK3: EXP 2024 | AL3: 232000 | AM3: 92.69 | AN3: Bosque Izquierdo | AO3: Medio
A4: 50QK2 | B4: Centro Sur | C4: Distrito Capital | D4: Bogotá | E4: CIUDAD JARDIN | F4: 3 | G4: 1ero De Mayo | H4: 0 | I4: Esquinero | J4: 83.9 | K4: 537 | L4: 142 | M4: 186 | N4: 43740 | O4: 2 | P4: 30 | Q4: 31 | R4: 83 | S4: 4.576091 | T4: -74.094651 | U4: =_xlfn.XLOOKUP(A4,'BD UM'!A:A,'BD UM'!B:B) -> 24710 | V4: =_xlfn.XLOOKUP(A4,'BD U6M'!A:A,'BD U6M'!B:B) -> 26219.833 | W4: =_xlfn.XLOOKUP(A4,'BD UM'!A:A,'BD UM'!C:C) -> 11952.2 | X4: =_xlfn.XLOOKUP(A4,'BD U6M'!A:A,'BD U6M'!C:C) -> 12043.8 | Y4: =_xlfn.XLOOKUP(A4,'BD UM'!A:A,'BD UM'!D:D) -> 295339.88 | Z4: =_xlfn.XLOOKUP(A4,'BD U6M'!A:A,'BD U6M'!D:D) -> 315786.29 | AA4: =_xlfn.XLOOKUP(A4,'BD UM'!A:A,'BD UM'!E:E) -> 29877.54 | AB4: =_xlfn.XLOOKUP(A4,'BD U6M'!A:A,'BD U6M'!E:E) -> 34274.564 | AC4: =_xlfn.XLOOKUP(A4,'BD UM'!A:A,'BD UM'!F:F) -> 95950.726 | AD4: =_xlfn.XLOOKUP(A4,'BD U6M'!A:A,'BD U6M'!F:F) -> 104090.9 | AE4: =_xlfn.XLOOKUP(A4,'BD UM'!A:A,'BD UM'!G:G) -> 8067.591 | AF4: =_xlfn.XLOOKUP(A4,'BD U6M'!A:A,'BD U6M'!G:G) -> 7824.8097 | AG4: =_xlfn.XLOOKUP(A4,'BD UM'!A:A,'BD UM'!H:H) -> 0 | AH4: COMERCIO/SERVICIO | AI4: ABIERTA | AJ4: BASE | AK4: TMCB | AL4: 232000 | AM4: 91.49 | AN4: Quiroga | AO4: Medio
A5: 50HQ9 | B5: Centro Sur | C5: Distrito Capital | D5: Bogotá | E5: PARDO RUBIO | F5: 4 | G5: 7 Estorias | H5: 0 | I5: Esquinero | J5: 128.02 | K5: 2789 | L5: 1350 | M5: 139 | N5: 46078 | O5: 25 | P5: 4 | Q5: 28 | R5: 6 | S5: 6.249603 | T5: -75.588874 | U5: =_xlfn.XLOOKUP(A5,'BD UM'!A:A,'BD UM'!B:B) -> 16492 | V5: =_xlfn.XLOOKUP(A5,'BD U6M'!A:A,'BD U6M'!B:B) -> 14178.333 | W5: =_xlfn.XLOOKUP(A5,'BD UM'!A:A,'BD UM'!C:C) -> 11515.4 | X5: =_xlfn.XLOOKUP(A5,'BD U6M'!A:A,'BD U6M'!C:C) -> 11523.2 | Y5: =_xlfn.XLOOKUP(A5,'BD UM'!A:A,'BD UM'!D:D) -> 189911.95 | Z5: =_xlfn.XLOOKUP(A5,'BD U6M'!A:A,'BD U6M'!D:D) -> 163380.17 | AA5: =_xlfn.XLOOKUP(A5,'BD UM'!A:A,'BD UM'!E:E) -> 13610.537 | AB5: =_xlfn.XLOOKUP(A5,'BD U6M'!A:A,'BD U6M'!E:E) -> 7529.342 | AC5: =_xlfn.XLOOKUP(A5,'BD UM'!A:A,'BD UM'!F:F) -> 71073.664 | AD5: =_xlfn.XLOOKUP(A5,'BD U6M'!A:A,'BD U6M'!F:F) -> 59571.772 | AE5: =_xlfn.XLOOKUP(A5,'BD UM'!A:A,'BD UM'!G:G) -> 9877.52 | AF5: =_xlfn.XLOOKUP(A5,'BD U6M'!A:A,'BD U6M'!G:G) -> 8465.2449 | AG5: =_xlfn.XLOOKUP(A5,'BD UM'!A:A,'BD UM'!H:H) -> 1.3425 | AH5: ND | AI5: ABIERTA | AJ5: BASE | AK5: EXP 2026 | AL5: 204160 | AM5: 77.16 | AN5: Septima 49 | AO5: Medio
A6: 50VEG | B6: Centro Norte | C6: Distrito Capital | D6: Bogotá | E6: CHICO LAGO | F6: 4 | G6: 72 Caracas | H6: TAQ INVERSIONES S.A.S | I6: Esquinero | J6: 125.91 | K6: 560 | L6: 2330 | M6: 235 | N6: 45899 | O6: 30 | P6: 2 | Q6: 31 | R6: 12 | S6: 4.658777 | T6: -74.061517 | U6: =_xlfn.XLOOKUP(A6,'BD UM'!A:A,'BD UM'!B:B) -> 19258 | V6: =_xlfn.XLOOKUP(A6,'BD U6M'!A:A,'BD U6M'!B:B) -> 15677.833 | W6: =_xlfn.XLOOKUP(A6,'BD UM'!A:A,'BD UM'!C:C) -> 10212.9 | X6: =_xlfn.XLOOKUP(A6,'BD U6M'!A:A,'BD U6M'!C:C) -> 10403.3 | Y6: =_xlfn.XLOOKUP(A6,'BD UM'!A:A,'BD UM'!D:D) -> 196680.59 | Z6: =_xlfn.XLOOKUP(A6,'BD U6M'!A:A,'BD U6M'!D:D) -> 163101.26 | AA6: =_xlfn.XLOOKUP(A6,'BD UM'!A:A,'BD UM'!E:E) -> 6743.534 | AB6: =_xlfn.XLOOKUP(A6,'BD U6M'!A:A,'BD U6M'!E:E) -> -2707.8947 | AC6: =_xlfn.XLOOKUP(A6,'BD UM'!A:A,'BD UM'!F:F) -> 73753.755 | AD6: =_xlfn.XLOOKUP(A6,'BD U6M'!A:A,'BD U6M'!F:F) -> 58330.5 | AE6: =_xlfn.XLOOKUP(A6,'BD UM'!A:A,'BD UM'!G:G) -> 19286.25 | AF6: =_xlfn.XLOOKUP(A6,'BD U6M'!A:A,'BD U6M'!G:G) -> 18805.255 | AG6: =_xlfn.XLOOKUP(A6,'BD UM'!A:A,'BD UM'!H:H) -> 1.0328 | AH6: COMERCIO/SERVICIO | AI6: ABIERTA | AJ6: BASE | AK6: EXP 2025 | AL6: 232000 | AM6: 146.93 | AN6: 1ero De Mayo | AO6: Medio
A7: 50EXM | B7: Centro Sur | C7: Distrito Capital | D7: Bogotá | E7: CASTILLA | F7: 3 | G7: 72 Castilla | H7: 0 | I7: Esquinero | J7: 146.43 | K7: 1343 | L7: 375 | M7: 0 | N7: 44672 | O7: 21 | P7: 10 | Q7: 30 | R7: 52 | S7: 4.639826 | T7: -74.137131 | U7: =_xlfn.XLOOKUP(A7,'BD UM'!A:A,'BD UM'!B:B) -> 15085 | V7: =_xlfn.XLOOKUP(A7,'BD U6M'!A:A,'BD U6M'!B:B) -> 14927.5 | W7: =_xlfn.XLOOKUP(A7,'BD UM'!A:A,'BD UM'!C:C) -> 13272.9 | X7: =_xlfn.XLOOKUP(A7,'BD U6M'!A:A,'BD U6M'!C:C) -> 14024.1 | Y7: =_xlfn.XLOOKUP(A7,'BD UM'!A:A,'BD UM'!D:D) -> 200221.17 | Z7: =_xlfn.XLOOKUP(A7,'BD U6M'!A:A,'BD U6M'!D:D) -> 209344.71 | AA7: =_xlfn.XLOOKUP(A7,'BD UM'!A:A,'BD UM'!E:E) -> 13884.992 | AB7: =_xlfn.XLOOKUP(A7,'BD U6M'!A:A,'BD U6M'!E:E) -> 12789.462 | AC7: =_xlfn.XLOOKUP(A7,'BD UM'!A:A,'BD UM'!F:F) -> 66934.827 | AD7: =_xlfn.XLOOKUP(A7,'BD U6M'!A:A,'BD U6M'!F:F) -> 69195.44 | AE7: =_xlfn.XLOOKUP(A7,'BD UM'!A:A,'BD UM'!G:G) -> 9567.458 | AF7: =_xlfn.XLOOKUP(A7,'BD U6M'!A:A,'BD U6M'!G:G) -> 9664.2761 | AG7: =_xlfn.XLOOKUP(A7,'BD UM'!A:A,'BD UM'!H:H) -> 0 | AH7: BAJA DENSIDAD | AI7: ABIERTA | AJ7: HOGAR | AK7: TMCB | AL7: 241405 | AM7: 65.33 | AN7: Britania | AO7: Medio
A8: 50WLE | B8: Centro Sur | C8: Distrito Capital | D8: Bogotá | E8: KENNEDY CENTRAL | F8: 3 | G8: 73 Kennedy | H8: 0 | I8: Esquinero | J8: 99.8 | K8: 1837 | L8: 1249 | M8: 0 | N8: 44587 | O8: 26 | P8: 6 | Q8: 31 | R8: 55 | S8: 4.621015 | T8: -74.147364 | U8: =_xlfn.XLOOKUP(A8,'BD UM'!A:A,'BD UM'!B:B) -> 15770 | V8: =_xlfn.XLOOKUP(A8,'BD U6M'!A:A,'BD U6M'!B:B) -> 16554.833 | W8: =_xlfn.XLOOKUP(A8,'BD UM'!A:A,'BD UM'!C:C) -> 12160.2 | X8: =_xlfn.XLOOKUP(A8,'BD U6M'!A:A,'BD U6M'!C:C) -> 12236.3 | Y8: =_xlfn.XLOOKUP(A8,'BD UM'!A:A,'BD UM'!D:D) -> 191765.95 | Z8: =_xlfn.XLOOKUP(A8,'BD U6M'!A:A,'BD U6M'!D:D) -> 202569.39 | AA8: =_xlfn.XLOOKUP(A8,'BD UM'!A:A,'BD UM'!E:E) -> 6919.84 | AB8: =_xlfn.XLOOKUP(A8,'BD U6M'!A:A,'BD U6M'!E:E) -> 11253.276 | AC8: =_xlfn.XLOOKUP(A8,'BD UM'!A:A,'BD UM'!F:F) -> 59452.32 | AD8: =_xlfn.XLOOKUP(A8,'BD U6M'!A:A,'BD U6M'!F:F) -> 62913.102 | AE8: =_xlfn.XLOOKUP(A8,'BD UM'!A:A,'BD UM'!G:G) -> 8928.005 | AF8: =_xlfn.XLOOKUP(A8,'BD U6M'!A:A,'BD U6M'!G:G) -> 9021.956 | AG8: =_xlfn.XLOOKUP(A8,'BD UM'!A:A,'BD UM'!H:H) -> 0 | AH8: BAJA DENSIDAD | AI8: ABIERTA | AJ8: HOGAR | AK8: TMCB | AL8: 241405 | AM8: 89.46 | AN8: Kennedy Central | AO8: Medio
A9: 50JA1 | B9: Centro Sur | C9: Distrito Capital | D9: Bogotá | E9: KENNEDY CENTRAL | F9: 3 | G9: 78 Kennedy | H9: 0 | I9: Esquinero | J9: 99.5 | K9: 1566 | L9: 1357 | M9: 0 | N9: 44684 | O9: 3 | P9: 29 | Q9: 31 | R9: 51 | S9: 4.622262 | T9: -74.149932 | U9: =_xlfn.XLOOKUP(A9,'BD UM'!A:A,'BD UM'!B:B) -> 16851 | V9: =_xlfn.XLOOKUP(A9,'BD U6M'!A:A,'BD U6M'!B:B) -> 15549 | W9: =_xlfn.XLOOKUP(A9,'BD UM'!A:A,'BD UM'!C:C) -> 10348.5 | X9: =_xlfn.XLOOKUP(A9,'BD U6M'!A:A,'BD U6M'!C:C) -> 10893 | Y9: =_xlfn.XLOOKUP(A9,'BD UM'!A:A,'BD UM'!D:D) -> 174382.02 | Z9: =_xlfn.XLOOKUP(A9,'BD U6M'!A:A,'BD U6M'!D:D) -> 169374.89 | AA9: =_xlfn.XLOOKUP(A9,'BD UM'!A:A,'BD UM'!E:E) -> 6278.494 | AB9: =_xlfn.XLOOKUP(A9,'BD U6M'!A:A,'BD U6M'!E:E) -> 5938.4532 | AC9: =_xlfn.XLOOKUP(A9,'BD UM'!A:A,'BD UM'!F:F) -> 58383.102 | AD9: =_xlfn.XLOOKUP(A9,'BD U6M'!A:A,'BD U6M'!F:F) -> 57350.701 | AE9: =_xlfn.XLOOKUP(A9,'BD UM'!A:A,'BD UM'!G:G) -> 8789.815 | AF9: =_xlfn.XLOOKUP(A9,'BD U6M'!A:A,'BD U6M'!G:G) -> 8908.3433 | AG9: =_xlfn.XLOOKUP(A9,'BD UM'!A:A,'BD UM'!H:H) -> 0 | AH9: SALUD | AI9: ABIERTA | AJ9: BASE | AK9: EXP 2024 | AL9: 204160 | AM9: 55.43 | AN9: Gonzalez Valencia | AO9: Alto
A10: 505TQ | B10: Centro Sur | C10: Cundinamarca | D10: Girardot | E10: NORTE | F10: 3 | G10: Acacias | H10: 0 | I10: Esquinero | J10: 121.8 | K10: 770 | L10: 675 | M10: 36 | N10: 45259 | O10: 29 | P10: 2 | Q10: 30 | R10: 33 | S10: 4.307396 | T10: -74.803587 | U10: =_xlfn.XLOOKUP(A10,'BD UM'!A:A,'BD UM'!B:B) -> 18516 | V10: =_xlfn.XLOOKUP(A10,'BD U6M'!A:A,'BD U6M'!B:B) -> 17323.5 | W10: =_xlfn.XLOOKUP(A10,'BD UM'!A:A,'BD UM'!C:C) -> 14178.2 | X10: =_xlfn.XLOOKUP(A10,'BD U6M'!A:A,'BD U6M'!C:C) -> 14137.4 | Y10: =_xlfn.XLOOKUP(A10,'BD UM'!A:A,'BD UM'!D:D) -> 262523.89 | Z10: =_xlfn.XLOOKUP(A10,'BD U6M'!A:A,'BD U6M'!D:D) -> 244908.63 | AA10: =_xlfn.XLOOKUP(A10,'BD UM'!A:A,'BD UM'!E:E) -> 21691.861 | AB10: =_xlfn.XLOOKUP(A10,'BD U6M'!A:A,'BD U6M'!E:E) -> 19392.74 | AC10: =_xlfn.XLOOKUP(A10,'BD UM'!A:A,'BD UM'!F:F) -> 84571.373 | AD10: =_xlfn.XLOOKUP(A10,'BD U6M'!A:A,'BD U6M'!F:F) -> 79228.526 | AE10: =_xlfn.XLOOKUP(A10,'BD UM'!A:A,'BD UM'!G:G) -> 5000 | AF10: =_xlfn.XLOOKUP(A10,'BD U6M'!A:A,'BD U6M'!G:G) -> 5061.014 | AG10: =_xlfn.XLOOKUP(A10,'BD UM'!A:A,'BD UM'!H:H) -> 0 | AH10: COMERCIO/SERVICIO | AI10: ABIERTA | AJ10: BASE | AK10: TMCB | AL10: 232000 | AM10: 41.05 | AN10: Uan Sur | AO10: Bajo
A11: 509BS | B11: Centro Norte | C11: Distrito Capital | D11: Bogotá | E11: COUNTRY CLUB | F11: 5 | G11: Acomedica 2 | H11: 0 | I11: Medianero | J11: 169.13 | K11: 650 | L11: 1848 | M11: 0 | N11: 44679 | O11: 28 | P11: 3 | Q11: 30 | R11: 52 | S11: 4.706164 | T11: -74.050061 | U11: =_xlfn.XLOOKUP(A11,'BD UM'!A:A,'BD UM'!B:B) -> 17060 | V11: =_xlfn.XLOOKUP(A11,'BD U6M'!A:A,'BD U6M'!B:B) -> 17249.5 | W11: =_xlfn.XLOOKUP(A11,'BD UM'!A:A,'BD UM'!C:C) -> 10898.4 | X11: =_xlfn.XLOOKUP(A11,'BD U6M'!A:A,'BD U6M'!C:C) -> 10911.8 | Y11: =_xlfn.XLOOKUP(A11,'BD UM'!A:A,'BD UM'!D:D) -> 185927.1 | Z11: =_xlfn.XLOOKUP(A11,'BD U6M'!A:A,'BD U6M'!D:D) -> 188223.76 | AA11: =_xlfn.XLOOKUP(A11,'BD UM'!A:A,'BD UM'!E:E) -> 12813.622 | AB11: =_xlfn.XLOOKUP(A11,'BD U6M'!A:A,'BD U6M'!E:E) -> 13611.432 | AC11: =_xlfn.XLOOKUP(A11,'BD UM'!A:A,'BD UM'!F:F) -> 81384.913 | AD11: =_xlfn.XLOOKUP(A11,'BD U6M'!A:A,'BD U6M'!F:F) -> 82267.277 | AE11: =_xlfn.XLOOKUP(A11,'BD UM'!A:A,'BD UM'!G:G) -> 21185.086 | AF11: =_xlfn.XLOOKUP(A11,'BD U6M'!A:A,'BD U6M'!G:G) -> 21300.101 | AG11: =_xlfn.XLOOKUP(A11,'BD UM'!A:A,'BD UM'!H:H) -> 0 | AH11: SALUD | AI11: ABIERTA | AJ11: BASE | AK11: TMCB | AL11: 232000 | AM11: 66.6 | AN11: Chicamocha | AO11: Medio
A12: 502B0 | B12: Occidente | C12: Risaralda | D12: Dosquebradas | E12: COMUNA 10 | F12: 3 | G12: Acuarela | H12: 0 | I12: Esquinero | J12: 126.54 | K12: 1914 | L12: 150 | M12: 98 | N12: 45443 | O12: 31 | P12: 1 | Q12: 31 | R12: 27 | S12: 4.851488 | T12: -75.662514 | U12: =_xlfn.XLOOKUP(A12,'BD UM'!A:A,'BD UM'!B:B) -> 18230 | V12: =_xlfn.XLOOKUP(A12,'BD U6M'!A:A,'BD U6M'!B:B) -> 17241.667 | W12: =_xlfn.XLOOKUP(A12,'BD UM'!A:A,'BD UM'!C:C) -> 16856.1 | X12: =_xlfn.XLOOKUP(A12,'BD U6M'!A:A,'BD U6M'!C:C) -> 15371.1 | Y12: =_xlfn.XLOOKUP(A12,'BD UM'!A:A,'BD UM'!D:D) -> 307286.2 | Z12: =_xlfn.XLOOKUP(A12,'BD U6M'!A:A,'BD U6M'!D:D) -> 265023.9 | AA12: =_xlfn.XLOOKUP(A12,'BD UM'!A:A,'BD UM'!E:E) -> 47419.103 | AB12: =_xlfn.XLOOKUP(A12,'BD U6M'!A:A,'BD U6M'!E:E) -> 37186.756 | AC12: =_xlfn.XLOOKUP(A12,'BD UM'!A:A,'BD UM'!F:F) -> 114466.78 | AD12: =_xlfn.XLOOKUP(A12,'BD U6M'!A:A,'BD U6M'!F:F) -> 97010.258 | AE12: =_xlfn.XLOOKUP(A12,'BD UM'!A:A,'BD UM'!G:G) -> 4493.149 | AF12: =_xlfn.XLOOKUP(A12,'BD U6M'!A:A,'BD U6M'!G:G) -> 4523.917 | AG12: =_xlfn.XLOOKUP(A12,'BD UM'!A:A,'BD UM'!H:H) -> 0 | AH12: COMERCIO/SERVICIO | AI12: ABIERTA | AJ12: BASE | AK12: TMCB | AL12: 232000 | AM12: 35.51 | AN12: TC | AO12: Alto
A13: 50IHY | B13: Occidente | C13: Valle del Cauca | D13: Cali | E13: COMUNA 19 | F13: 5 | G13: Afe Refugio | H13: SPORT SALUD CENTRO MÉDICO DEPORTIVO SAS | I13: Esquinero | J13: 120 | K13: 2 | L13: 406 | M13: 81 | N13: 45495 | O13: 22 | P13: 10 | Q13: 31 | R13: 25 | S13: 3.39805 | T13: -76.549917 | U13: =_xlfn.XLOOKUP(A13,'BD UM'!A:A,'BD UM'!B:B) -> 15763 | V13: =_xlfn.XLOOKUP(A13,'BD U6M'!A:A,'BD U6M'!B:B) -> 18375.833 | W13: =_xlfn.XLOOKUP(A13,'BD UM'!A:A,'BD UM'!C:C) -> 12853.6 | X13: =_xlfn.XLOOKUP(A13,'BD U6M'!A:A,'BD U6M'!C:C) -> 12581.2 | Y13: =_xlfn.XLOOKUP(A13,'BD UM'!A:A,'BD UM'!D:D) -> 202611.65 | Z13: =_xlfn.XLOOKUP(A13,'BD U6M'!A:A,'BD U6M'!D:D) -> 231190.35 | AA13: =_xlfn.XLOOKUP(A13,'BD UM'!A:A,'BD UM'!E:E) -> -2863.765 | AB13: =_xlfn.XLOOKUP(A13,'BD U6M'!A:A,'BD U6M'!E:E) -> 15395.307 | AC13: =_xlfn.XLOOKUP(A13,'BD UM'!A:A,'BD UM'!F:F) -> 81946.027 | AD13: =_xlfn.XLOOKUP(A13,'BD U6M'!A:A,'BD U6M'!F:F) -> 84952.666 | AE13: =_xlfn.XLOOKUP(A13,'BD UM'!A:A,'BD UM'!G:G) -> 11056.52 | AF13: =_xlfn.XLOOKUP(A13,'BD U6M'!A:A,'BD U6M'!G:G) -> 10806.189 | AG13: =_xlfn.XLOOKUP(A13,'BD UM'!A:A,'BD UM'!H:H) -> 0 | AH13: COMERCIO/SERVICIO | AI13: ABIERTA | AJ13: BASE | AK13: EXP 2024 | AL13: 232000 | AM13: 87.67 | AN13: Cedritos | AO13: Medio
A14: 505DL | B14: Oriente | C14: Santander | D14: Bucaramanga | E14: ORIENTAL | F14: 4 | G14: Agustin | H14: 0 | I14: Esquinero | J14: 76.05 | K14: 2 | L14: 2 | M14: 0 | N14: 43637 | O14: 21 | P14: 10 | Q14: 30 | R14: 86 | S14: 6.1474794 | T14: -75.616317 | U14: =_xlfn.XLOOKUP(A14,'BD UM'!A:A,'BD UM'!B:B) -> 16104 | V14: =_xlfn.XLOOKUP(A14,'BD U6M'!A:A,'BD U6M'!B:B) -> 15640 | W14: =_xlfn.XLOOKUP(A14,'BD UM'!A:A,'BD UM'!C:C) -> 9686.7 | X14: =_xlfn.XLOOKUP(A14,'BD U6M'!A:A,'BD U6M'!C:C) -> 10059.9 | Y14: =_xlfn.XLOOKUP(A14,'BD UM'!A:A,'BD UM'!D:D) -> 155994.16 | Z14: =_xlfn.XLOOKUP(A14,'BD U6M'!A:A,'BD U6M'!D:D) -> 157336.07 | AA14: =_xlfn.XLOOKUP(A14,'BD UM'!A:A,'BD UM'!E:E) -> 1763.756 | AB14: =_xlfn.XLOOKUP(A14,'BD U6M'!A:A,'BD U6M'!E:E) -> 9139.4587 | AC14: =_xlfn.XLOOKUP(A14,'BD UM'!A:A,'BD UM'!F:F) -> 57080.948 | AD14: =_xlfn.XLOOKUP(A14,'BD U6M'!A:A,'BD U6M'!F:F) -> 57716.038 | AE14: =_xlfn.XLOOKUP(A14,'BD UM'!A:A,'BD UM'!G:G) -> 4814.108 | AF14: =_xlfn.XLOOKUP(A14,'BD U6M'!A:A,'BD U6M'!G:G) -> 4798.8428 | AG14: =_xlfn.XLOOKUP(A14,'BD UM'!A:A,'BD UM'!H:H) -> 0 | AH14: COMERCIO/SERVICIO | AI14: ABIERTA | AJ14: RECESO | AK14: TMCB | AL14: 232000 | AM14: 63.09 | AN14: PT | AO14: Medio
A15: 50T5A | B15: Centro Norte | C15: Boyacá | D15: Tunja | E15: NORTE (1) | F15: 4 | G15: Alameda De Unicentro | H15: 0 | I15: Esquinero | J15: 148 | K15: 1 | L15: 474 | M15: 71 | N15: 45412 | O15: 30 | P15: 1 | Q15: 30 | R15: 28 | S15: 5.5479207 | T15: -73.346477 | U15: =_xlfn.XLOOKUP(A15,'BD UM'!A:A,'BD UM'!B:B) -> 15656 | V15: =_xlfn.XLOOKUP(A15,'BD U6M'!A:A,'BD U6M'!B:B) -> 14237.5 | W15: =_xlfn.XLOOKUP(A15,'BD UM'!A:A,'BD UM'!C:C) -> 12949.7 | X15: =_xlfn.XLOOKUP(A15,'BD U6M'!A:A,'BD U6M'!C:C) -> 13545.4 | Y15: =_xlfn.XLOOKUP(A15,'BD UM'!A:A,'BD UM'!D:D) -> 202740.21 | Z15: =_xlfn.XLOOKUP(A15,'BD U6M'!A:A,'BD U6M'!D:D) -> 192852.15 | AA15: =_xlfn.XLOOKUP(A15,'BD UM'!A:A,'BD UM'!E:E) -> 13181.916 | AB15: =_xlfn.XLOOKUP(A15,'BD U6M'!A:A,'BD U6M'!E:E) -> 10651.653 | AC15: =_xlfn.XLOOKUP(A15,'BD UM'!A:A,'BD UM'!F:F) -> 71107.855 | AD15: =_xlfn.XLOOKUP(A15,'BD U6M'!A:A,'BD U6M'!F:F) -> 68661.933 | AE15: =_xlfn.XLOOKUP(A15,'BD UM'!A:A,'BD UM'!G:G) -> 9151.066 | AF15: =_xlfn.XLOOKUP(A15,'BD U6M'!A:A,'BD U6M'!G:G) -> 9164.1217 | AG15: =_xlfn.XLOOKUP(A15,'BD UM'!A:A,'BD UM'!H:H) -> 0 | AH15: EDUCACION | AI15: ABIERTA | AJ15: BASE | AK15: TMCB | AL15: 232000 | AM15: 61.83 | AN15: Portal Javeriana | AO15: Medio
A16: 50UPU | B16: Centro Sur | C16: Distrito Capital | D16: Bogotá | E16: BOYACA REAL | F16: 3 | G16: Alamos 90 | H16: MAYRA ALEJANDRA ARIZA JIMENEZ y MIGUEL ANGEL ARIZA JIMENEZ | I16: Esquinero | J16: 98.6 | K16: 3149 | L16: 105 | M16: 106 | N16: 45770 | O16: 23 | P16: 8 | Q16: 30 | R16: 16 | S16: 4.695583 | T16: -74.110236 | U16: =_xlfn.XLOOKUP(A16,'BD UM'!A:A,'BD UM'!B:B) -> 17621 | V16: =_xlfn.XLOOKUP(A16,'BD U6M'!A:A,'BD U6M'!B:B) -> 17516.667 | W16: =_xlfn.XLOOKUP(A16,'BD UM'!A:A,'BD UM'!C:C) -> 12035.9 | X16: =_xlfn.XLOOKUP(A16,'BD U6M'!A:A,'BD U6M'!C:C) -> 11979.1 | Y16: =_xlfn.XLOOKUP(A16,'BD UM'!A:A,'BD UM'!D:D) -> 212085.27 | Z16: =_xlfn.XLOOKUP(A16,'BD U6M'!A:A,'BD U6M'!D:D) -> 209833.43 | AA16: =_xlfn.XLOOKUP(A16,'BD UM'!A:A,'BD UM'!E:E) -> 14067.499 | AB16: =_xlfn.XLOOKUP(A16,'BD U6M'!A:A,'BD U6M'!E:E) -> 13948.008 | AC16: =_xlfn.XLOOKUP(A16,'BD UM'!A:A,'BD UM'!F:F) -> 66113.363 | AD16: =_xlfn.XLOOKUP(A16,'BD U6M'!A:A,'BD U6M'!F:F) -> 65631.033 | AE16: =_xlfn.XLOOKUP(A16,'BD UM'!A:A,'BD UM'!G:G) -> 7882.5 | AF16: =_xlfn.XLOOKUP(A16,'BD U6M'!A:A,'BD U6M'!G:G) -> 7902.5332 | AG16: =_xlfn.XLOOKUP(A16,'BD UM'!A:A,'BD UM'!H:H) -> 1.4606 | AH16: ALTA DENSIDAD | AI16: ABIERTA | AJ16: HOGAR | AK16: EXP 2025 | AL16: 241405 | AM16: 79.95 | AN16: Trinidad Galan | AO16: Bajo
A17: 50FZH | B17: Centro Sur | C17: Distrito Capital | D17: Bogotá | E17: ALAMOS | F17: 3 | G17: Alamos Industrial | H17: 0 | I17: Esquinero | J17: 157.95 | K17: 0 | L17: 5400 | M17: 52 | N17: 45168 | O17: 30 | P17: 2 | Q17: 31 | R17: 36 | S17: 4.6900555 | T17: -74.117545 | U17: =_xlfn.XLOOKUP(A17,'BD UM'!A:A,'BD UM'!B:B) -> 16578 | V17: =_xlfn.XLOOKUP(A17,'BD U6M'!A:A,'BD U6M'!B:B) -> 17073.833 | W17: =_xlfn.XLOOKUP(A17,'BD UM'!A:A,'BD UM'!C:C) -> 11756.7 | X17: =_xlfn.XLOOKUP(A17,'BD U6M'!A:A,'BD U6M'!C:C) -> 10774.8 | Y17: =_xlfn.XLOOKUP(A17,'BD UM'!A:A,'BD UM'!D:D) -> 194901.99 | Z17: =_xlfn.XLOOKUP(A17,'BD U6M'!A:A,'BD U6M'!D:D) -> 183967.49 | AA17: =_xlfn.XLOOKUP(A17,'BD UM'!A:A,'BD UM'!E:E) -> 16836.768 | AB17: =_xlfn.XLOOKUP(A17,'BD U6M'!A:A,'BD U6M'!E:E) -> 13801.752 | AC17: =_xlfn.XLOOKUP(A17,'BD UM'!A:A,'BD UM'!F:F) -> 69852.446 | AD17: =_xlfn.XLOOKUP(A17,'BD U6M'!A:A,'BD U6M'!F:F) -> 67972.798 | AE17: =_xlfn.XLOOKUP(A17,'BD UM'!A:A,'BD UM'!G:G) -> 9786.877 | AF17: =_xlfn.XLOOKUP(A17,'BD U6M'!A:A,'BD U6M'!G:G) -> 9530.5266 | AG17: =_xlfn.XLOOKUP(A17,'BD UM'!A:A,'BD UM'!H:H) -> 0 | AH17: ADMINISTRATIVO | AI17: ABIERTA | AJ17: RECESO | AK17: TMCB | AL17: 204160 | AM17: 58.96 | AN17: Zona Franca | AO17: Medio
A18: 50IOP | B18: Centro Norte | C18: Distrito Capital | D18: Bogotá | E18: EL PRADO | F18: 3 | G18: Alcala | H18: 0 | I18: Esquinero | J18: 112.03 | K18: 1080 | L18: 1240 | M18: 138 | N18: 45199 | O18: 30 | P18: 1 | Q18: 30 | R18: 35 | S18: 4.7228338 | T18: -74.051648 | U18: =_xlfn.XLOOKUP(A18,'BD UM'!A:A,'BD UM'!B:B) -> 17087 | V18: =_xlfn.XLOOKUP(A18,'BD U6M'!A:A,'BD U6M'!B:B) -> 16886.167 | W18: =_xlfn.XLOOKUP(A18,'BD UM'!A:A,'BD UM'!C:C) -> 11199.9 | X18: =_xlfn.XLOOKUP(A18,'BD U6M'!A:A,'BD U6M'!C:C) -> 11410.1 | Y18: =_xlfn.XLOOKUP(A18,'BD UM'!A:A,'BD UM'!D:D) -> 191372.06 | Z18: =_xlfn.XLOOKUP(A18,'BD U6M'!A:A,'BD U6M'!D:D) -> 192673.52 | AA18: =_xlfn.XLOOKUP(A18,'BD UM'!A:A,'BD UM'!E:E) -> 10507.289 | AB18: =_xlfn.XLOOKUP(A18,'BD U6M'!A:A,'BD U6M'!E:E) -> 9823.5799 | AC18: =_xlfn.XLOOKUP(A18,'BD UM'!A:A,'BD UM'!F:F) -> 67267.439 | AD18: =_xlfn.XLOOKUP(A18,'BD U6M'!A:A,'BD U6M'!F:F) -> 66433.983 | AE18: =_xlfn.XLOOKUP(A18,'BD UM'!A:A,'BD UM'!G:G) -> 7185.16 | AF18: =_xlfn.XLOOKUP(A18,'BD U6M'!A:A,'BD U6M'!G:G) -> 7264.4969 | AG18: =_xlfn.XLOOKUP(A18,'BD UM'!A:A,'BD UM'!H:H) -> 0 | AH18: COMERCIO/SERVICIO | AI18: ABIERTA | AJ18: BASE | AK18: TMCB | AL18: 232000 | AM18: 64.13 | AN18: Rionegro | AO18: Medio
A19: 503Z7 | B19: Oriente | C19: Santander | D19: Piedecuesta | E19: PIEDECUESTA | F19: 6 | G19: Aldea Comercial | H19: 0 | I19: Medianero | J19: 95.42 | K19: 1652 | L19: 489 | M19: 216 | N19: 45377 | O19: 26 | P19: 6 | Q19: 31 | R19: 29 | S19: 7.0236593 | T19: -73.082625 | U19: =_xlfn.XLOOKUP(A19,'BD UM'!A:A,'BD UM'!B:B) -> 10617 | V19: =_xlfn.XLOOKUP(A19,'BD U6M'!A:A,'BD U6M'!B:B) -> 9694 | W19: =_xlfn.XLOOKUP(A19,'BD UM'!A:A,'BD UM'!C:C) -> 13453.8 | X19: =_xlfn.XLOOKUP(A19,'BD U6M'!A:A,'BD U6M'!C:C) -> 14751.5 | Y19: =_xlfn.XLOOKUP(A19,'BD UM'!A:A,'BD UM'!D:D) -> 142838.67 | Z19: =_xlfn.XLOOKUP(A19,'BD U6M'!A:A,'BD U6M'!D:D) -> 143000.93 | AA19: =_xlfn.XLOOKUP(A19,'BD UM'!A:A,'BD UM'!E:E) -> 5666.403 | AB19: =_xlfn.XLOOKUP(A19,'BD U6M'!A:A,'BD U6M'!E:E) -> 4523.284 | AC19: =_xlfn.XLOOKUP(A19,'BD UM'!A:A,'BD UM'!F:F) -> 55731.84 | AD19: =_xlfn.XLOOKUP(A19,'BD U6M'!A:A,'BD U6M'!F:F) -> 57017.756 | AE19: =_xlfn.XLOOKUP(A19,'BD UM'!A:A,'BD UM'!G:G) -> 8077.396 | AF19: =_xlfn.XLOOKUP(A19,'BD U6M'!A:A,'BD U6M'!G:G) -> 8215.5747 | AG19: =_xlfn.XLOOKUP(A19,'BD UM'!A:A,'BD UM'!H:H) -> 0 | AH19: BAJA DENSIDAD | AI19: ABIERTA | AJ19: HOGAR | AK19: TMCB | AL19: 241405 | AM19: 84.65 | AN19: Pista Aeropuerto | AO19: Medio
A20: 50K6C | B20: Centro Sur | C20: Distrito Capital | D20: Bogotá | E20: GALERIAS | F20: 3 | G20: Alfonso Lopez | H20: ADMINISTRACIÓN Y ABASTECIMIENTO S.A.S. | I20: Esquinero | J20: 112.28 | K20: 1986 | L20: 1180 | M20: 49 | N20: 45747 | O20: 31 | P20: 1 | Q20: 31 | R20: 17 | S20: 6.2524725 | T20: -75.587859 | U20: =_xlfn.XLOOKUP(A20,'BD UM'!A:A,'BD UM'!B:B) -> 20223 | V20: =_xlfn.XLOOKUP(A20,'BD U6M'!A:A,'BD U6M'!B:B) -> 18255.167 | W20: =_xlfn.XLOOKUP(A20,'BD UM'!A:A,'BD UM'!C:C) -> 11271.8 | X20: =_xlfn.XLOOKUP(A20,'BD U6M'!A:A,'BD U6M'!C:C) -> 11584.4 | Y20: =_xlfn.XLOOKUP(A20,'BD UM'!A:A,'BD UM'!D:D) -> 227949.72 | Z20: =_xlfn.XLOOKUP(A20,'BD U6M'!A:A,'BD U6M'!D:D) -> 211475.91 | AA20: =_xlfn.XLOOKUP(A20,'BD UM'!A:A,'BD UM'!E:E) -> 13853.039 | AB20: =_xlfn.XLOOKUP(A20,'BD U6M'!A:A,'BD U6M'!E:E) -> 15408.897 | AC20: =_xlfn.XLOOKUP(A20,'BD UM'!A:A,'BD UM'!F:F) -> 67104.989 | AD20: =_xlfn.XLOOKUP(A20,'BD U6M'!A:A,'BD U6M'!F:F) -> 68591.339 | AE20: =_xlfn.XLOOKUP(A20,'BD UM'!A:A,'BD UM'!G:G) -> 10510 | AF20: =_xlfn.XLOOKUP(A20,'BD U6M'!A:A,'BD U6M'!G:G) -> 10611.425 | AG20: =_xlfn.XLOOKUP(A20,'BD UM'!A:A,'BD UM'!H:H) -> 1.4458 | AH20: COMERCIO/SERVICIO | AI20: ABIERTA | AJ20: BASE | AK20: EXP 2025 | AL20: 232000 | AM20: 93.61 | AN20: La Estrella 1 | AO20: Medio
A21: 50HZJ | B21: Occidente | C21: Antioquia | D21: Medellín | E21: LA CANDELARIA | F21: 4 | G21: Almacentro | H21: ALIANZA FIDUCIARIA - FIDEICOMISO ALMACENTRO INVERAL | I21: Esquinero | J21: 163.44 | K21: 0 | L21: 2459 | M21: 58 | N21: 45534 | O21: 30 | P21: 2 | Q21: 31 | R21: 24 | S21: 6.2357045 | T21: -75.570384 | U21: =_xlfn.XLOOKUP(A21,'BD UM'!A:A,'BD UM'!B:B) -> 23177 | V21: =_xlfn.XLOOKUP(A21,'BD U6M'!A:A,'BD U6M'!B:B) -> 21239.667 | W21: =_xlfn.XLOOKUP(A21,'BD UM'!A:A,'BD UM'!C:C) -> 9228.2 | X21: =_xlfn.XLOOKUP(A21,'BD U6M'!A:A,'BD U6M'!C:C) -> 9365 | Y21: =_xlfn.XLOOKUP(A21,'BD UM'!A:A,'BD UM'!D:D) -> 213880.96 | Z21: =_xlfn.XLOOKUP(A21,'BD U6M'!A:A,'BD U6M'!D:D) -> 198908.56 | AA21: =_xlfn.XLOOKUP(A21,'BD UM'!A:A,'BD UM'!E:E) -> 18269.134 | AB21: =_xlfn.XLOOKUP(A21,'BD U6M'!A:A,'BD U6M'!E:E) -> 14099.37 | AC21: =_xlfn.XLOOKUP(A21,'BD UM'!A:A,'BD UM'!F:F) -> 87293.543 | AD21: =_xlfn.XLOOKUP(A21,'BD U6M'!A:A,'BD U6M'!F:F) -> 79844.559 | AE21: =_xlfn.XLOOKUP(A21,'BD UM'!A:A,'BD UM'!G:G) -> 14212.166 | AF21: =_xlfn.XLOOKUP(A21,'BD U6M'!A:A,'BD U6M'!G:G) -> 14067.377 | AG21: =_xlfn.XLOOKUP(A21,'BD UM'!A:A,'BD UM'!H:H) -> 0 | AH21: COMERCIO/SERVICIO | AI21: ABIERTA | AJ21: RECESO | AK21: EXP 2024 | AL21: 204160 | AM21: 83.96 | AN21: Morato | AO21: Alto
A22: 50L8W | B22: Oriente | C22: Santander | D22: Bucaramanga | E22: ORIENTAL | F22: 3 | G22: Alonso Calle 19 | H22: 0 | I22: Esquinero | J22: 167.2 | K22: 2243 | L22: 76 | M22: 92 | N22: 45230 | O22: 31 | P22: 1 | Q22: 31 | R22: 34 | S22: 7.1312944 | T22: -73.115113 | U22: =_xlfn.XLOOKUP(A22,'BD UM'!A:A,'BD UM'!B:B) -> 18866 | V22: =_xlfn.XLOOKUP(A22,'BD U6M'!A:A,'BD U6M'!B:B) -> 17279 | W22: =_xlfn.XLOOKUP(A22,'BD UM'!A:A,'BD UM'!C:C) -> 10880.4 | X22: =_xlfn.XLOOKUP(A22,'BD U6M'!A:A,'BD U6M'!C:C) -> 11110.9 | Y22: =_xlfn.XLOOKUP(A22,'BD UM'!A:A,'BD UM'!D:D) -> 205268.89 | Z22: =_xlfn.XLOOKUP(A22,'BD U6M'!A:A,'BD U6M'!D:D) -> 191985.4 | AA22: =_xlfn.XLOOKUP(A22,'BD UM'!A:A,'BD UM'!E:E) -> 12984.094 | AB22: =_xlfn.XLOOKUP(A22,'BD U6M'!A:A,'BD U6M'!E:E) -> 13462.743 | AC22: =_xlfn.XLOOKUP(A22,'BD UM'!A:A,'BD UM'!F:F) -> 74786.325 | AD22: =_xlfn.XLOOKUP(A22,'BD U6M'!A:A,'BD U6M'!F:F) -> 69370.853 | AE22: =_xlfn.XLOOKUP(A22,'BD UM'!A:A,'BD UM'!G:G) -> 8047.379 | AF22: =_xlfn.XLOOKUP(A22,'BD U6M'!A:A,'BD U6M'!G:G) -> 8133.9457 | AG22: =_xlfn.XLOOKUP(A22,'BD UM'!A:A,'BD UM'!H:H) -> 0 | AH22: ALTA DENSIDAD | AI22: ABIERTA | AJ22: HOGAR | AK22: TMCB | AL22: 241405 | AM22: 48.13 | AN22: San Alonso | AO22: Medio
A23: 50SKG | B23: Centro Sur | C23: Distrito Capital | D23: Bogotá | E23: CASTILLA | F23: 3 | G23: Alsacia | H23: 0 | I23: Esquinero | J23: 119.06 | K23: 4224 | L23: 1630 | M23: 0 | N23: 44670 | O23: 19 | P23: 12 | Q23: 30 | R23: 52 | S23: 4.6481631 | T23: -74.134948 | U23: =_xlfn.XLOOKUP(A23,'BD UM'!A:A,'BD UM'!B:B) -> 21634 | V23: =_xlfn.XLOOKUP(A23,'BD U6M'!A:A,'BD U6M'!B:B) -> 21456.167 | W23: =_xlfn.XLOOKUP(A23,'BD UM'!A:A,'BD UM'!C:C) -> 15356.6 | X23: =_xlfn.XLOOKUP(A23,'BD U6M'!A:A,'BD U6M'!C:C) -> 15349.4 | Y23: =_xlfn.XLOOKUP(A23,'BD UM'!A:A,'BD UM'!D:D) -> 332225.11 | Z23: =_xlfn.XLOOKUP(A23,'BD U6M'!A:A,'BD U6M'!D:D) -> 329338.75 | AA23: =_xlfn.XLOOKUP(A23,'BD UM'!A:A,'BD UM'!E:E) -> 41656.004 | AB23: =_xlfn.XLOOKUP(A23,'BD U6M'!A:A,'BD U6M'!E:E) -> 40855.583 | AC23: =_xlfn.XLOOKUP(A23,'BD UM'!A:A,'BD UM'!F:F) -> 114004.32 | AD23: =_xlfn.XLOOKUP(A23,'BD U6M'!A:A,'BD U6M'!F:F) -> 109896.26 | AE23: =_xlfn.XLOOKUP(A23,'BD UM'!A:A,'BD UM'!G:G) -> 10250.848 | AF23: =_xlfn.XLOOKUP(A23,'BD U6M'!A:A,'BD U6M'!G:G) -> 10355.891 | AG23: =_xlfn.XLOOKUP(A23,'BD UM'!A:A,'BD UM'!H:H) -> 0 | AH23: ALTA DENSIDAD | AI23: ABIERTA | AJ23: HOGAR | AK23: TMCB | AL23: 241405 | AM23: 86.1 | AN23: Bonavista | AO23: Medio
A24: 50P88 | B24: Occidente | C24: Caldas | D24: Manizales | E24: ECOTURISTICO CERRO DE ORO | F24: 4 | G24: Alta Suiza | H24: LUZ CLEMENCIA SALAZAR RAMÍREZ, | I24: Medianero | J24: 125.27 | K24: 1922 | L24: 781 | M24: 56 | N24: 45590 | O24: 25 | P24: 7 | Q24: 31 | R24: 22 | S24: 5.0493157 | T24: -75.479528 | U24: =_xlfn.XLOOKUP(A24,'BD UM'!A:A,'BD UM'!B:B) -> 16621 | V24: =_xlfn.XLOOKUP(A24,'BD U6M'!A:A,'BD U6M'!B:B) -> 15438.167 | W24: =_xlfn.XLOOKUP(A24,'BD UM'!A:A,'BD UM'!C:C) -> 14834.6 | X24: =_xlfn.XLOOKUP(A24,'BD U6M'!A:A,'BD U6M'!C:C) -> 14403.6 | Y24: =_xlfn.XLOOKUP(A24,'BD UM'!A:A,'BD UM'!D:D) -> 246565.76 | Z24: =_xlfn.XLOOKUP(A24,'BD U6M'!A:A,'BD U6M'!D:D) -> 222364.98 | AA24: =_xlfn.XLOOKUP(A24,'BD UM'!A:A,'BD UM'!E:E) -> 22953.75 | AB24: =_xlfn.XLOOKUP(A24,'BD U6M'!A:A,'BD U6M'!E:E) -> 28595.254 | AC24: =_xlfn.XLOOKUP(A24,'BD UM'!A:A,'BD UM'!F:F) -> 94562.339 | AD24: =_xlfn.XLOOKUP(A24,'BD U6M'!A:A,'BD U6M'!F:F) -> 88667.603 | AE24: =_xlfn.XLOOKUP(A24,'BD UM'!A:A,'BD UM'!G:G) -> 7695 | AF24: =_xlfn.XLOOKUP(A24,'BD U6M'!A:A,'BD U6M'!G:G) -> 7942.7471 | AG24: =_xlfn.XLOOKUP(A24,'BD UM'!A:A,'BD UM'!H:H) -> 0 | AH24: COMERCIO/SERVICIO | AI24: ABIERTA | AJ24: BASE | AK24: EXP 2024 | AL24: 232000 | AM24: 62.98 | AN24: Junin | AO24: Medio
A25: 50PT8 | B25: Occidente | C25: Quindío | D25: Armenia | E25: EL CAFETERO | F25: 3 | G25: Altavista | H25: 0 | I25: Esquinero | J25: 97.07 | K25: 587 | L25: 3650 | M25: 56 | N25: 45377 | O25: 26 | P25: 6 | Q25: 31 | R25: 29 | S25: 4.5326893 | T25: -75.672029 | U25: =_xlfn.XLOOKUP(A25,'BD UM'!A:A,'BD UM'!B:B) -> 18888 | V25: =_xlfn.XLOOKUP(A25,'BD U6M'!A:A,'BD U6M'!B:B) -> 19783.833 | W25: =_xlfn.XLOOKUP(A25,'BD UM'!A:A,'BD UM'!C:C) -> 10080.9 | X25: =_xlfn.XLOOKUP(A25,'BD U6M'!A:A,'BD U6M'!C:C) -> 10417.2 | Y25: =_xlfn.XLOOKUP(A25,'BD UM'!A:A,'BD UM'!D:D) -> 190407.33 | Z25: =_xlfn.XLOOKUP(A25,'BD U6M'!A:A,'BD U6M'!D:D) -> 206092.97 | AA25: =_xlfn.XLOOKUP(A25,'BD UM'!A:A,'BD UM'!E:E) -> -6007.63 | AB25: =_xlfn.XLOOKUP(A25,'BD U6M'!A:A,'BD U6M'!E:E) -> 14772.491 | AC25: =_xlfn.XLOOKUP(A25,'BD UM'!A:A,'BD UM'!F:F) -> 74975.913 | AD25: =_xlfn.XLOOKUP(A25,'BD U6M'!A:A,'BD U6M'!F:F) -> 80156.934 | AE25: =_xlfn.XLOOKUP(A25,'BD UM'!A:A,'BD UM'!G:G) -> 9950.868 | AF25: =_xlfn.XLOOKUP(A25,'BD U6M'!A:A,'BD U6M'!G:G) -> 10052.634 | AG25: =_xlfn.XLOOKUP(A25,'BD UM'!A:A,'BD UM'!H:H) -> 0 | AH25: ADMINISTRATIVO | AI25: ABIERTA | AJ25: RECESO | AK25: TMCB | AL25: 204160 | AM25: 102.51 | AN25: Esmeralda | AO25: Alto
A26: 50L9T | B26: Norte | C26: Atlántico | D26: Barranquilla | E26: CENTRO HISTORICO | F26: 4 | G26: Alto Prado 76 | H26: H.U.B. SOLUCIONES INMOBILIARIAS S.A.S. | I26: Esquinero | J26: 145.99 | K26: 1086 | L26: 1055 | M26: 38 | N26: 45590 | O26: 25 | P26: 7 | Q26: 31 | R26: 22 | S26: 11.000576 | T26: -74.808289 | U26: =_xlfn.XLOOKUP(A26,'BD UM'!A:A,'BD UM'!B:B) -> 17728 | V26: =_xlfn.XLOOKUP(A26,'BD U6M'!A:A,'BD U6M'!B:B) -> 16446.833 | W26: =_xlfn.XLOOKUP(A26,'BD UM'!A:A,'BD UM'!C:C) -> 11408.5 | X26: =_xlfn.XLOOKUP(A26,'BD U6M'!A:A,'BD U6M'!C:C) -> 11312.4 | Y26: =_xlfn.XLOOKUP(A26,'BD UM'!A:A,'BD UM'!D:D) -> 202249.98 | Z26: =_xlfn.XLOOKUP(A26,'BD U6M'!A:A,'BD U6M'!D:D) -> 186053.13 | AA26: =_xlfn.XLOOKUP(A26,'BD UM'!A:A,'BD UM'!E:E) -> 10506.59 | AB26: =_xlfn.XLOOKUP(A26,'BD U6M'!A:A,'BD U6M'!E:E) -> 8558.2409 | AC26: =_xlfn.XLOOKUP(A26,'BD UM'!A:A,'BD UM'!F:F) -> 76424.28 | AD26: =_xlfn.XLOOKUP(A26,'BD U6M'!A:A,'BD U6M'!F:F) -> 69786.005 | AE26: =_xlfn.XLOOKUP(A26,'BD UM'!A:A,'BD UM'!G:G) -> 9468 | AF26: =_xlfn.XLOOKUP(A26,'BD U6M'!A:A,'BD U6M'!G:G) -> 9566.4788 | AG26: =_xlfn.XLOOKUP(A26,'BD UM'!A:A,'BD UM'!H:H) -> 0 | AH26: ADMINISTRATIVO | AI26: ABIERTA | AJ26: BASE | AK26: EXP 2024 | AL26: 232000 | AM26: 64.85 | AN26: 140 | AO26: Medio
A27: 50YHD | B27: Oriente | C27: Santander | D27: Bucaramanga | E27: CABECERA DEL LLANO | F27: 5 | G27: Altos De Cabecera 2 | H27: 0 | I27: Esquinero | J27: 78.85 | K27: 1464 | L27: 2130 | M27: 187 | N27: 45350 | O27: 28 | P27: 2 | Q27: 29 | R27: 30 | S27: 7.1212495 | T27: -73.110151 | U27: =_xlfn.XLOOKUP(A27,'BD UM'!A:A,'BD UM'!B:B) -> 22770 | V27: =_xlfn.XLOOKUP(A27,'BD U6M'!A:A,'BD U6M'!B:B) -> 21353.667 | W27: =_xlfn.XLOOKUP(A27,'BD UM'!A:A,'BD UM'!C:C) -> 10130.1 | X27: =_xlfn.XLOOKUP(A27,'BD U6M'!A:A,'BD U6M'!C:C) -> 10423.5 | Y27: =_xlfn.XLOOKUP(A27,'BD UM'!A:A,'BD UM'!D:D) -> 230662.79 | Z27: =_xlfn.XLOOKUP(A27,'BD U6M'!A:A,'BD U6M'!D:D) -> 222580.43 | AA27: =_xlfn.XLOOKUP(A27,'BD UM'!A:A,'BD UM'!E:E) -> 21651.656 | AB27: =_xlfn.XLOOKUP(A27,'BD U6M'!A:A,'BD U6M'!E:E) -> 22875.005 | AC27: =_xlfn.XLOOKUP(A27,'BD UM'!A:A,'BD UM'!F:F) -> 90718.378 | AD27: =_xlfn.XLOOKUP(A27,'BD U6M'!A:A,'BD U6M'!F:F) -> 86946.48 | AE27: =_xlfn.XLOOKUP(A27,'BD UM'!A:A,'BD UM'!G:G) -> 10504 | AF27: =_xlfn.XLOOKUP(A27,'BD U6M'!A:A,'BD U6M'!G:G) -> 10611.166 | AG27: =_xlfn.XLOOKUP(A27,'BD UM'!A:A,'BD UM'!H:H) -> 0 | AH27: ADMINISTRATIVO | AI27: ABIERTA | AJ27: BASE | AK27: TMCB | AL27: 232000 | AM27: 133.21 | AN27: Sotomayor | AO27: Alto
A28: 50Y4E | B28: Centro Sur | C28: Cundinamarca | D28: Madrid | E28: MADRID | F28: 3 | G28: Altos Del Ciclista | H28: RICARDO JUNCA GARZON | I28: Esquinero | J28: 127.82 | K28: 134 | L28: 1253 | M28: 115 | N28: 45510 | O28: 6 | P28: 26 | Q28: 31 | R28: 24 | S28: 4.8154064 | T28: -74.222889 | U28: =_xlfn.XLOOKUP(A28,'BD UM'!A:A,'BD UM'!B:B) -> 11410 | V28: =_xlfn.XLOOKUP(A28,'BD U6M'!A:A,'BD U6M'!B:B) -> 11328.5 | W28: =_xlfn.XLOOKUP(A28,'BD UM'!A:A,'BD UM'!C:C) -> 15005.4 | X28: =_xlfn.XLOOKUP(A28,'BD U6M'!A:A,'BD U6M'!C:C) -> 15380.3 | Y28: =_xlfn.XLOOKUP(A28,'BD UM'!A:A,'BD UM'!D:D) -> 171211.57 | Z28: =_xlfn.XLOOKUP(A28,'BD U6M'!A:A,'BD U6M'!D:D) -> 174235.29 | AA28: =_xlfn.XLOOKUP(A28,'BD UM'!A:A,'BD UM'!E:E) -> 11439.399 | AB28: =_xlfn.XLOOKUP(A28,'BD U6M'!A:A,'BD U6M'!E:E) -> 7479.0417 | AC28: =_xlfn.XLOOKUP(A28,'BD UM'!A:A,'BD UM'!F:F) -> 65210.841 | AD28: =_xlfn.XLOOKUP(A28,'BD U6M'!A:A,'BD U6M'!F:F) -> 64739.497 | AE28: =_xlfn.XLOOKUP(A28,'BD UM'!A:A,'BD UM'!G:G) -> 6831.5 | AF28: =_xlfn.XLOOKUP(A28,'BD U6M'!A:A,'BD U6M'!G:G) -> 6723.0514 | AG28: =_xlfn.XLOOKUP(A28,'BD UM'!A:A,'BD UM'!H:H) -> 0 | AH28: TRANSPORTE | AI28: ABIERTA | AJ28: RECESO | AK28: EXP 2024 | AL28: 204160 | AM28: 52.67 | AN28: Giron El Poblado | AO28: Medio
A29: 501YH | B29: Centro Sur | C29: Distrito Capital | D29: Bogotá | E29: AMERICAS | F29: 3 | G29: America Occidental | H29: CALZADO DE LA SABANA S.A.S. | I29: Medianero | J29: 116.55 | K29: 622 | L29: 2103 | M29: 0 | N29: 43535 | O29: 11 | P29: 21 | Q29: 31 | R29: 89 | S29: 4.6185998 | T29: -74.1385 | U29: =_xlfn.XLOOKUP(A29,'BD UM'!A:A,'BD UM'!B:B) -> 18695 | V29: =_xlfn.XLOOKUP(A29,'BD U6M'!A:A,'BD U6M'!B:B) -> 18560 | W29: =_xlfn.XLOOKUP(A29,'BD UM'!A:A,'BD UM'!C:C) -> 11297.3 | X29: =_xlfn.XLOOKUP(A29,'BD U6M'!A:A,'BD U6M'!C:C) -> 11156.7 | Y29: =_xlfn.XLOOKUP(A29,'BD UM'!A:A,'BD UM'!D:D) -> 211202.33 | Z29: =_xlfn.XLOOKUP(A29,'BD U6M'!A:A,'BD U6M'!D:D) -> 207067.64 | AA29: =_xlfn.XLOOKUP(A29,'BD UM'!A:A,'BD UM'!E:E) -> 9623.01 | AB29: =_xlfn.XLOOKUP(A29,'BD U6M'!A:A,'BD U6M'!E:E) -> 9837.3472 | AC29: =_xlfn.XLOOKUP(A29,'BD UM'!A:A,'BD UM'!F:F) -> 69830.896 | AD29: =_xlfn.XLOOKUP(A29,'BD U6M'!A:A,'BD U6M'!F:F) -> 67793.063 | AE29: =_xlfn.XLOOKUP(A29,'BD UM'!A:A,'BD UM'!G:G) -> 12270.539 | AF29: =_xlfn.XLOOKUP(A29,'BD U6M'!A:A,'BD U6M'!G:G) -> 12392.518 | AG29: =_xlfn.XLOOKUP(A29,'BD UM'!A:A,'BD UM'!H:H) -> 0 | AH29: COMERCIO/SERVICIO | AI29: ABIERTA | AJ29: BASE | AK29: TMCB | AL29: 232000 | AM29: 105.29 | AN29: Chapinero | AO29: Medio
A30: 50LTJ | B30: Centro Sur | C30: Distrito Capital | D30: Bogotá | E30: PUENTE ARANDA | F30: 3 | G30: Américas | H30: SI SISTEMA INTEGRAL INMOBILIARIO S.A.S. | I30: Medianero | J30: 122.76 | K30: 0 | L30: 5900 | M30: 77 | N30: 45899 | O30: 30 | P30: 2 | Q30: 31 | R30: 12 | S30: 4.6299456 | T30: -74.110935 | U30: =_xlfn.XLOOKUP(A30,'BD UM'!A:A,'BD UM'!B:B) -> 19234 | V30: =_xlfn.XLOOKUP(A30,'BD U6M'!A:A,'BD U6M'!B:B) -> 19762.833 | W30: =_xlfn.XLOOKUP(A30,'BD UM'!A:A,'BD UM'!C:C) -> 10064.9 | X30: =_xlfn.XLOOKUP(A30,'BD U6M'!A:A,'BD U6M'!C:C) -> 10409 | Y30: =_xlfn.XLOOKUP(A30,'BD UM'!A:A,'BD UM'!D:D) -> 193588.4 | Z30: =_xlfn.XLOOKUP(A30,'BD U6M'!A:A,'BD U6M'!D:D) -> 205712.05 | AA30: =_xlfn.XLOOKUP(A30,'BD UM'!A:A,'BD UM'!E:E) -> 19846.903 | AB30: =_xlfn.XLOOKUP(A30,'BD U6M'!A:A,'BD U6M'!E:E) -> 22823.348 | AC30: =_xlfn.XLOOKUP(A30,'BD UM'!A:A,'BD UM'!F:F) -> 82103.287 | AD30: =_xlfn.XLOOKUP(A30,'BD U6M'!A:A,'BD U6M'!F:F) -> 83978.55 | AE30: =_xlfn.XLOOKUP(A30,'BD UM'!A:A,'BD UM'!G:G) -> 13052.1 | AF30: =_xlfn.XLOOKUP(A30,'BD U6M'!A:A,'BD U6M'!G:G) -> 12772.744 | AG30: =_xlfn.XLOOKUP(A30,'BD UM'!A:A,'BD UM'!H:H) -> 1.698 | AH30: COMERCIO/SERVICIO | AI30: ABIERTA | AJ30: BASE | AK30: EXP 2024 | AL30: 232000 | AM30: 62.65 | AN30: Primera 27 | AO30: Medio
A31: 50417 | B31: Centro Sur | C31: Distrito Capital | D31: Bogotá | E31: AMERICAS | F31: 3 | G31: Américas 72 | H31: CLAUDIO ENRIQUE BRICEÑO BERMUDEZ | I31: Esquinero | J31: 167.49 | K31: 1717 | L31: 983 | M31: 315 | N31: 45595 | O31: 30 | P31: 2 | Q31: 31 | R31: 22 | S31: 4.6256917 | T31: -74.138007 | U31: =_xlfn.XLOOKUP(A31,'BD UM'!A:A,'BD UM'!B:B) -> 14069 | V31: =_xlfn.XLOOKUP(A31,'BD U6M'!A:A,'BD U6M'!B:B) -> 14060.833 | W31: =_xlfn.XLOOKUP(A31,'BD UM'!A:A,'BD UM'!C:C) -> 12737.5 | X31: =_xlfn.XLOOKUP(A31,'BD U6M'!A:A,'BD U6M'!C:C) -> 12606.2 | Y31: =_xlfn.XLOOKUP(A31,'BD UM'!A:A,'BD UM'!D:D) -> 179203.72 | Z31: =_xlfn.XLOOKUP(A31,'BD U6M'!A:A,'BD U6M'!D:D) -> 177254.33 | AA31: =_xlfn.XLOOKUP(A31,'BD UM'!A:A,'BD UM'!E:E) -> 7304.356 | AB31: =_xlfn.XLOOKUP(A31,'BD U6M'!A:A,'BD U6M'!E:E) -> 6272.3101 | AC31: =_xlfn.XLOOKUP(A31,'BD UM'!A:A,'BD UM'!F:F) -> 63036.422 | AD31: =_xlfn.XLOOKUP(A31,'BD U6M'!A:A,'BD U6M'!F:F) -> 61775.952 | AE31: =_xlfn.XLOOKUP(A31,'BD UM'!A:A,'BD UM'!G:G) -> 10494 | AF31: =_xlfn.XLOOKUP(A31,'BD U6M'!A:A,'BD U6M'!G:G) -> 10601.082 | AG31: =_xlfn.XLOOKUP(A31,'BD UM'!A:A,'BD UM'!H:H) -> 0 | AH31: COMERCIO/SERVICIO | AI31: ABIERTA | AJ31: RECESO | AK31: EXP 2025 | AL31: 204160 | AM31: 95.4 | AN31: America Occidental | AO31: Medio
A32: 50VOZ | B32: Centro Sur | C32: Distrito Capital | D32: Bogotá | E32: AMERICAS | F32: 3 | G32: Américas Boyacá | H32: JOHN EDISON GIRALDO GIRALDO, ELKIN URIEL ARISTIZABAL BOTERO, GILBERTO ANDRES OCHOA CEBALLOS, LUIS ALEJANDRO OCHOA CEBALLOS, CESAR AUGUSTO OCHOA OSPINA Y ASTRID JOHANNA MESA HERRERA. | I32: Medianero | J32: 142.56 | K32: 430 | L32: 1177 | M32: 190 | N32: 45866 | O32: 28 | P32: 4 | Q32: 31 | R32: 13 | S32: 4.6166961 | T32: -74.137253 | U32: =_xlfn.XLOOKUP(A32,'BD UM'!A:A,'BD UM'!B:B) -> 18308 | V32: =_xlfn.XLOOKUP(A32,'BD U6M'!A:A,'BD U6M'!B:B) -> 17832.667 | W32: =_xlfn.XLOOKUP(A32,'BD UM'!A:A,'BD UM'!C:C) -> 12084.4 | X32: =_xlfn.XLOOKUP(A32,'BD U6M'!A:A,'BD U6M'!C:C) -> 11919.8 | Y32: =_xlfn.XLOOKUP(A32,'BD UM'!A:A,'BD UM'!D:D) -> 221241.11 | Z32: =_xlfn.XLOOKUP(A32,'BD U6M'!A:A,'BD U6M'!D:D) -> 212561.54 | AA32: =_xlfn.XLOOKUP(A32,'BD UM'!A:A,'BD UM'!E:E) -> 13604.747 | AB32: =_xlfn.XLOOKUP(A32,'BD U6M'!A:A,'BD U6M'!E:E) -> 10391.25 | AC32: =_xlfn.XLOOKUP(A32,'BD UM'!A:A,'BD UM'!F:F) -> 72420.387 | AD32: =_xlfn.XLOOKUP(A32,'BD U6M'!A:A,'BD U6M'!F:F) -> 70428.873 | AE32: =_xlfn.XLOOKUP(A32,'BD UM'!A:A,'BD UM'!G:G) -> 14275 | AF32: =_xlfn.XLOOKUP(A32,'BD U6M'!A:A,'BD U6M'!G:G) -> 13948.538 | AG32: =_xlfn.XLOOKUP(A32,'BD UM'!A:A,'BD UM'!H:H) -> 1.4992 | AH32: ESTACION DE SERVICIO | AI32: ABIERTA | AJ32: RECESO | AK32: TMCB | AL32: 204160 | AM32: 70.38 | AN32: Eds Molino | AO32: Medio
A33: 50IP7 | B33: Oriente | C33: Santander | D33: Floridablanca | E33: FLORIDABLANCA | F33: 4 | G33: Anillo Vial | H33: 0 | I33: Medianero | J33: 120.52 | K33: 30 | L33: 170 | M33: 52 | N33: 45016 | O33: 31 | P33: 1 | Q33: 31 | R33: 41 | S33: 7.0632186 | T33: -73.146089 | U33: =_xlfn.XLOOKUP(A33,'BD UM'!A:A,'BD UM'!B:B) -> 16419 | V33: =_xlfn.XLOOKUP(A33,'BD U6M'!A:A,'BD U6M'!B:B) -> 15852.167 | W33: =_xlfn.XLOOKUP(A33,'BD UM'!A:A,'BD UM'!C:C) -> 12780 | X33: =_xlfn.XLOOKUP(A33,'BD U6M'!A:A,'BD U6M'!C:C) -> 13725.4 | Y33: =_xlfn.XLOOKUP(A33,'BD UM'!A:A,'BD UM'!D:D) -> 209835.22 | Z33: =_xlfn.XLOOKUP(A33,'BD U6M'!A:A,'BD U6M'!D:D) -> 217577.3 | AA33: =_xlfn.XLOOKUP(A33,'BD UM'!A:A,'BD UM'!E:E) -> 15604.528 | AB33: =_xlfn.XLOOKUP(A33,'BD U6M'!A:A,'BD U6M'!E:E) -> 22111.743 | AC33: =_xlfn.XLOOKUP(A33,'BD UM'!A:A,'BD UM'!F:F) -> 82956.152 | AD33: =_xlfn.XLOOKUP(A33,'BD U6M'!A:A,'BD U6M'!F:F) -> 81957.446 | AE33: =_xlfn.XLOOKUP(A33,'BD UM'!A:A,'BD UM'!G:G) -> 8481.949 | AF33: =_xlfn.XLOOKUP(A33,'BD U6M'!A:A,'BD U6M'!G:G) -> 8583.6107 | AG33: =_xlfn.XLOOKUP(A33,'BD UM'!A:A,'BD UM'!H:H) -> 0 | AH33: ALTA DENSIDAD | AI33: ABIERTA | AJ33: HOGAR | AK33: TMCB | AL33: 241405 | AM33: 79.4 | AN33: Cedro | AO33: Medio
A34: 502XT | B34: Centro Norte | C34: Distrito Capital | D34: Bogotá | E34: LOS CEDROS | F34: 5 | G34: Antigua | H34: 0 | I34: Esquinero | J34: 139.26 | K34: 2248 | L34: 263 | M34: 28 | N34: 45412 | O34: 30 | P34: 1 | Q34: 30 | R34: 28 | S34: 4.7143477 | T34: -74.03684 | U34: =_xlfn.XLOOKUP(A34,'BD UM'!A:A,'BD UM'!B:B) -> 15328 | V34: =_xlfn.XLOOKUP(A34,'BD U6M'!A:A,'BD U6M'!B:B) -> 14805.167 | W34: =_xlfn.XLOOKUP(A34,'BD UM'!A:A,'BD UM'!C:C) -> 14328.3 | X34: =_xlfn.XLOOKUP(A34,'BD U6M'!A:A,'BD U6M'!C:C) -> 14475.7 | Y34: =_xlfn.XLOOKUP(A34,'BD UM'!A:A,'BD UM'!D:D) -> 219624.63 | Z34: =_xlfn.XLOOKUP(A34,'BD U6M'!A:A,'BD U6M'!D:D) -> 214314.87 | AA34: =_xlfn.XLOOKUP(A34,'BD UM'!A:A,'BD UM'!E:E) -> 16556.697 | AB34: =_xlfn.XLOOKUP(A34,'BD U6M'!A:A,'BD U6M'!E:E) -> 15444.616 | AC34: =_xlfn.XLOOKUP(A34,'BD UM'!A:A,'BD UM'!F:F) -> 79846.129 | AD34: =_xlfn.XLOOKUP(A34,'BD U6M'!A:A,'BD U6M'!F:F) -> 77595.142 | AE34: =_xlfn.XLOOKUP(A34,'BD UM'!A:A,'BD UM'!G:G) -> 11056.52 | AF34: =_xlfn.XLOOKUP(A34,'BD U6M'!A:A,'BD U6M'!G:G) -> 11073.916 | AG34: =_xlfn.XLOOKUP(A34,'BD UM'!A:A,'BD UM'!H:H) -> 0 | AH34: ALTA DENSIDAD | AI34: ABIERTA | AJ34: HOGAR | AK34: EXP 2024 | AL34: 241405 | AM34: 77.38 | AN34: Foresta Norte Armeni | AO34: Medio
A35: 50OMJ | B35: Occidente | C35: Quindío | D35: Armenia | E35: QUIMBAYA | F35: 5 | G35: Aquazul | H35: INVERSIONES CABO VERDE S.A.S | I35: Esquinero | J35: 115.56 | K35: 3162 | L35: 0 | M35: 55 | N35: 45647 | O35: 21 | P35: 11 | Q35: 31 | R35: 20 | S35: 4.5616803 | T35: -75.657848 | U35: =_xlfn.XLOOKUP(A35,'BD UM'!A:A,'BD UM'!B:B) -> 12999 | V35: =_xlfn.XLOOKUP(A35,'BD U6M'!A:A,'BD U6M'!B:B) -> 12680 | W35: =_xlfn.XLOOKUP(A35,'BD UM'!A:A,'BD UM'!C:C) -> 13326 | X35: =_xlfn.XLOOKUP(A35,'BD U6M'!A:A,'BD U6M'!C:C) -> 13367.5 | Y35: =_xlfn.XLOOKUP(A35,'BD UM'!A:A,'BD UM'!D:D) -> 173224.77 | Z35: =_xlfn.XLOOKUP(A35,'BD U6M'!A:A,'BD U6M'!D:D) -> 169500.42 | AA35: =_xlfn.XLOOKUP(A35,'BD UM'!A:A,'BD UM'!E:E) -> -3080.598 | AB35: =_xlfn.XLOOKUP(A35,'BD U6M'!A:A,'BD U6M'!E:E) -> 6868.7623 | AC35: =_xlfn.XLOOKUP(A35,'BD UM'!A:A,'BD UM'!F:F) -> 65921.256 | AD35: =_xlfn.XLOOKUP(A35,'BD U6M'!A:A,'BD U6M'!F:F) -> 62170.732 | AE35: =_xlfn.XLOOKUP(A35,'BD UM'!A:A,'BD UM'!G:G) -> 8942 | AF35: =_xlfn.XLOOKUP(A35,'BD U6M'!A:A,'BD U6M'!G:G) -> 9036.0682 | AG35: =_xlfn.XLOOKUP(A35,'BD UM'!A:A,'BD UM'!H:H) -> 0 | AH35: COMERCIO/SERVICIO | AI35: ABIERTA | AJ35: BASE | AK35: TMCB | AL35: 232000 | AM35: 123.28 | AN35: Pista Aeropuerto | AO35: Alto
A36: 50CV4 | B36: Occidente | C36: Valle del Cauca | D36: Cali | E36: CALI | F36: 4 | G36: Arbolatta Mall | H36: 0 | I36: Esquinero | J36: 98.65 | K36: 2200 | L36: 320 | M36: 63 | N36: 45435 | O36: 23 | P36: 9 | Q36: 31 | R36: 27 | S36: 3.3603253 | T36: -76.515519 | U36: =_xlfn.XLOOKUP(A36,'BD UM'!A:A,'BD UM'!B:B) -> 19624 | V36: =_xlfn.XLOOKUP(A36,'BD U6M'!A:A,'BD U6M'!B:B) -> 17401.5 | W36: =_xlfn.XLOOKUP(A36,'BD UM'!A:A,'BD UM'!C:C) -> 14526.1 | X36: =_xlfn.XLOOKUP(A36,'BD U6M'!A:A,'BD U6M'!C:C) -> 14281.2 | Y36: =_xlfn.XLOOKUP(A36,'BD UM'!A:A,'BD UM'!D:D) -> 285060.19 | Z36: =_xlfn.XLOOKUP(A36,'BD U6M'!A:A,'BD U6M'!D:D) -> 248513.68 | AA36: =_xlfn.XLOOKUP(A36,'BD UM'!A:A,'BD UM'!E:E) -> 31153.137 | AB36: =_xlfn.XLOOKUP(A36,'BD U6M'!A:A,'BD U6M'!E:E) -> 25320.448 | AC36: =_xlfn.XLOOKUP(A36,'BD UM'!A:A,'BD UM'!F:F) -> 110128.91 | AD36: =_xlfn.XLOOKUP(A36,'BD U6M'!A:A,'BD U6M'!F:F) -> 94196.101 | AE36: =_xlfn.XLOOKUP(A36,'BD UM'!A:A,'BD UM'!G:G) -> 12162.172 | AF36: =_xlfn.XLOOKUP(A36,'BD U6M'!A:A,'BD U6M'!G:G) -> 12122.962 | AG36: =_xlfn.XLOOKUP(A36,'BD UM'!A:A,'BD UM'!H:H) -> 0 | AH36: ALTA DENSIDAD | AI36: ABIERTA | AJ36: HOGAR | AK36: TMCB | AL36: 241405 | AM36: 60.57 | AN36: Santa Matilde | AO36: Medio
A37: 50R0P | B37: Centro Sur | C37: Distrito Capital | D37: Bogotá | E37: SANTA CECILIA | F37: 3 | G37: Arrayanes | H37: 0 | I37: Esquinero | J37: 106.29 | K37: 2615 | L37: 335 | M37: 155 | N37: 45169 | O37: 31 | P37: 1 | Q37: 31 | R37: 36 | S37: 4.6807622 | T37: -74.113838 | U37: =_xlfn.XLOOKUP(A37,'BD UM'!A:A,'BD UM'!B:B) -> 14520 | V37: =_xlfn.XLOOKUP(A37,'BD U6M'!A:A,'BD U6M'!B:B) -> 14616.167 | W37: =_xlfn.XLOOKUP(A37,'BD UM'!A:A,'BD UM'!C:C) -> 13143.6 | X37: =_xlfn.XLOOKUP(A37,'BD U6M'!A:A,'BD U6M'!C:C) -> 12953.7 | Y37: =_xlfn.XLOOKUP(A37,'BD UM'!A:A,'BD UM'!D:D) -> 190845.29 | Z37: =_xlfn.XLOOKUP(A37,'BD U6M'!A:A,'BD U6M'!D:D) -> 189332.89 | AA37: =_xlfn.XLOOKUP(A37,'BD UM'!A:A,'BD UM'!E:E) -> 11576.281 | AB37: =_xlfn.XLOOKUP(A37,'BD U6M'!A:A,'BD U6M'!E:E) -> 9741.9539 | AC37: =_xlfn.XLOOKUP(A37,'BD UM'!A:A,'BD UM'!F:F) -> 62654.675 | AD37: =_xlfn.XLOOKUP(A37,'BD U6M'!A:A,'BD U6M'!F:F) -> 61034.232 | AE37: =_xlfn.XLOOKUP(A37,'BD UM'!A:A,'BD UM'!G:G) -> 6766.236 | AF37: =_xlfn.XLOOKUP(A37,'BD U6M'!A:A,'BD U6M'!G:G) -> 6591.2473 | AG37: =_xlfn.XLOOKUP(A37,'BD UM'!A:A,'BD UM'!H:H) -> 0 | AH37: ADMINISTRATIVO | AI37: ABIERTA | AJ37: RECESO | AK37: EXP 2025 | AL37: 204160 | AM37: 47.41 | AN37: Dorado Plaza | AO37: Medio
A38: 50B6R | B38: Centro Sur | C38: Distrito Capital | D38: Bogotá | E38: CIUDAD SALITRE OCCIDENTAL | F38: 4 | G38: Arrecife | H38: MCJ INVERSIONES S.A.S. | I38: Esquinero | J38: 144.1 | K38: 395 | L38: 4660 | M38: 0 | N38: 45771 | O38: 24 | P38: 7 | Q38: 30 | R38: 16 | S38: 4.6482314 | T38: -74.101443 | U38: =_xlfn.XLOOKUP(A38,'BD UM'!A:A,'BD UM'!B:B) -> 13277 | V38: =_xlfn.XLOOKUP(A38,'BD U6M'!A:A,'BD U6M'!B:B) -> 13416.5 | W38: =_xlfn.XLOOKUP(A38,'BD UM'!A:A,'BD UM'!C:C) -> 8997.1 | X38: =_xlfn.XLOOKUP(A38,'BD U6M'!A:A,'BD U6M'!C:C) -> 9427.2 | Y38: =_xlfn.XLOOKUP(A38,'BD UM'!A:A,'BD UM'!D:D) -> 119453.92 | Z38: =_xlfn.XLOOKUP(A38,'BD U6M'!A:A,'BD U6M'!D:D) -> 126479.84 | AA38: =_xlfn.XLOOKUP(A38,'BD UM'!A:A,'BD UM'!E:E) -> 4111.511 | AB38: =_xlfn.XLOOKUP(A38,'BD U6M'!A:A,'BD U6M'!E:E) -> 7128.1676 | AC38: =_xlfn.XLOOKUP(A38,'BD UM'!A:A,'BD UM'!F:F) -> 51466.877 | AD38: =_xlfn.XLOOKUP(A38,'BD U6M'!A:A,'BD U6M'!F:F) -> 52590.503 | AE38: =_xlfn.XLOOKUP(A38,'BD UM'!A:A,'BD UM'!G:G) -> 6831.5 | AF38: =_xlfn.XLOOKUP(A38,'BD U6M'!A:A,'BD U6M'!G:G) -> 6862.1819 | AG38: =_xlfn.XLOOKUP(A38,'BD UM'!A:A,'BD UM'!H:H) -> 1.1944 | AH38: COMERCIO/SERVICIO | AI38: ABIERTA | AJ38: BASE | AK38: TMCB | AL38: 232000 | AM38: 58.13 | AN38: Chicamocha | AO38: Medio
A39: 50ZFN | B39: Oriente | C39: Santander | D39: Bucaramanga | E39: LA PEDREGOSA | F39: 3 | G39: Asturias | H39: 0 | I39: Esquinero | J39: 100.67 | K39: 770 | L39: 510 | M39: 46 | N39: 44890 | O39: 25 | P39: 6 | Q39: 30 | R39: 45 | S39: 7.0895364 | T39: -73.107467 | U39: =_xlfn.XLOOKUP(A39,'BD UM'!A:A,'BD UM'!B:B) -> 16512 | V39: =_xlfn.XLOOKUP(A39,'BD U6M'!A:A,'BD U6M'!B:B) -> 16162 | W39: =_xlfn.XLOOKUP(A39,'BD UM'!A:A,'BD UM'!C:C) -> 10595.3 | X39: =_xlfn.XLOOKUP(A39,'BD U6M'!A:A,'BD U6M'!C:C) -> 10791.3 | Y39: =_xlfn.XLOOKUP(A39,'BD UM'!A:A,'BD UM'!D:D) -> 174950.37 | Z39: =_xlfn.XLOOKUP(A39,'BD U6M'!A:A,'BD U6M'!D:D) -> 174408.44 | AA39: =_xlfn.XLOOKUP(A39,'BD UM'!A:A,'BD UM'!E:E) -> 4645.578 | AB39: =_xlfn.XLOOKUP(A39,'BD U6M'!A:A,'BD U6M'!E:E) -> 6598.9899 | AC39: =_xlfn.XLOOKUP(A39,'BD UM'!A:A,'BD UM'!F:F) -> 61332.33 | AD39: =_xlfn.XLOOKUP(A39,'BD U6M'!A:A,'BD U6M'!F:F) -> 60600.201 | AE39: =_xlfn.XLOOKUP(A39,'BD UM'!A:A,'BD UM'!G:G) -> 5852.054 | AF39: =_xlfn.XLOOKUP(A39,'BD U6M'!A:A,'BD U6M'!G:G) -> 5920.2128 | AG39: =_xlfn.XLOOKUP(A39,'BD UM'!A:A,'BD UM'!H:H) -> 0 | AH39: ADMINISTRATIVO | AI39: ABIERTA | AJ39: BASE | AK39: TMCB | AL39: 232000 | AM39: 128.9 | AN39: PT | AO39: Alto
A40: 504EU | B40: Centro Norte | C40: Distrito Capital | D40: Bogotá | E40: EL PRADO | F40: 4 | G40: Atabanza | H40: 0 | I40: Esquinero | J40: 150 | K40: 3207 | L40: 1461 | M40: 0 | N40: 43453 | O40: 19 | P40: 13 | Q40: 31 | R40: 92 | S40: 4.7094003 | T40: -74.0617 | U40: =_xlfn.XLOOKUP(A40,'BD UM'!A:A,'BD UM'!B:B) -> 31142 | V40: =_xlfn.XLOOKUP(A40,'BD U6M'!A:A,'BD U6M'!B:B) -> 32653.5 | W40: =_xlfn.XLOOKUP(A40,'BD UM'!A:A,'BD UM'!C:C) -> 12639.7 | X40: =_xlfn.XLOOKUP(A40,'BD U6M'!A:A,'BD U6M'!C:C) -> 12853.3 | Y40: =_xlfn.XLOOKUP(A40,'BD UM'!A:A,'BD UM'!D:D) -> 393626.4 | Z40: =_xlfn.XLOOKUP(A40,'BD U6M'!A:A,'BD U6M'!D:D) -> 419705.45 | AA40: =_xlfn.XLOOKUP(A40,'BD UM'!A:A,'BD UM'!E:E) -> 62055.343 | AB40: =_xlfn.XLOOKUP(A40,'BD U6M'!A:A,'BD U6M'!E:E) -> 64561.956 | AC40: =_xlfn.XLOOKUP(A40,'BD UM'!A:A,'BD UM'!F:F) -> 148038.29 | AD40: =_xlfn.XLOOKUP(A40,'BD U6M'!A:A,'BD U6M'!F:F) -> 156035.39 | AE40: =_xlfn.XLOOKUP(A40,'BD UM'!A:A,'BD UM'!G:G) -> 19334.793 | AF40: =_xlfn.XLOOKUP(A40,'BD U6M'!A:A,'BD U6M'!G:G) -> 19604.57 | AG40: =_xlfn.XLOOKUP(A40,'BD UM'!A:A,'BD UM'!H:H) -> 0 | AH40: EDUCACION | AI40: ABIERTA | AJ40: BASE | AK40: TMCB | AL40: 232000 | AM40: 65.47 | AN40: Gran Provenza | AO40: Alto
A41: 50A5Z | B41: Oriente | C41: Santander | D41: Bucaramanga | E41: ORIENTAL | F41: 4 | G41: Aurora 2 | H41: 0 | I41: Medianero | J41: 122.92 | K41: 2469 | L41: 624 | M41: 94 | N41: 45198 | O41: 29 | P41: 2 | Q41: 30 | R41: 35 | S41: 7.1242955 | T41: -73.116785 | U41: =_xlfn.XLOOKUP(A41,'BD UM'!A:A,'BD UM'!B:B) -> 18690 | V41: =_xlfn.XLOOKUP(A41,'BD U6M'!A:A,'BD U6M'!B:B) -> 18421 | W41: =_xlfn.XLOOKUP(A41,'BD UM'!A:A,'BD UM'!C:C) -> 10243.1 | X41: =_xlfn.XLOOKUP(A41,'BD U6M'!A:A,'BD U6M'!C:C) -> 10554.2 | Y41: =_xlfn.XLOOKUP(A41,'BD UM'!A:A,'BD UM'!D:D) -> 191444.28 | Z41: =_xlfn.XLOOKUP(A41,'BD U6M'!A:A,'BD U6M'!D:D) -> 194418.46 | AA41: =_xlfn.XLOOKUP(A41,'BD UM'!A:A,'BD UM'!E:E) -> 10703.415 | AB41: =_xlfn.XLOOKUP(A41,'BD U6M'!A:A,'BD U6M'!E:E) -> 16334.494 | AC41: =_xlfn.XLOOKUP(A41,'BD UM'!A:A,'BD UM'!F:F) -> 75931.381 | AD41: =_xlfn.XLOOKUP(A41,'BD U6M'!A:A,'BD U6M'!F:F) -> 76859.574 | AE41: =_xlfn.XLOOKUP(A41,'BD UM'!A:A,'BD UM'!G:G) -> 8156.823 | AF41: =_xlfn.XLOOKUP(A41,'BD U6M'!A:A,'BD U6M'!G:G) -> 8152.1864 | AG41: =_xlfn.XLOOKUP(A41,'BD UM'!A:A,'BD UM'!H:H) -> 0 | AH41: ADMINISTRATIVO | AI41: ABIERTA | AJ41: BASE | AK41: TMCB | AL41: 232000 | AM41: 129.61 | AN41: PT | AO41: Alto
A42: 50AT6 | B42: Centro Norte | C42: Distrito Capital | D42: Bogotá | E42: CHICO LAGO | F42: 6 | G42: Auto 100 | H42: 0 | I42: Esquinero | J42: 188.98 | K42: 18 | L42: 1914 | M42: 0 | N42: 42684 | O42: 10 | P42: 21 | Q42: 30 | R42: 115 | S42: 4.6858733 | T42: -74.055822 | U42: =_xlfn.XLOOKUP(A42,'BD UM'!A:A,'BD UM'!B:B) -> 31821 | V42: =_xlfn.XLOOKUP(A42,'BD U6M'!A:A,'BD U6M'!B:B) -> 32327 | W42: =_xlfn.XLOOKUP(A42,'BD UM'!A:A,'BD UM'!C:C) -> 11429.5 | X42: =_xlfn.XLOOKUP(A42,'BD U6M'!A:A,'BD U6M'!C:C) -> 11487.3 | Y42: =_xlfn.XLOOKUP(A42,'BD UM'!A:A,'BD UM'!D:D) -> 363697.31 | Z42: =_xlfn.XLOOKUP(A42,'BD U6M'!A:A,'BD U6M'!D:D) -> 371349.53 | AA42: =_xlfn.XLOOKUP(A42,'BD UM'!A:A,'BD UM'!E:E) -> 44599.251 | AB42: =_xlfn.XLOOKUP(A42,'BD U6M'!A:A,'BD U6M'!E:E) -> 47535.96 | AC42: =_xlfn.XLOOKUP(A42,'BD UM'!A:A,'BD UM'!F:F) -> 138563.5 | AD42: =_xlfn.XLOOKUP(A42,'BD U6M'!A:A,'BD U6M'!F:F) -> 139915.34 | AE42: =_xlfn.XLOOKUP(A42,'BD UM'!A:A,'BD UM'!G:G) -> 24915.613 | AF42: =_xlfn.XLOOKUP(A42,'BD U6M'!A:A,'BD U6M'!G:G) -> 24552.55 | AG42: =_xlfn.XLOOKUP(A42,'BD UM'!A:A,'BD UM'!H:H) -> 0 | AH42: COMERCIO/SERVICIO | AI42: ABIERTA | AJ42: BASE | AK42: TMCB | AL42: 232000 | AM42: 72.93 | AN42: Morato | AO42: Alto
A43: 50I2O | B43: Centro Norte | C43: Distrito Capital | D43: Bogotá | E43: SANTA BARBARA | F43: 5 | G43: Autonorte 100 | H43: 0 | I43: Esquinero | J43: 107 | K43: 798 | L43: 2110 | M43: 98 | N43: 44824 | O43: 20 | P43: 11 | Q43: 30 | R43: 47 | S43: 4.6874147 | T43: -74.056677 | U43: =_xlfn.XLOOKUP(A43,'BD UM'!A:A,'BD UM'!B:B) -> 11796 | V43: =_xlfn.XLOOKUP(A43,'BD U6M'!A:A,'BD U6M'!B:B) -> 11065.167 | W43: =_xlfn.XLOOKUP(A43,'BD UM'!A:A,'BD UM'!C:C) -> 9905.4 | X43: =_xlfn.XLOOKUP(A43,'BD U6M'!A:A,'BD U6M'!C:C) -> 10366.2 | Y43: =_xlfn.XLOOKUP(A43,'BD UM'!A:A,'BD UM'!D:D) -> 116844.26 | Z43: =_xlfn.XLOOKUP(A43,'BD U6M'!A:A,'BD U6M'!D:D) -> 114703.19 | AA43: =_xlfn.XLOOKUP(A43,'BD UM'!A:A,'BD UM'!E:E) -> 3724.547 | AB43: =_xlfn.XLOOKUP(A43,'BD U6M'!A:A,'BD U6M'!E:E) -> 9.8435613 | AC43: =_xlfn.XLOOKUP(A43,'BD UM'!A:A,'BD UM'!F:F) -> 48413.456 | AD43: =_xlfn.XLOOKUP(A43,'BD U6M'!A:A,'BD U6M'!F:F) -> 47606.644 | AE43: =_xlfn.XLOOKUP(A43,'BD UM'!A:A,'BD UM'!G:G) -> 8200.678 | AF43: =_xlfn.XLOOKUP(A43,'BD U6M'!A:A,'BD U6M'!G:G) -> 7998.2379 | AG43: =_xlfn.XLOOKUP(A43,'BD UM'!A:A,'BD UM'!H:H) -> 0 | AH43: COMERCIO/SERVICIO | AI43: ABIERTA | AJ43: BASE | AK43: TMCB | AL43: 232000 | AM43: 176.59 | AN43: PT | AO43: Medio
A44: 50AJF | B44: Centro Norte | C44: Distrito Capital | D44: Bogotá | E44: EL PRADO | F44: 3 | G44: Autopista | H44: 0 | I44: Esquinero | J44: 98.93 | K44: 524 | L44: 1999 | M44: 0 | N44: 40171 | O44: 24 | P44: 8 | Q44: 31 | R44: 115 | S44: 4.7138224 | T44: -74.053676 | U44: =_xlfn.XLOOKUP(A44,'BD UM'!A:A,'BD UM'!B:B) -> 23974 | V44: =_xlfn.XLOOKUP(A44,'BD U6M'!A:A,'BD U6M'!B:B) -> 24843.667 | W44: =_xlfn.XLOOKUP(A44,'BD UM'!A:A,'BD UM'!C:C) -> 9773.2 | X44: =_xlfn.XLOOKUP(A44,'BD U6M'!A:A,'BD U6M'!C:C) -> 9626.6 | Y44: =_xlfn.XLOOKUP(A44,'BD UM'!A:A,'BD UM'!D:D) -> 234303.42 | Z44: =_xlfn.XLOOKUP(A44,'BD U6M'!A:A,'BD U6M'!D:D) -> 239160.69 | AA44: =_xlfn.XLOOKUP(A44,'BD UM'!A:A,'BD UM'!E:E) -> 21096.717 | AB44: =_xlfn.XLOOKUP(A44,'BD U6M'!A:A,'BD U6M'!E:E) -> 17379.644 | AC44: =_xlfn.XLOOKUP(A44,'BD UM'!A:A,'BD UM'!F:F) -> 84377.437 | AD44: =_xlfn.XLOOKUP(A44,'BD U6M'!A:A,'BD U6M'!F:F) -> 85588.772 | AE44: =_xlfn.XLOOKUP(A44,'BD UM'!A:A,'BD UM'!G:G) -> 17463.886 | AF44: =_xlfn.XLOOKUP(A44,'BD U6M'!A:A,'BD U6M'!G:G) -> 17703.166 | AG44: =_xlfn.XLOOKUP(A44,'BD UM'!A:A,'BD UM'!H:H) -> 0 | AH44: ADMINISTRATIVO | AI44: ABIERTA | AJ44: RECESO | AK44: EXP 2024 | AL44: 204160 | AM44: 152.38 | AN44: Estación Pepe Sierra | AO44: Alto
A45: 50FKJ | B45: Centro Norte | C45: Distrito Capital | D45: Bogotá | E45: CHICO LAGO | F45: 5 | G45: Autopista 97 | H45: 0 | I45: Medianero | J45: 103.56 | K45: 1180 | L45: 4100 | M45: 98 | N45: 45520 | O45: 16 | P45: 16 | Q45: 31 | R45: 24 | S45: 4.6858029 | T45: -74.056912 | U45: =_xlfn.XLOOKUP(A45,'BD UM'!A:A,'BD UM'!B:B) -> 30705 | V45: =_xlfn.XLOOKUP(A45,'BD U6M'!A:A,'BD U6M'!B:B) -> 31124.333 | W45: =_xlfn.XLOOKUP(A45,'BD UM'!A:A,'BD UM'!C:C) -> 10668.1 | X45: =_xlfn.XLOOKUP(A45,'BD U6M'!A:A,'BD U6M'!C:C) -> 9954.8 | Y45: =_xlfn.XLOOKUP(A45,'BD UM'!A:A,'BD UM'!D:D) -> 327564.14 | Z45: =_xlfn.XLOOKUP(A45,'BD U6M'!A:A,'BD U6M'!D:D) -> 309836.52 | AA45: =_xlfn.XLOOKUP(A45,'BD UM'!A:A,'BD UM'!E:E) -> 43047.42 | AB45: =_xlfn.XLOOKUP(A45,'BD U6M'!A:A,'BD U6M'!E:E) -> 43880.521 | AC45: =_xlfn.XLOOKUP(A45,'BD UM'!A:A,'BD UM'!F:F) -> 127827.94 | AD45: =_xlfn.XLOOKUP(A45,'BD U6M'!A:A,'BD U6M'!F:F) -> 122232.59 | AE45: =_xlfn.XLOOKUP(A45,'BD UM'!A:A,'BD UM'!G:G) -> 16584 | AF45: =_xlfn.XLOOKUP(A45,'BD U6M'!A:A,'BD U6M'!G:G) -> 16160.199 | AG45: =_xlfn.XLOOKUP(A45,'BD UM'!A:A,'BD UM'!H:H) -> 0 | AH45: ND | AI45: ABIERTA | AJ45: BASE | AK45: EXP 2026 | AL45: 232000 | AM45: $ - | AN45: San Pedro | AO45: Medio
A46: 5028Z | B46: Occidente | C46: Antioquia | D46: Medellín | E46: LAURELES | F46: 2 | G46: Av Bolivariana | H46: INVERSIONES RYJ S.A.S | I46: Esquinero | J46: 120.46 | K46: 2399 | L46: 345 | M46: 124 | N46: 46172 | O46: 30 | P46: 2 | Q46: 31 | R46: 3 | S46: 6.2451319 | T46: -75.583769 | U46: =_xlfn.XLOOKUP(A46,'BD UM'!A:A,'BD UM'!B:B) -> 13175 | V46: =_xlfn.XLOOKUP(A46,'BD U6M'!A:A,'BD U6M'!B:B) -> 8747.25 | W46: =_xlfn.XLOOKUP(A46,'BD UM'!A:A,'BD UM'!C:C) -> 14212.5 | X46: =_xlfn.XLOOKUP(A46,'BD U6M'!A:A,'BD U6M'!C:C) -> 14226.2 | Y46: =_xlfn.XLOOKUP(A46,'BD UM'!A:A,'BD UM'!D:D) -> 187249.79 | Z46: =_xlfn.XLOOKUP(A46,'BD U6M'!A:A,'BD U6M'!D:D) -> 124440.02 | AA46: =_xlfn.XLOOKUP(A46,'BD UM'!A:A,'BD UM'!E:E) -> -7020.44 | AB46: =_xlfn.XLOOKUP(A46,'BD U6M'!A:A,'BD U6M'!E:E) -> -221.3394 | AC46: =_xlfn.XLOOKUP(A46,'BD UM'!A:A,'BD UM'!F:F) -> 69787.036 | AD46: =_xlfn.XLOOKUP(A46,'BD U6M'!A:A,'BD U6M'!F:F) -> 47443.293 | AE46: =_xlfn.XLOOKUP(A46,'BD UM'!A:A,'BD UM'!G:G) -> 29900 | AF46: =_xlfn.XLOOKUP(A46,'BD U6M'!A:A,'BD U6M'!G:G) -> 9779.8899 | AG46: =_xlfn.XLOOKUP(A46,'BD UM'!A:A,'BD UM'!H:H) -> 1.9365 | AH46: COMERCIO/SERVICIO | AI46: ABIERTA | AJ46: RECESO | AK46: TMCB | AL46: 204160 | AM46: 130.77 | AN46: Norte 626 | AO46: Alto
A47: 50Y57 | B47: Occidente | C47: Valle del Cauca | D47: Cali | E47: COMUNA 2 | F47: 4 | G47: Av Colombia Centenar | H47: 0 | I47: Esquinero | J47: 83.51 | K47: 651 | L47: 1051 | M47: 187 | N47: 45322 | O47: 31 | P47: 1 | Q47: 31 | R47: 31 | S47: 3.452137 | T47: -76.536846 | U47: =_xlfn.XLOOKUP(A47,'BD UM'!A:A,'BD UM'!B:B) -> 16530 | V47: =_xlfn.XLOOKUP(A47,'BD U6M'!A:A,'BD U6M'!B:B) -> 17163.5 | W47: =_xlfn.XLOOKUP(A47,'BD UM'!A:A,'BD UM'!C:C) -> 14700.1 | X47: =_xlfn.XLOOKUP(A47,'BD U6M'!A:A,'BD U6M'!C:C) -> 14399.1 | Y47: =_xlfn.XLOOKUP(A47,'BD UM'!A:A,'BD UM'!D:D) -> 242991.97 | Z47: =_xlfn.XLOOKUP(A47,'BD U6M'!A:A,'BD U6M'!D:D) -> 247139.17 | AA47: =_xlfn.XLOOKUP(A47,'BD UM'!A:A,'BD UM'!E:E) -> 18990.151 | AB47: =_xlfn.XLOOKUP(A47,'BD U6M'!A:A,'BD U6M'!E:E) -> 22463.09 | AC47: =_xlfn.XLOOKUP(A47,'BD UM'!A:A,'BD UM'!F:F) -> 90159.86 | AD47: =_xlfn.XLOOKUP(A47,'BD U6M'!A:A,'BD U6M'!F:F) -> 87760.928 | AE47: =_xlfn.XLOOKUP(A47,'BD UM'!A:A,'BD UM'!G:G) -> 10921.443 | AF47: =_xlfn.XLOOKUP(A47,'BD U6M'!A:A,'BD U6M'!G:G) -> 11032.109 | AG47: =_xlfn.XLOOKUP(A47,'BD UM'!A:A,'BD UM'!H:H) -> 0 | AH47: COMERCIO/SERVICIO | AI47: ABIERTA | AJ47: BASE | AK47: TMCB | AL47: 232000 | AM47: 68.11 | AN47: Calle 116 | AO47: Medio
A48: 50LMN | B48: Centro Sur | C48: Distrito Capital | D48: Bogotá | E48: CARVAJAL | F48: 3 | G48: Av Quimbaya | H48: 0 | I48: Medianero | J48: 114.76 | K48: 1529 | L48: 300 | M48: 71 | N48: 45260 | O48: 30 | P48: 1 | Q48: 30 | R48: 33 | S48: 4.608005 | T48: -74.146589 | U48: =_xlfn.XLOOKUP(A48,'BD UM'!A:A,'BD UM'!B:B) -> 13640 | V48: =_xlfn.XLOOKUP(A48,'BD U6M'!A:A,'BD U6M'!B:B) -> 13610.333 | W48: =_xlfn.XLOOKUP(A48,'BD UM'!A:A,'BD UM'!C:C) -> 14038.5 | X48: =_xlfn.XLOOKUP(A48,'BD U6M'!A:A,'BD U6M'!C:C) -> 15321.8 | Y48: =_xlfn.XLOOKUP(A48,'BD UM'!A:A,'BD UM'!D:D) -> 191484.83 | Z48: =_xlfn.XLOOKUP(A48,'BD U6M'!A:A,'BD U6M'!D:D) -> 208534.74 | AA48: =_xlfn.XLOOKUP(A48,'BD UM'!A:A,'BD UM'!E:E) -> 8284.749 | AB48: =_xlfn.XLOOKUP(A48,'BD U6M'!A:A,'BD U6M'!E:E) -> 13194.687 | AC48: =_xlfn.XLOOKUP(A48,'BD UM'!A:A,'BD UM'!F:F) -> 60140.274 | AD48: =_xlfn.XLOOKUP(A48,'BD U6M'!A:A,'BD U6M'!F:F) -> 64853.115 | AE48: =_xlfn.XLOOKUP(A48,'BD UM'!A:A,'BD UM'!G:G) -> 6897.754 | AF48: =_xlfn.XLOOKUP(A48,'BD U6M'!A:A,'BD U6M'!G:G) -> 6974.6809 | AG48: =_xlfn.XLOOKUP(A48,'BD UM'!A:A,'BD UM'!H:H) -> 0 | AH48: COMERCIO/SERVICIO | AI48: ABIERTA | AJ48: BASE | AK48: TMCB | AL48: 232000 | AM48: 58.38 | AN48: Gonzalez Valencia | AO48: Medio
A49: 50RZH | B49: Occidente | C49: Valle del Cauca | D49: Cali | E49: COMUNA 19 | F49: 4 | G49: Av Roosevelt | H49: 0 | I49: Esquinero | J49: 118.14 | K49: 582 | L49: 1800 | M49: 42 | N49: 45259 | O49: 29 | P49: 2 | Q49: 30 | R49: 33 | S49: 3.425072 | T49: -76.540297 | U49: =_xlfn.XLOOKUP(A49,'BD UM'!A:A,'BD UM'!B:B) -> 10935 | V49: =_xlfn.XLOOKUP(A49,'BD U6M'!A:A,'BD U6M'!B:B) -> 12507.167 | W49: =_xlfn.XLOOKUP(A49,'BD UM'!A:A,'BD UM'!C:C) -> 11557.1 | X49: =_xlfn.XLOOKUP(A49,'BD U6M'!A:A,'BD U6M'!C:C) -> 12297.3 | Y49: =_xlfn.XLOOKUP(A49,'BD UM'!A:A,'BD UM'!D:D) -> 126376.44 | Z49: =_xlfn.XLOOKUP(A49,'BD U6M'!A:A,'BD U6M'!D:D) -> 153803.87 | AA49: =_xlfn.XLOOKUP(A49,'BD UM'!A:A,'BD UM'!E:E) -> -40184.532 | AB49: =_xlfn.XLOOKUP(A49,'BD U6M'!A:A,'BD U6M'!E:E) -> -4969.9957 | AC49: =_xlfn.XLOOKUP(A49,'BD UM'!A:A,'BD UM'!F:F) -> 42050.263 | AD49: =_xlfn.XLOOKUP(A49,'BD U6M'!A:A,'BD U6M'!F:F) -> 56262.92 | AE49: =_xlfn.XLOOKUP(A49,'BD UM'!A:A,'BD UM'!G:G) -> 8047.379 | AF49: =_xlfn.XLOOKUP(A49,'BD U6M'!A:A,'BD U6M'!G:G) -> 8133.9457 | AG49: =_xlfn.XLOOKUP(A49,'BD UM'!A:A,'BD UM'!H:H) -> 0 | AH49: BAJA DENSIDAD | AI49: ABIERTA | AJ49: HOGAR | AK49: TMCB | AL49: 241405 | AM49: 102.9 | AN49: PT | AO49: Medio
A50: 50CJQ | B50: Occidente | C50: Risaralda | D50: Dosquebradas | E50: COMUNA 5 | F50: 4 | G50: Av Santa Monica | H50: 0 | I50: Esquinero | J50: 128 | K50: 1124 | L50: 828 | M50: 52 | N50: 45220 | O50: 21 | P50: 11 | Q50: 31 | R50: 34 | S50: 4.8255751 | T50: -75.680493 | U50: =_xlfn.XLOOKUP(A50,'BD UM'!A:A,'BD UM'!B:B) -> 16259 | V50: =_xlfn.XLOOKUP(A50,'BD U6M'!A:A,'BD U6M'!B:B) -> 15878.5 | W50: =_xlfn.XLOOKUP(A50,'BD UM'!A:A,'BD UM'!C:C) -> 14319.9 | X50: =_xlfn.XLOOKUP(A50,'BD U6M'!A:A,'BD U6M'!C:C) -> 13400.9 | Y50: =_xlfn.XLOOKUP(A50,'BD UM'!A:A,'BD UM'!D:D) -> 232827.22 | Z50: =_xlfn.XLOOKUP(A50,'BD U6M'!A:A,'BD U6M'!D:D) -> 212786.33 | AA50: =_xlfn.XLOOKUP(A50,'BD UM'!A:A,'BD UM'!E:E) -> 13935.798 | AB50: =_xlfn.XLOOKUP(A50,'BD U6M'!A:A,'BD U6M'!E:E) -> 17169.766 | AC50: =_xlfn.XLOOKUP(A50,'BD UM'!A:A,'BD UM'!F:F) -> 88093.809 | AD50: =_xlfn.XLOOKUP(A50,'BD U6M'!A:A,'BD U6M'!F:F) -> 79281.743 | AE50: =_xlfn.XLOOKUP(A50,'BD UM'!A:A,'BD UM'!G:G) -> 7472.566 | AF50: =_xlfn.XLOOKUP(A50,'BD U6M'!A:A,'BD U6M'!G:G) -> 7554.3128 | AG50: =_xlfn.XLOOKUP(A50,'BD UM'!A:A,'BD UM'!H:H) -> 0 | AH50: COMERCIO/SERVICIO | AI50: ABIERTA | AJ50: BASE | AK50: TMCB | AL50: 232000 | AM50: 97.83 | AN50: Kennedy Cll 26 | AO50: Medio
A51: 5075T | B51: Centro Norte | C51: Cundinamarca | D51: Chía | E51: CHIA | F51: 3 | G51: Av. Pradilla | H51: 0 | I51: Esquinero | J51: 133.72 | K51: 189 | L51: 696 | M51: 0 | N51: 44688 | O51: 7 | P51: 25 | Q51: 31 | R51: 51 | S51: 4.8624682 | T51: -74.057385 | U51: =_xlfn.XLOOKUP(A51,'BD UM'!A:A,'BD UM'!B:B) -> 17874 | V51: =_xlfn.XLOOKUP(A51,'BD U6M'!A:A,'BD U6M'!B:B) -> 18629.5 | W51: =_xlfn.XLOOKUP(A51,'BD UM'!A:A,'BD UM'!C:C) -> 13193.6 | X51: =_xlfn.XLOOKUP(A51,'BD U6M'!A:A,'BD U6M'!C:C) -> 13259.9 | Y51: =_xlfn.XLOOKUP(A51,'BD UM'!A:A,'BD UM'!D:D) -> 235822.68 | Z51: =_xlfn.XLOOKUP(A51,'BD U6M'!A:A,'BD U6M'!D:D) -> 247025.58 | AA51: =_xlfn.XLOOKUP(A51,'BD UM'!A:A,'BD UM'!E:E) -> 13809.006 | AB51: =_xlfn.XLOOKUP(A51,'BD U6M'!A:A,'BD U6M'!E:E) -> 18065.564 | AC51: =_xlfn.XLOOKUP(A51,'BD UM'!A:A,'BD UM'!F:F) -> 80768.05 | AD51: =_xlfn.XLOOKUP(A51,'BD U6M'!A:A,'BD U6M'!F:F) -> 85485.262 | AE51: =_xlfn.XLOOKUP(A51,'BD UM'!A:A,'BD UM'!G:G) -> 12301.018 | AF51: =_xlfn.XLOOKUP(A51,'BD U6M'!A:A,'BD U6M'!G:G) -> 12345.304 | AG51: =_xlfn.XLOOKUP(A51,'BD UM'!A:A,'BD UM'!H:H) -> 0 | AH51: COMERCIO/SERVICIO | AI51: ABIERTA | AJ51: BASE | AK51: EXP 2025 | AL51: 232000 | AM51: 79.95 | AN51: Corales Cra 25 | AO51: Medio
A52: 50WLJ | B52: Centro Norte | C52: Distrito Capital | D52: Bogotá | E52: LA FLORESTA | F52: 3 | G52: Avenida Constitucion | H52: 0 | I52: Esquinero | J52: 110.35 | K52: 950 | L52: 1600 | M52: 78 | N52: 45322 | O52: 31 | P52: 1 | Q52: 31 | R52: 31 | S52: 4.692634 | T52: -74.077258 | U52: =_xlfn.XLOOKUP(A52,'BD UM'!A:A,'BD UM'!B:B) -> 16303 | V52: =_xlfn.XLOOKUP(A52,'BD U6M'!A:A,'BD U6M'!B:B) -> 16354.333 | W52: =_xlfn.XLOOKUP(A52,'BD UM'!A:A,'BD UM'!C:C) -> 11962.1 | X52: =_xlfn.XLOOKUP(A52,'BD U6M'!A:A,'BD U6M'!C:C) -> 12603.3 | Y52: =_xlfn.XLOOKUP(A52,'BD UM'!A:A,'BD UM'!D:D) -> 195017.52 | Z52: =_xlfn.XLOOKUP(A52,'BD U6M'!A:A,'BD U6M'!D:D) -> 206118.78 | AA52: =_xlfn.XLOOKUP(A52,'BD UM'!A:A,'BD UM'!E:E) -> 16489.128 | AB52: =_xlfn.XLOOKUP(A52,'BD U6M'!A:A,'BD U6M'!E:E) -> 16911.332 | AC52: =_xlfn.XLOOKUP(A52,'BD UM'!A:A,'BD UM'!F:F) -> 71292.055 | AD52: =_xlfn.XLOOKUP(A52,'BD U6M'!A:A,'BD U6M'!F:F) -> 72828.977 | AE52: =_xlfn.XLOOKUP(A52,'BD UM'!A:A,'BD UM'!G:G) -> 10796.208 | AF52: =_xlfn.XLOOKUP(A52,'BD U6M'!A:A,'BD U6M'!G:G) -> 10905.824 | AG52: =_xlfn.XLOOKUP(A52,'BD UM'!A:A,'BD UM'!H:H) -> 0 | AH52: BAJA DENSIDAD | AI52: ABIERTA | AJ52: HOGAR | AK52: TMCB | AL52: 241405 | AM52: 60.11 | AN52: Suba 103 | AO52: Medio
A53: 50QFF | B53: Occidente | C53: Caldas | D53: Manizales | E53: PALOGRANDE | F53: 6 | G53: Avenida Palermo | H53: JOSE GABRIEL RESTREPO SALAZAR | MARTIN ALONSO RESTREPO SALAZAR | CAMILO ANDRÉS LOPERA OSORNO | I53: Esquinero | J53: 128.83 | K53: 3330 | L53: 773 | M53: 46 | N53: 45747 | O53: 31 | P53: 1 | Q53: 31 | R53: 17 | S53: 5.052141 | T53: -75.487964 | U53: =_xlfn.XLOOKUP(A53,'BD UM'!A:A,'BD UM'!B:B) -> 9237 | V53: =_xlfn.XLOOKUP(A53,'BD U6M'!A:A,'BD U6M'!B:B) -> 12990.667 | W53: =_xlfn.XLOOKUP(A53,'BD UM'!A:A,'BD UM'!C:C) -> 13462.9 | X53: =_xlfn.XLOOKUP(A53,'BD U6M'!A:A,'BD U6M'!C:C) -> 13097 | Y53: =_xlfn.XLOOKUP(A53,'BD UM'!A:A,'BD UM'!D:D) -> 124357.2 | Z53: =_xlfn.XLOOKUP(A53,'BD U6M'!A:A,'BD U6M'!D:D) -> 170138.83 | AA53: =_xlfn.XLOOKUP(A53,'BD UM'!A:A,'BD UM'!E:E) -> -39076.49 | AB53: =_xlfn.XLOOKUP(A53,'BD U6M'!A:A,'BD U6M'!E:E) -> 5688.8766 | AC53: =_xlfn.XLOOKUP(A53,'BD UM'!A:A,'BD UM'!F:F) -> 48139.619 | AD53: =_xlfn.XLOOKUP(A53,'BD U6M'!A:A,'BD U6M'!F:F) -> 65114.983 | AE53: =_xlfn.XLOOKUP(A53,'BD UM'!A:A,'BD UM'!G:G) -> 10299.803 | AF53: =_xlfn.XLOOKUP(A53,'BD U6M'!A:A,'BD U6M'!G:G) -> 10405.254 | AG53: =_xlfn.XLOOKUP(A53,'BD UM'!A:A,'BD UM'!H:H) -> 1.1523 | AH53: ADMINISTRATIVO | AI53: ABIERTA | AJ53: RECESO | AK53: TMCB | AL53: 204160 | AM53: 72.73 | AN53: Carrera 9Qc | AO53: Medio
A54: 50NUQ | B54: Occidente | C54: Valle del Cauca | D54: Cali | E54: COMUNA 2 | F54: 4 | G54: Avenida Sexta | H54: 0 | I54: Esquinero | J54: 158.06 | K54: 512 | L54: 1400 | M54: 93 | N54: 45198 | O54: 29 | P54: 2 | Q54: 30 | R54: 35 | S54: 3.4714683 | T54: -76.526851 | U54: =_xlfn.XLOOKUP(A54,'BD UM'!A:A,'BD UM'!B:B) -> 17819 | V54: =_xlfn.XLOOKUP(A54,'BD U6M'!A:A,'BD U6M'!B:B) -> 17384.167 | W54: =_xlfn.XLOOKUP(A54,'BD UM'!A:A,'BD UM'!C:C) -> 12404.3 | X54: =_xlfn.XLOOKUP(A54,'BD U6M'!A:A,'BD U6M'!C:C) -> 12648.3 | Y54: =_xlfn.XLOOKUP(A54,'BD UM'!A:A,'BD UM'!D:D) -> 221032.16 | Z54: =_xlfn.XLOOKUP(A54,'BD U6M'!A:A,'BD U6M'!D:D) -> 219879.77 | AA54: =_xlfn.XLOOKUP(A54,'BD UM'!A:A,'BD UM'!E:E) -> 6326.556 | AB54: =_xlfn.XLOOKUP(A54,'BD U6M'!A:A,'BD U6M'!E:E) -> 11805.31 | AC54: =_xlfn.XLOOKUP(A54,'BD UM'!A:A,'BD UM'!F:F) -> 81892.249 | AD54: =_xlfn.XLOOKUP(A54,'BD U6M'!A:A,'BD U6M'!F:F) -> 80014.943 | AE54: =_xlfn.XLOOKUP(A54,'BD UM'!A:A,'BD UM'!G:G) -> 11671.889 | AF54: =_xlfn.XLOOKUP(A54,'BD U6M'!A:A,'BD U6M'!G:G) -> 11640.799 | AG54: =_xlfn.XLOOKUP(A54,'BD UM'!A:A,'BD UM'!H:H) -> 0 | AH54: COMERCIO/SERVICIO | AI54: ABIERTA | AJ54: BASE | AK54: TMCB | AL54: 241405 | AM54: 81.03 | AN54: Trivenza | AO54: Medio
A55: 50FG4 | B55: Occidente | C55: Risaralda | D55: Pereira | E55: EL JARDIN | F55: 4 | G55: Avenida Sur | H55: 0 | I55: Esquinero | J55: 93 | K55: 1006 | L55: 120 | M55: 60 | N55: 45138 | O55: 31 | P55: 1 | Q55: 31 | R55: 37 | S55: 4.808176 | T55: -75.710187 | U55: =_xlfn.XLOOKUP(A55,'BD UM'!A:A,'BD UM'!B:B) -> 16417 | V55: =_xlfn.XLOOKUP(A55,'BD U6M'!A:A,'BD U6M'!B:B) -> 14685.5 | W55: =_xlfn.XLOOKUP(A55,'BD UM'!A:A,'BD UM'!C:C) -> 16443.7 | X55: =_xlfn.XLOOKUP(A55,'BD U6M'!A:A,'BD U6M'!C:C) -> 15579.4 | Y55: =_xlfn.XLOOKUP(A55,'BD UM'!A:A,'BD UM'!D:D) -> 269955.85 | Z55: =_xlfn.XLOOKUP(A55,'BD U6M'!A:A,'BD U6M'!D:D) -> 228791.06 | AA55: =_xlfn.XLOOKUP(A55,'BD UM'!A:A,'BD UM'!E:E) -> 25465.017 | AB55: =_xlfn.XLOOKUP(A55,'BD U6M'!A:A,'BD U6M'!E:E) -> 18021.651 | AC55: =_xlfn.XLOOKUP(A55,'BD UM'!A:A,'BD UM'!F:F) -> 98822.026 | AD55: =_xlfn.XLOOKUP(A55,'BD U6M'!A:A,'BD U6M'!F:F) -> 81211.081 | AE55: =_xlfn.XLOOKUP(A55,'BD UM'!A:A,'BD UM'!G:G) -> 7853.666 | AF55: =_xlfn.XLOOKUP(A55,'BD U6M'!A:A,'BD U6M'!G:G) -> 7692.0371 | AG55: =_xlfn.XLOOKUP(A55,'BD UM'!A:A,'BD UM'!H:H) -> 0 | AH55: COMERCIO/SERVICIO | AI55: ABIERTA | AJ55: BASE | AK55: EXP 2024 | AL55: 232000 | AM55: 85.98 | AN55: Torres De Timiza | AO55: Alto
A56: 50W8O | B56: Occidente | C56: Antioquia | D56: Sabaneta | E56: SABANETA | F56: 4 | G56: Aves Maria | H56: RUTA INMOBILIARIA S.A.S. | I56: Esquinero | J56: 144.55 | K56: 3989 | L56: 260 | M56: 80 | N56: 45535 | O56: 31 | P56: 1 | Q56: 31 | R56: 24 | S56: 6.1474794 | T56: -75.616317 | U56: =_xlfn.XLOOKUP(A56,'BD UM'!A:A,'BD UM'!B:B) -> 16157 | V56: =_xlfn.XLOOKUP(A56,'BD U6M'!A:A,'BD U6M'!B:B) -> 15650.5 | W56: =_xlfn.XLOOKUP(A56,'BD UM'!A:A,'BD UM'!C:C) -> 13542.8 | X56: =_xlfn.XLOOKUP(A56,'BD U6M'!A:A,'BD U6M'!C:C) -> 13700.4 | Y56: =_xlfn.XLOOKUP(A56,'BD UM'!A:A,'BD UM'!D:D) -> 218810.22 | Z56: =_xlfn.XLOOKUP(A56,'BD U6M'!A:A,'BD U6M'!D:D) -> 214417.58 | AA56: =_xlfn.XLOOKUP(A56,'BD UM'!A:A,'BD UM'!E:E) -> 7450.294 | AB56: =_xlfn.XLOOKUP(A56,'BD U6M'!A:A,'BD U6M'!E:E) -> 9066.3201 | AC56: =_xlfn.XLOOKUP(A56,'BD UM'!A:A,'BD UM'!F:F) -> 83142.297 | AD56: =_xlfn.XLOOKUP(A56,'BD U6M'!A:A,'BD U6M'!F:F) -> 80493.151 | AE56: =_xlfn.XLOOKUP(A56,'BD UM'!A:A,'BD UM'!G:G) -> 13042.148 | AF56: =_xlfn.XLOOKUP(A56,'BD U6M'!A:A,'BD U6M'!G:G) -> 12654.818 | AG56: =_xlfn.XLOOKUP(A56,'BD UM'!A:A,'BD UM'!H:H) -> 0 | AH56: COMERCIO/SERVICIO | AI56: ABIERTA | AJ56: BASE | AK56: TMCB | AL56: 232000 | AM56: 104.52 | AN56: PT | AO56: Medio
A57: 502JA | B57: Centro Norte | C57: Distrito Capital | D57: Bogotá | E57: CASA BLANCA SUBA | F57: 4 | G57: Bacata | H57: 0 | I57: Medianero | J57: 103.31 | K57: 3124 | L57: 309 | M57: 0 | N57: 44659 | O57: 8 | P57: 23 | Q57: 30 | R57: 52 | S57: 4.7495652 | T57: -74.067825 | U57: =_xlfn.XLOOKUP(A57,'BD UM'!A:A,'BD UM'!B:B) -> 17576 | V57: =_xlfn.XLOOKUP(A57,'BD U6M'!A:A,'BD U6M'!B:B) -> 18327.167 | W57: =_xlfn.XLOOKUP(A57,'BD UM'!A:A,'BD UM'!C:C) -> 15297.4 | X57: =_xlfn.XLOOKUP(A57,'BD U6M'!A:A,'BD U6M'!C:C) -> 15474.3 | Y57: =_xlfn.XLOOKUP(A57,'BD UM'!A:A,'BD UM'!D:D) -> 268866.55 | Z57: =_xlfn.XLOOKUP(A57,'BD U6M'!A:A,'BD U6M'!D:D) -> 283600.62 | AA57: =_xlfn.XLOOKUP(A57,'BD UM'!A:A,'BD UM'!E:E) -> 22453.634 | AB57: =_xlfn.XLOOKUP(A57,'BD U6M'!A:A,'BD U6M'!E:E) -> 27291.494 | AC57: =_xlfn.XLOOKUP(A57,'BD UM'!A:A,'BD UM'!F:F) -> 91670.293 | AD57: =_xlfn.XLOOKUP(A57,'BD U6M'!A:A,'BD U6M'!F:F) -> 95738.477 | AE57: =_xlfn.XLOOKUP(A57,'BD UM'!A:A,'BD UM'!G:G) -> 9410.748 | AF57: =_xlfn.XLOOKUP(A57,'BD U6M'!A:A,'BD U6M'!G:G) -> 9508.7469 | AG57: =_xlfn.XLOOKUP(A57,'BD UM'!A:A,'BD UM'!H:H) -> 0 | AH57: COMERCIO/SERVICIO | AI57: ABIERTA | AJ57: BASE | AK57: TMCB | AL57: 232000 | AM57: 158.35 | AN57: PT | AO57: Medio
A58: 5053N | B58: Centro Sur | C58: Distrito Capital | D58: Bogotá | E58: MODELIA | F58: 4 | G58: Baleares | H58: 0 | I58: Esquinero | J58: 94.07 | K58: 803 | L58: 186 | M58: 52 | N58: 44645 | O58: 25 | P58: 7 | Q58: 31 | R58: 53 | S58: 4.6652991 | T58: -74.126901 | U58: =_xlfn.XLOOKUP(A58,'BD UM'!A:A,'BD UM'!B:B) -> 18711 | V58: =_xlfn.XLOOKUP(A58,'BD U6M'!A:A,'BD U6M'!B:B) -> 17786.667 | W58: =_xlfn.XLOOKUP(A58,'BD UM'!A:A,'BD UM'!C:C) -> 12002.1 | X58: =_xlfn.XLOOKUP(A58,'BD U6M'!A:A,'BD U6M'!C:C) -> 12843.3 | Y58: =_xlfn.XLOOKUP(A58,'BD UM'!A:A,'BD UM'!D:D) -> 224571.66 | Z58: =_xlfn.XLOOKUP(A58,'BD U6M'!A:A,'BD U6M'!D:D) -> 228440.32 | AA58: =_xlfn.XLOOKUP(A58,'BD UM'!A:A,'BD UM'!E:E) -> 25040.069 | AB58: =_xlfn.XLOOKUP(A58,'BD U6M'!A:A,'BD U6M'!E:E) -> 20584.723 | AC58: =_xlfn.XLOOKUP(A58,'BD UM'!A:A,'BD UM'!F:F) -> 78934.236 | AD58: =_xlfn.XLOOKUP(A58,'BD U6M'!A:A,'BD U6M'!F:F) -> 77961.104 | AE58: =_xlfn.XLOOKUP(A58,'BD UM'!A:A,'BD UM'!G:G) -> 9977.492 | AF58: =_xlfn.XLOOKUP(A58,'BD U6M'!A:A,'BD U6M'!G:G) -> 10080.243 | AG58: =_xlfn.XLOOKUP(A58,'BD UM'!A:A,'BD UM'!H:H) -> 0 | AH58: COMERCIO/SERVICIO | AI58: ABIERTA | AJ58: RECESO | AK58: TMCB | AL58: 204160 | AM58: 127.59 | AN58: Javeriana | AO58: Alto
A59: 50TLI | B59: Occidente | C59: Quindío | D59: Armenia | E59: EL CAFETERO | F59: 4 | G59: Banca Armenia | H59: 0 | I59: Esquinero | J59: 95.32 | K59: 445 | L59: 1705 | M59: 35 | N59: 45422 | O59: 10 | P59: 22 | Q59: 31 | R59: 27 | S59: 4.5381847 | T59: -75.667464 | U59: =_xlfn.XLOOKUP(A59,'BD UM'!A:A,'BD UM'!B:B) -> 21781 | V59: =_xlfn.XLOOKUP(A59,'BD U6M'!A:A,'BD U6M'!B:B) -> 20536.833 | W59: =_xlfn.XLOOKUP(A59,'BD UM'!A:A,'BD UM'!C:C) -> 10152.4 | X59: =_xlfn.XLOOKUP(A59,'BD U6M'!A:A,'BD U6M'!C:C) -> 10137 | Y59: =_xlfn.XLOOKUP(A59,'BD UM'!A:A,'BD UM'!D:D) -> 221130.02 | Z59: =_xlfn.XLOOKUP(A59,'BD U6M'!A:A,'BD U6M'!D:D) -> 208181.45 | AA59: =_xlfn.XLOOKUP(A59,'BD UM'!A:A,'BD UM'!E:E) -> 8561.407 | AB59: =_xlfn.XLOOKUP(A59,'BD U6M'!A:A,'BD U6M'!E:E) -> 12304.368 | AC59: =_xlfn.XLOOKUP(A59,'BD UM'!A:A,'BD UM'!F:F) -> 88206.763 | AD59: =_xlfn.XLOOKUP(A59,'BD U6M'!A:A,'BD U6M'!F:F) -> 81202.64 | AE59: =_xlfn.XLOOKUP(A59,'BD UM'!A:A,'BD UM'!G:G) -> 12162.172 | AF59: =_xlfn.XLOOKUP(A59,'BD U6M'!A:A,'BD U6M'!G:G) -> 12169.439 | AG59: =_xlfn.XLOOKUP(A59,'BD UM'!A:A,'BD UM'!H:H) -> 0 | AH59: EDUCACION | AI59: ABIERTA | AJ59: BASE | AK59: TMCB | AL59: 232000 | AM59: 136.08 | AN59: PT | AO59: Medio
A60: 50M68 | B60: Centro Norte | C60: Cundinamarca | D60: Chía | E60: CHIA | F60: 4 | G60: Barcelona | H60: 0 | I60: Esquinero | J60: 119.01 | K60: 162 | L60: 278 | M60: 0 | N60: 44617 | O60: 25 | P60: 4 | Q60: 28 | R60: 54 | S60: 4.8653731 | T60: -74.0389 | U60: =_xlfn.XLOOKUP(A60,'BD UM'!A:A,'BD UM'!B:B) -> 17946 | V60: =_xlfn.XLOOKUP(A60,'BD U6M'!A:A,'BD U6M'!B:B) -> 17504 | W60: =_xlfn.XLOOKUP(A60,'BD UM'!A:A,'BD UM'!C:C) -> 12265.3 | X60: =_xlfn.XLOOKUP(A60,'BD U6M'!A:A,'BD U6M'!C:C) -> 11807.8 | Y60: =_xlfn.XLOOKUP(A60,'BD UM'!A:A,'BD UM'!D:D) -> 220112.56 | Z60: =_xlfn.XLOOKUP(A60,'BD U6M'!A:A,'BD U6M'!D:D) -> 206683.5 | AA60: =_xlfn.XLOOKUP(A60,'BD UM'!A:A,'BD UM'!E:E) -> 23565.957 | AB60: =_xlfn.XLOOKUP(A60,'BD U6M'!A:A,'BD U6M'!E:E) -> 19945.961 | AC60: =_xlfn.XLOOKUP(A60,'BD UM'!A:A,'BD UM'!F:F) -> 85064.077 | AD60: =_xlfn.XLOOKUP(A60,'BD U6M'!A:A,'BD U6M'!F:F) -> 79723.117 | AE60: =_xlfn.XLOOKUP(A60,'BD UM'!A:A,'BD UM'!G:G) -> 11053.881 | AF60: =_xlfn.XLOOKUP(A60,'BD U6M'!A:A,'BD U6M'!G:G) -> 10992.268 | AG60: =_xlfn.XLOOKUP(A60,'BD UM'!A:A,'BD UM'!H:H) -> 0 | AH60: COMERCIO/SERVICIO | AI60: ABIERTA | AJ60: BASE | AK60: TMCB | AL60: 232000 | AM60: 113.31 | AN60: Chapinero | AO60: Medio
A61: 50APD | B61: Centro Sur | C61: Distrito Capital | D61: Bogotá | E61: CASTILLA | F61: 3 | G61: Barrio Bavaria | H61: 0 | I61: Esquinero | J61: 103.73 | K61: 1533 | L61: 600 | M61: 75 | N61: 44757 | O61: 15 | P61: 17 | Q61: 31 | R61: 49 | S61: 4.6416209 | T61: -74.140104 | U61: =_xlfn.XLOOKUP(A61,'BD UM'!A:A,'BD UM'!B:B) -> 15822 | V61: =_xlfn.XLOOKUP(A61,'BD U6M'!A:A,'BD U6M'!B:B) -> 16703 | W61: =_xlfn.XLOOKUP(A61,'BD UM'!A:A,'BD UM'!C:C) -> 14310.1 | X61: =_xlfn.XLOOKUP(A61,'BD U6M'!A:A,'BD U6M'!C:C) -> 14032.8 | Y61: =_xlfn.XLOOKUP(A61,'BD UM'!A:A,'BD UM'!D:D) -> 226414.24 | Z61: =_xlfn.XLOOKUP(A61,'BD U6M'!A:A,'BD U6M'!D:D) -> 234389.51 | AA61: =_xlfn.XLOOKUP(A61,'BD UM'!A:A,'BD UM'!E:E) -> 12459.093 | AB61: =_xlfn.XLOOKUP(A61,'BD U6M'!A:A,'BD U6M'!E:E) -> 15128.544 | AC61: =_xlfn.XLOOKUP(A61,'BD UM'!A:A,'BD UM'!F:F) -> 69362.997 | AD61: =_xlfn.XLOOKUP(A61,'BD U6M'!A:A,'BD U6M'!F:F) -> 74531.438 | AE61: =_xlfn.XLOOKUP(A61,'BD UM'!A:A,'BD UM'!G:G) -> 11754.308 | AF61: =_xlfn.XLOOKUP(A61,'BD U6M'!A:A,'BD U6M'!G:G) -> 11678.55 | AG61: =_xlfn.XLOOKUP(A61,'BD UM'!A:A,'BD UM'!H:H) -> 0 | AH61: COMERCIO/SERVICIO | AI61: ABIERTA | AJ61: BASE | AK61: TMCB | AL61: 232000 | AM61: 61.61 | AN61: Giron El Poblado | AO61: Medio
A62: 50M25 | B62: Centro Sur | C62: Cundinamarca | D62: Melgar | E62: MELGAR | F62: 3 | G62: Base Aerea | H62: 0 | I62: Esquinero | J62: 71.79 | K62: 1134 | L62: 400 | M62: 33 | N62: 45377 | O62: 26 | P62: 6 | Q62: 31 | R62: 29 | S62: 4.210173 | T62: -74.634124 | U62: =_xlfn.XLOOKUP(A62,'BD UM'!A:A,'BD UM'!B:B) -> 20206 | V62: =_xlfn.XLOOKUP(A62,'BD U6M'!A:A,'BD U6M'!B:B) -> 18578.333 | W62: =_xlfn.XLOOKUP(A62,'BD UM'!A:A,'BD UM'!C:C) -> 16703.4 | X62: =_xlfn.XLOOKUP(A62,'BD U6M'!A:A,'BD U6M'!C:C) -> 17024.4 | Y62: =_xlfn.XLOOKUP(A62,'BD UM'!A:A,'BD UM'!D:D) -> 337508.09 | Z62: =_xlfn.XLOOKUP(A62,'BD U6M'!A:A,'BD U6M'!D:D) -> 316284.51 | AA62: =_xlfn.XLOOKUP(A62,'BD UM'!A:A,'BD UM'!E:E) -> 48153.482 | AB62: =_xlfn.XLOOKUP(A62,'BD U6M'!A:A,'BD U6M'!E:E) -> 39893.539 | AC62: =_xlfn.XLOOKUP(A62,'BD UM'!A:A,'BD UM'!F:F) -> 116629.77 | AD62: =_xlfn.XLOOKUP(A62,'BD U6M'!A:A,'BD U6M'!F:F) -> 105530.42 | AE62: =_xlfn.XLOOKUP(A62,'BD UM'!A:A,'BD UM'!G:G) -> 4422.608 | AF62: =_xlfn.XLOOKUP(A62,'BD U6M'!A:A,'BD U6M'!G:G) -> 4478.7807 | AG62: =_xlfn.XLOOKUP(A62,'BD UM'!A:A,'BD UM'!H:H) -> 0 | AH62: BAJA DENSIDAD | AI62: ABIERTA | AJ62: HOGAR | AK62: EXP 2025 | AL62: 241405 | AM62: 69 | AN62: La Victoria | AO62: Medio
A63: 50U9Q | B63: Norte | C63: Atlántico | D63: Barranquilla | E63: CENTRO HISTORICO | F63: 4 | G63: Batallón Paraiso | H63: PATRICIA CHING LAW | I63: Esquinero | J63: 129.47 | K63: 1712 | L63: 370 | M63: 90 | N63: 45743 | O63: 27 | P63: 5 | Q63: 31 | R63: 17 | S63: 11.013806 | T63: -74.805783 | U63: =_xlfn.XLOOKUP(A63,'BD UM'!A:A,'BD UM'!B:B) -> 14633 | V63: =_xlfn.XLOOKUP(A63,'BD U6M'!A:A,'BD U6M'!B:B) -> 14070.833 | W63: =_xlfn.XLOOKUP(A63,'BD UM'!A:A,'BD UM'!C:C) -> 13029.9 | X63: =_xlfn.XLOOKUP(A63,'BD U6M'!A:A,'BD U6M'!C:C) -> 13022.7 | Y63: =_xlfn.XLOOKUP(A63,'BD UM'!A:A,'BD UM'!D:D) -> 190667.1 | Z63: =_xlfn.XLOOKUP(A63,'BD U6M'!A:A,'BD U6M'!D:D) -> 183240.26 | AA63: =_xlfn.XLOOKUP(A63,'BD UM'!A:A,'BD UM'!E:E) -> 6645.546 | AB63: =_xlfn.XLOOKUP(A63,'BD U6M'!A:A,'BD U6M'!E:E) -> 8449.6522 | AC63: =_xlfn.XLOOKUP(A63,'BD UM'!A:A,'BD UM'!F:F) -> 70255.266 | AD63: =_xlfn.XLOOKUP(A63,'BD U6M'!A:A,'BD U6M'!F:F) -> 65025.533 | AE63: =_xlfn.XLOOKUP(A63,'BD UM'!A:A,'BD UM'!G:G) -> 8933.5 | AF63: =_xlfn.XLOOKUP(A63,'BD U6M'!A:A,'BD U6M'!G:G) -> 9027.4969 | AG63: =_xlfn.XLOOKUP(A63,'BD UM'!A:A,'BD UM'!H:H) -> 1.3207 | AH63: COMERCIO/SERVICIO | AI63: ABIERTA | AJ63: BASE | AK63: TMCB | AL63: 232000 | AM63: 104.2 | AN63: Shaio | AO63: Medio
A64: 50J37 | B64: Centro Norte | C64: Distrito Capital | D64: Bogotá | E64: LA ALHAMBRA | F64: 3 | G64: Batan | H64: 0 | I64: Esquinero | J64: 120.55 | K64: 66 | L64: 2207 | M64: 125 | N64: 43763 | O64: 25 | P64: 7 | Q64: 31 | R64: 82 | S64: 4.705361 | T64: -74.055264 | U64: =_xlfn.XLOOKUP(A64,'BD UM'!A:A,'BD UM'!B:B) -> 24868 | V64: =_xlfn.XLOOKUP(A64,'BD U6M'!A:A,'BD U6M'!B:B) -> 25398.333 | W64: =_xlfn.XLOOKUP(A64,'BD UM'!A:A,'BD UM'!C:C) -> 11382.6 | X64: =_xlfn.XLOOKUP(A64,'BD U6M'!A:A,'BD U6M'!C:C) -> 11464.9 | Y64: =_xlfn.XLOOKUP(A64,'BD UM'!A:A,'BD UM'!D:D) -> 283061.91 | Z64: =_xlfn.XLOOKUP(A64,'BD U6M'!A:A,'BD U6M'!D:D) -> 291190.34 | AA64: =_xlfn.XLOOKUP(A64,'BD UM'!A:A,'BD UM'!E:E) -> 31788.017 | AB64: =_xlfn.XLOOKUP(A64,'BD U6M'!A:A,'BD U6M'!E:E) -> 33873.967 | AC64: =_xlfn.XLOOKUP(A64,'BD UM'!A:A,'BD UM'!F:F) -> 99727.866 | AD64: =_xlfn.XLOOKUP(A64,'BD U6M'!A:A,'BD U6M'!F:F) -> 103195.08 | AE64: =_xlfn.XLOOKUP(A64,'BD UM'!A:A,'BD UM'!G:G) -> 12560.877 | AF64: =_xlfn.XLOOKUP(A64,'BD U6M'!A:A,'BD U6M'!G:G) -> 12685.29 | AG64: =_xlfn.XLOOKUP(A64,'BD UM'!A:A,'BD UM'!H:H) -> 0 | AH64: ADMINISTRATIVO | AI64: ABIERTA | AJ64: BASE | AK64: EXP 2024 | AL64: 204160 | AM64: 63.65 | AN64: Morato | AO64: Medio
A65: 50BAX | B65: Centro Norte | C65: Boyacá | D65: Tunja | E65: NORORIENTAL (3) | F65: 4 | G65: Bávaro Plaza | H65: CARLOS ELIAS ROJAS LOZANO | I65: Esquinero | J65: 123.95 | K65: 658 | L65: 1804 | M65: 33 | N65: 45611 | O65: 15 | P65: 16 | Q65: 30 | R65: 21 | S65: 5.5515005 | T65: -73.34665 | U65: =_xlfn.XLOOKUP(A65,'BD UM'!A:A,'BD UM'!B:B) -> 16318 | V65: =_xlfn.XLOOKUP(A65,'BD U6M'!A:A,'BD U6M'!B:B) -> 14634.167 | W65: =_xlfn.XLOOKUP(A65,'BD UM'!A:A,'BD UM'!C:C) -> 14292.7 | X65: =_xlfn.XLOOKUP(A65,'BD U6M'!A:A,'BD U6M'!C:C) -> 14676.8 | Y65: =_xlfn.XLOOKUP(A65,'BD UM'!A:A,'BD UM'!D:D) -> 233229 | Z65: =_xlfn.XLOOKUP(A65,'BD U6M'!A:A,'BD U6M'!D:D) -> 214782.25 | AA65: =_xlfn.XLOOKUP(A65,'BD UM'!A:A,'BD UM'!E:E) -> 32114.786 | AB65: =_xlfn.XLOOKUP(A65,'BD U6M'!A:A,'BD U6M'!E:E) -> 24428.007 | AC65: =_xlfn.XLOOKUP(A65,'BD UM'!A:A,'BD UM'!F:F) -> 86959.688 | AD65: =_xlfn.XLOOKUP(A65,'BD U6M'!A:A,'BD U6M'!F:F) -> 80070.982 | AE65: =_xlfn.XLOOKUP(A65,'BD UM'!A:A,'BD UM'!G:G) -> 7890 | AF65: =_xlfn.XLOOKUP(A65,'BD U6M'!A:A,'BD U6M'!G:G) -> 7975.2471 | AG65: =_xlfn.XLOOKUP(A65,'BD UM'!A:A,'BD UM'!H:H) -> 0 | AH65: ALTA DENSIDAD | AI65: ABIERTA | AJ65: HOGAR | AK65: TMCB | AL65: 241405 | AM65: 63.12 | AN65: Cedritos | AO65: Medio
A66: 50E5U | B66: Centro Norte | C66: Distrito Capital | D66: Bogotá | E66: SAN JOSE DE BAVARIA | F66: 4 | G66: Baviera 174 | H66: 0 | I66: Esquinero | J66: 200.68 | K66: 2300 | L66: 550 | M66: 56 | N66: 44740 | O66: 28 | P66: 3 | Q66: 30 | R66: 50 | S66: 4.7557636 | T66: -74.050162 | U66: =_xlfn.XLOOKUP(A66,'BD UM'!A:A,'BD UM'!B:B) -> 15745 | V66: =_xlfn.XLOOKUP(A66,'BD U6M'!A:A,'BD U6M'!B:B) -> 15852.167 | W66: =_xlfn.XLOOKUP(A66,'BD UM'!A:A,'BD UM'!C:C) -> 14855.1 | X66: =_xlfn.XLOOKUP(A66,'BD U6M'!A:A,'BD U6M'!C:C) -> 14859.8 | Y66: =_xlfn.XLOOKUP(A66,'BD UM'!A:A,'BD UM'!D:D) -> 233893.25 | Z66: =_xlfn.XLOOKUP(A66,'BD U6M'!A:A,'BD U6M'!D:D) -> 235560.4 | AA66: =_xlfn.XLOOKUP(A66,'BD UM'!A:A,'BD UM'!E:E) -> 17758.332 | AB66: =_xlfn.XLOOKUP(A66,'BD U6M'!A:A,'BD U6M'!E:E) -> 15106.631 | AC66: =_xlfn.XLOOKUP(A66,'BD UM'!A:A,'BD UM'!F:F) -> 79473.705 | AD66: =_xlfn.XLOOKUP(A66,'BD U6M'!A:A,'BD U6M'!F:F) -> 78737.448 | AE66: =_xlfn.XLOOKUP(A66,'BD UM'!A:A,'BD UM'!G:G) -> 12666.416 | AF66: =_xlfn.XLOOKUP(A66,'BD U6M'!A:A,'BD U6M'!G:G) -> 12593.8 | AG66: =_xlfn.XLOOKUP(A66,'BD UM'!A:A,'BD UM'!H:H) -> 0 | AH66: COMERCIO/SERVICIO | AI66: ABIERTA | AJ66: BASE | AK66: EXP 2025 | AL66: 232000 | AM66: 95.68 | AN66: Calle 116 | AO66: Alto
A67: 50OSX | B67: Centro Norte | C67: Distrito Capital | D67: Bogotá | E67: USAQUEN | F67: 5 | G67: Bella Suiza 127 | H67: ADMINISTRACIÓN INMOBILIARIA EDIFICIO EL GALEÓN BOGOTA S.A.S | I67: Esquinero | J67: 123.03 | K67: 1921 | L67: 2180 | M67: 48 | N67: 45777 | O67: 30 | P67: 1 | Q67: 30 | R67: 16 | S67: 4.7027451 | T67: -74.0298 | U67: =_xlfn.XLOOKUP(A67,'BD UM'!A:A,'BD UM'!B:B) -> 19346 | V67: =_xlfn.XLOOKUP(A67,'BD U6M'!A:A,'BD U6M'!B:B) -> 18680.5 | W67: =_xlfn.XLOOKUP(A67,'BD UM'!A:A,'BD UM'!C:C) -> 12080 | X67: =_xlfn.XLOOKUP(A67,'BD U6M'!A:A,'BD U6M'!C:C) -> 12449.5 | Y67: =_xlfn.XLOOKUP(A67,'BD UM'!A:A,'BD UM'!D:D) -> 233699.55 | Z67: =_xlfn.XLOOKUP(A67,'BD U6M'!A:A,'BD U6M'!D:D) -> 232563.78 | AA67: =_xlfn.XLOOKUP(A67,'BD UM'!A:A,'BD UM'!E:E) -> 30234.952 | AB67: =_xlfn.XLOOKUP(A67,'BD U6M'!A:A,'BD U6M'!E:E) -> 27566.264 | AC67: =_xlfn.XLOOKUP(A67,'BD UM'!A:A,'BD UM'!F:F) -> 90839.731 | AD67: =_xlfn.XLOOKUP(A67,'BD U6M'!A:A,'BD U6M'!F:F) -> 89746.814 | AE67: =_xlfn.XLOOKUP(A67,'BD UM'!A:A,'BD UM'!G:G) -> 11771.2 | AF67: =_xlfn.XLOOKUP(A67,'BD U6M'!A:A,'BD U6M'!G:G) -> 11772.421 | AG67: =_xlfn.XLOOKUP(A67,'BD UM'!A:A,'BD UM'!H:H) -> 1.5369 | AH67: ALTA DENSIDAD | AI67: ABIERTA | AJ67: HOGAR | AK67: TMCB | AL67: 241405 | AM67: 104.9 | AN67: Suba 103 | AO67: Bajo
A68: 50ZEL | B68: Centro Norte | C68: Distrito Capital | D68: Bogotá | E68: MINUTO DE DIOS | F68: 3 | G68: Belmonte | H68: 0 | I68: Esquinero | J68: 84.32 | K68: 3977 | L68: 359 | M68: 0 | N68: 45341 | O68: 19 | P68: 11 | Q68: 29 | R68: 30 | S68: 4.7034935 | T68: -74.092133 | U68: =_xlfn.XLOOKUP(A68,'BD UM'!A:A,'BD UM'!B:B) -> 13372 | V68: =_xlfn.XLOOKUP(A68,'BD U6M'!A:A,'BD U6M'!B:B) -> 13485.667 | W68: =_xlfn.XLOOKUP(A68,'BD UM'!A:A,'BD UM'!C:C) -> 13389.7 | X68: =_xlfn.XLOOKUP(A68,'BD U6M'!A:A,'BD U6M'!C:C) -> 13204.3 | Y68: =_xlfn.XLOOKUP(A68,'BD UM'!A:A,'BD UM'!D:D) -> 179046.89 | Z68: =_xlfn.XLOOKUP(A68,'BD U6M'!A:A,'BD U6M'!D:D) -> 178068.31 | AA68: =_xlfn.XLOOKUP(A68,'BD UM'!A:A,'BD UM'!E:E) -> 3131.419 | AB68: =_xlfn.XLOOKUP(A68,'BD U6M'!A:A,'BD U6M'!E:E) -> 2643.6446 | AC68: =_xlfn.XLOOKUP(A68,'BD UM'!A:A,'BD UM'!F:F) -> 57841.19 | AD68: =_xlfn.XLOOKUP(A68,'BD U6M'!A:A,'BD U6M'!F:F) -> 56907.734 | AE68: =_xlfn.XLOOKUP(A68,'BD UM'!A:A,'BD UM'!G:G) -> 8845.216 | AF68: =_xlfn.XLOOKUP(A68,'BD U6M'!A:A,'BD U6M'!G:G) -> 8938.4727 | AG68: =_xlfn.XLOOKUP(A68,'BD UM'!A:A,'BD UM'!H:H) -> 0 | AH68: COMERCIO/SERVICIO | AI68: ABIERTA | AJ68: RECESO | AK68: EXP 2024 | AL68: 204160 | AM68: 63.8 | AN68: Dorado Plaza | AO68: Alto
A69: 50T52 | B69: Norte | C69: Atlántico | D69: Barranquilla | E69: RIOMAR | F69: 6 | G69: Blue Gardens | H69: HERNANDO HEREDIA ARQUITECTOS S.A.S | I69: Medianero | J69: 160.24 | K69: 128 | L69: 3920 | M69: 71 | N69: 45621 | O69: 25 | P69: 6 | Q69: 30 | R69: 21 | S69: 11.016161 | T69: -74.831158 | U69: =_xlfn.XLOOKUP(A69,'BD UM'!A:A,'BD UM'!B:B) -> 19778 | V69: =_xlfn.XLOOKUP(A69,'BD U6M'!A:A,'BD U6M'!B:B) -> 19017 | W69: =_xlfn.XLOOKUP(A69,'BD UM'!A:A,'BD UM'!C:C) -> 11959.6 | X69: =_xlfn.XLOOKUP(A69,'BD U6M'!A:A,'BD U6M'!C:C) -> 12001.2 | Y69: =_xlfn.XLOOKUP(A69,'BD UM'!A:A,'BD UM'!D:D) -> 236536.56 | Z69: =_xlfn.XLOOKUP(A69,'BD U6M'!A:A,'BD U6M'!D:D) -> 228226.48 | AA69: =_xlfn.XLOOKUP(A69,'BD UM'!A:A,'BD UM'!E:E) -> 11307.785 | AB69: =_xlfn.XLOOKUP(A69,'BD U6M'!A:A,'BD U6M'!E:E) -> 13241.415 | AC69: =_xlfn.XLOOKUP(A69,'BD UM'!A:A,'BD UM'!F:F) -> 91443.951 | AD69: =_xlfn.XLOOKUP(A69,'BD U6M'!A:A,'BD U6M'!F:F) -> 87294.452 | AE69: =_xlfn.XLOOKUP(A69,'BD UM'!A:A,'BD UM'!G:G) -> 10223.409 | AF69: =_xlfn.XLOOKUP(A69,'BD U6M'!A:A,'BD U6M'!G:G) -> 10328.223 | AG69: =_xlfn.XLOOKUP(A69,'BD UM'!A:A,'BD UM'!H:H) -> 0 | AH69: ADMINISTRATIVO | AI69: ABIERTA | AJ69: RECESO | AK69: EXP 2025 | AL69: 204160 | AM69: 101.75 | AN69: Torre Americas | AO69: Alto
A70: 501CC | B70: Centro Sur | C70: Distrito Capital | D70: Bogotá | E70: LAS FERIAS | F70: 3 | G70: Bonanza | H70: 0 | I70: Esquinero | J70: 154.59 | K70: 1231 | L70: 1280 | M70: 79 | N70: 44831 | O70: 27 | P70: 4 | Q70: 30 | R70: 47 | S70: 4.6845161 | T70: -74.091865 | U70: =_xlfn.XLOOKUP(A70,'BD UM'!A:A,'BD UM'!B:B) -> 15134 | V70: =_xlfn.XLOOKUP(A70,'BD U6M'!A:A,'BD U6M'!B:B) -> 14891.833 | W70: =_xlfn.XLOOKUP(A70,'BD UM'!A:A,'BD UM'!C:C) -> 11694.6 | X70: =_xlfn.XLOOKUP(A70,'BD U6M'!A:A,'BD U6M'!C:C) -> 11535.1 | Y70: =_xlfn.XLOOKUP(A70,'BD UM'!A:A,'BD UM'!D:D) -> 176985.86 | Z70: =_xlfn.XLOOKUP(A70,'BD U6M'!A:A,'BD U6M'!D:D) -> 171778.09 | AA70: =_xlfn.XLOOKUP(A70,'BD UM'!A:A,'BD UM'!E:E) -> -146.356 | AB70: =_xlfn.XLOOKUP(A70,'BD U6M'!A:A,'BD U6M'!E:E) -> 3730.2404 | AC70: =_xlfn.XLOOKUP(A70,'BD UM'!A:A,'BD UM'!F:F) -> 56284.518 | AD70: =_xlfn.XLOOKUP(A70,'BD U6M'!A:A,'BD U6M'!F:F) -> 55512.077 | AE70: =_xlfn.XLOOKUP(A70,'BD UM'!A:A,'BD UM'!G:G) -> 10134.782 | AF70: =_xlfn.XLOOKUP(A70,'BD U6M'!A:A,'BD U6M'!G:G) -> 9917.8551 | AG70: =_xlfn.XLOOKUP(A70,'BD UM'!A:A,'BD UM'!H:H) -> 0 | AH70: COMERCIO/SERVICIO | AI70: ABIERTA | AJ70: BASE | AK70: TMCB | AL70: 232000 | AM70: 63.09 | AN70: Chapinero | AO70: Bajo
A71: 50ZRH | B71: Centro Sur | C71: Distrito Capital | D71: Bogotá | E71: ISMAEL PERDOMO | F71: 2 | G71: Bonavista | H71: 0 | I71: Esquinero | J71: 181.13 | K71: 3390 | L71: 141 | M71: 0 | N71: 42492 | O71: 2 | P71: 30 | Q71: 31 | R71: 114 | S71: 4.5890962 | T71: -74.162378 | U71: =_xlfn.XLOOKUP(A71,'BD UM'!A:A,'BD UM'!B:B) -> 25656 | V71: =_xlfn.XLOOKUP(A71,'BD U6M'!A:A,'BD U6M'!B:B) -> 26600.833 | W71: =_xlfn.XLOOKUP(A71,'BD UM'!A:A,'BD UM'!C:C) -> 16256.1 | X71: =_xlfn.XLOOKUP(A71,'BD U6M'!A:A,'BD U6M'!C:C) -> 18222.8 | Y71: =_xlfn.XLOOKUP(A71,'BD UM'!A:A,'BD UM'!D:D) -> 417065.63 | Z71: =_xlfn.XLOOKUP(A71,'BD U6M'!A:A,'BD U6M'!D:D) -> 484742.52 | AA71: =_xlfn.XLOOKUP(A71,'BD UM'!A:A,'BD UM'!E:E) -> 45967.757 | AB71: =_xlfn.XLOOKUP(A71,'BD U6M'!A:A,'BD U6M'!E:E) -> 65924.245 | AC71: =_xlfn.XLOOKUP(A71,'BD UM'!A:A,'BD UM'!F:F) -> 130647.11 | AD71: =_xlfn.XLOOKUP(A71,'BD U6M'!A:A,'BD U6M'!F:F) -> 153306.06 | AE71: =_xlfn.XLOOKUP(A71,'BD UM'!A:A,'BD UM'!G:G) -> 11377.119 | AF71: =_xlfn.XLOOKUP(A71,'BD U6M'!A:A,'BD U6M'!G:G) -> 11116.038 | AG71: =_xlfn.XLOOKUP(A71,'BD UM'!A:A,'BD UM'!H:H) -> 0 | AH71: COMERCIO/SERVICIO | AI71: ABIERTA | AJ71: BASE | AK71: TMCB | AL71: 232000 | AM71: 71.5 | AN71: PT | AO71: Medio
A72: 50K7R | B72: Centro Sur | C72: Distrito Capital | D72: Bogotá | E72: BOSA CENTRAL | F72: 3 | G72: Bosa Los Naranjos | H72: 0 | I72: Esquinero | J72: 109.28 | K72: 1242 | L72: 884 | M72: 62 | N72: 45094 | O72: 17 | P72: 14 | Q72: 30 | R72: 38 | S72: 4.6048265 | T72: -74.196243 | U72: =_xlfn.XLOOKUP(A72,'BD UM'!A:A,'BD UM'!B:B) -> 20398 | V72: =_xlfn.XLOOKUP(A72,'BD U6M'!A:A,'BD U6M'!B:B) -> 18488.5 | W72: =_xlfn.XLOOKUP(A72,'BD UM'!A:A,'BD UM'!C:C) -> 13770.5 | X72: =_xlfn.XLOOKUP(A72,'BD U6M'!A:A,'BD U6M'!C:C) -> 15292 | Y72: =_xlfn.XLOOKUP(A72,'BD UM'!A:A,'BD UM'!D:D) -> 280890.18 | Z72: =_xlfn.XLOOKUP(A72,'BD U6M'!A:A,'BD U6M'!D:D) -> 282725.72 | AA72: =_xlfn.XLOOKUP(A72,'BD UM'!A:A,'BD UM'!E:E) -> 40537.48 | AB72: =_xlfn.XLOOKUP(A72,'BD U6M'!A:A,'BD U6M'!E:E) -> 33047.06 | AC72: =_xlfn.XLOOKUP(A72,'BD UM'!A:A,'BD UM'!F:F) -> 90976.911 | AD72: =_xlfn.XLOOKUP(A72,'BD U6M'!A:A,'BD U6M'!F:F) -> 90521.008 | AE72: =_xlfn.XLOOKUP(A72,'BD UM'!A:A,'BD UM'!G:G) -> 6074.087 | AF72: =_xlfn.XLOOKUP(A72,'BD U6M'!A:A,'BD U6M'!G:G) -> 6042.513 | AG72: =_xlfn.XLOOKUP(A72,'BD UM'!A:A,'BD UM'!H:H) -> 0 | AH72: COMERCIO/SERVICIO | AI72: ABIERTA | AJ72: BASE | AK72: TMCB | AL72: 232000 | AM72: 55.58 | AN72: Bosa Zona Bancaria | AO72: Bajo
A73: 50ROX | B73: Centro Sur | C73: Distrito Capital | D73: Bogotá | E73: GRAN BRITALIA | F73: 2 | G73: Bosa Maryland II | H73: CINTO INVERSIONES Y PORSPECCIONES S.A.S | I73: Esquinero | J73: 129.17 | K73: 1790 | L73: 800 | M73: 132 | N73: 45596 | O73: 31 | P73: 1 | Q73: 31 | R73: 22 | S73: 4.6121747 | T73: -74.201318 | U73: =_xlfn.XLOOKUP(A73,'BD UM'!A:A,'BD UM'!B:B) -> 15705 | V73: =_xlfn.XLOOKUP(A73,'BD U6M'!A:A,'BD U6M'!B:B) -> 14857.167 | W73: =_xlfn.XLOOKUP(A73,'BD UM'!A:A,'BD UM'!C:C) -> 12513.9 | X73: =_xlfn.XLOOKUP(A73,'BD U6M'!A:A,'BD U6M'!C:C) -> 12401.6 | Y73: =_xlfn.XLOOKUP(A73,'BD UM'!A:A,'BD UM'!D:D) -> 196530.68 | Z73: =_xlfn.XLOOKUP(A73,'BD U6M'!A:A,'BD U6M'!D:D) -> 184251.99 | AA73: =_xlfn.XLOOKUP(A73,'BD UM'!A:A,'BD UM'!E:E) -> 745.516 | AB73: =_xlfn.XLOOKUP(A73,'BD U6M'!A:A,'BD U6M'!E:E) -> 2882.0051 | AC73: =_xlfn.XLOOKUP(A73,'BD UM'!A:A,'BD UM'!F:F) -> 60197.378 | AD73: =_xlfn.XLOOKUP(A73,'BD U6M'!A:A,'BD U6M'!F:F) -> 56734.897 | AE73: =_xlfn.XLOOKUP(A73,'BD UM'!A:A,'BD UM'!G:G) -> 9731 | AF73: =_xlfn.XLOOKUP(A73,'BD U6M'!A:A,'BD U6M'!G:G) -> 9831.6841 | AG73: =_xlfn.XLOOKUP(A73,'BD UM'!A:A,'BD UM'!H:H) -> 0 | AH73: COMERCIO/SERVICIO | AI73: ABIERTA | AJ73: BASE | AK73: EXP 2024 | AL73: 232000 | AM73: 75.33 | AN73: Autopista | AO73: Bajo
A74: 50Q3X | B74: Centro Sur | C74: Distrito Capital | D74: Bogotá | E74: BOSA CENTRAL | F74: 3 | G74: Bosa Zona Bancaria | H74: 0 | I74: Medianero | J74: 127.96 | K74: 576 | L74: 2691 | M74: 0 | N74: 43377 | O74: 4 | P74: 28 | Q74: 31 | R74: 94 | S74: 4.6060502 | T74: -74.184311 | U74: =_xlfn.XLOOKUP(A74,'BD UM'!A:A,'BD UM'!B:B) -> 23779 | V74: =_xlfn.XLOOKUP(A74,'BD U6M'!A:A,'BD U6M'!B:B) -> 24769.833 | W74: =_xlfn.XLOOKUP(A74,'BD UM'!A:A,'BD UM'!C:C) -> 13651 | X74: =_xlfn.XLOOKUP(A74,'BD U6M'!A:A,'BD U6M'!C:C) -> 13708.7 | Y74: =_xlfn.XLOOKUP(A74,'BD UM'!A:A,'BD UM'!D:D) -> 324608.28 | Z74: =_xlfn.XLOOKUP(A74,'BD U6M'!A:A,'BD U6M'!D:D) -> 339563.27 | AA74: =_xlfn.XLOOKUP(A74,'BD UM'!A:A,'BD UM'!E:E) -> 24139.807 | AB74: =_xlfn.XLOOKUP(A74,'BD U6M'!A:A,'BD U6M'!E:E) -> 31337.261 | AC74: =_xlfn.XLOOKUP(A74,'BD UM'!A:A,'BD UM'!F:F) -> 103715.69 | AD74: =_xlfn.XLOOKUP(A74,'BD U6M'!A:A,'BD U6M'!F:F) -> 109119.23 | AE74: =_xlfn.XLOOKUP(A74,'BD UM'!A:A,'BD UM'!G:G) -> 20187.251 | AF74: =_xlfn.XLOOKUP(A74,'BD U6M'!A:A,'BD U6M'!G:G) -> 19551.072 | AG74: =_xlfn.XLOOKUP(A74,'BD UM'!A:A,'BD UM'!H:H) -> 0 | AH74: COMERCIO/SERVICIO | AI74: ABIERTA | AJ74: BASE | AK74: TMCB | AL74: 232000 | AM74: 73.46 | AN74: PT | AO74: Medio
A75: 50UZ3 | B75: Centro Sur | C75: Distrito Capital | D75: Bogotá | E75: LAS NIEVES | F75: 3 | G75: Bosque Izquierdo | H75: 0 | I75: Esquinero | J75: 114.47 | K75: 2722 | L75: 5014 | M75: 145 | N75: 45044 | O75: 28 | P75: 3 | Q75: 30 | R75: 40 | S75: 4.6063961 | T75: -74.069271 | U75: =_xlfn.XLOOKUP(A75,'BD UM'!A:A,'BD UM'!B:B) -> 27871 | V75: =_xlfn.XLOOKUP(A75,'BD U6M'!A:A,'BD U6M'!B:B) -> 23708.167 | W75: =_xlfn.XLOOKUP(A75,'BD UM'!A:A,'BD UM'!C:C) -> 10698.3 | X75: =_xlfn.XLOOKUP(A75,'BD U6M'!A:A,'BD U6M'!C:C) -> 10966.5 | Y75: =_xlfn.XLOOKUP(A75,'BD UM'!A:A,'BD UM'!D:D) -> 298172.86 | Z75: =_xlfn.XLOOKUP(A75,'BD U6M'!A:A,'BD U6M'!D:D) -> 259995.35 | AA75: =_xlfn.XLOOKUP(A75,'BD UM'!A:A,'BD UM'!E:E) -> 45926.846 | AB75: =_xlfn.XLOOKUP(A75,'BD U6M'!A:A,'BD U6M'!E:E) -> 25857.274 | AC75: =_xlfn.XLOOKUP(A75,'BD UM'!A:A,'BD UM'!F:F) -> 117245.75 | AD75: =_xlfn.XLOOKUP(A75,'BD U6M'!A:A,'BD U6M'!F:F) -> 99340.649 | AE75: =_xlfn.XLOOKUP(A75,'BD UM'!A:A,'BD UM'!G:G) -> 11478.437 | AF75: =_xlfn.XLOOKUP(A75,'BD U6M'!A:A,'BD U6M'!G:G) -> 11555.825 | AG75: =_xlfn.XLOOKUP(A75,'BD UM'!A:A,'BD UM'!H:H) -> 0 | AH75: EDUCACION | AI75: ABIERTA | AJ75: BASE | AK75: TMCB | AL75: 232000 | AM75: 100.27 | AN75: Piloto | AO75: Alto
A76: 50K7W | B76: Centro Sur | C76: Distrito Capital | D76: Bogotá | E76: FONTIBON | F76: 3 | G76: Boston | H76: 0 | I76: Esquinero | J76: 123 | K76: 1920 | L76: 450 | M76: 117 | N76: 45276 | O76: 16 | P76: 16 | Q76: 31 | R76: 32 | S76: 4.6801505 | T76: -74.142957 | U76: =_xlfn.XLOOKUP(A76,'BD UM'!A:A,'BD UM'!B:B) -> 13304 | V76: =_xlfn.XLOOKUP(A76,'BD U6M'!A:A,'BD U6M'!B:B) -> 13752.5 | W76: =_xlfn.XLOOKUP(A76,'BD UM'!A:A,'BD UM'!C:C) -> 12659.9 | X76: =_xlfn.XLOOKUP(A76,'BD U6M'!A:A,'BD U6M'!C:C) -> 12950.8 | Y76: =_xlfn.XLOOKUP(A76,'BD UM'!A:A,'BD UM'!D:D) -> 168427.14 | Z76: =_xlfn.XLOOKUP(A76,'BD U6M'!A:A,'BD U6M'!D:D) -> 178106.19 | AA76: =_xlfn.XLOOKUP(A76,'BD UM'!A:A,'BD UM'!E:E) -> 851.948 | AB76: =_xlfn.XLOOKUP(A76,'BD U6M'!A:A,'BD U6M'!E:E) -> 5254.7418 | AC76: =_xlfn.XLOOKUP(A76,'BD UM'!A:A,'BD UM'!F:F) -> 53135.588 | AD76: =_xlfn.XLOOKUP(A76,'BD U6M'!A:A,'BD U6M'!F:F) -> 55138.822 | AE76: =_xlfn.XLOOKUP(A76,'BD UM'!A:A,'BD UM'!G:G) -> 8047.379 | AF76: =_xlfn.XLOOKUP(A76,'BD U6M'!A:A,'BD U6M'!G:G) -> 8133.9457 | AG76: =_xlfn.XLOOKUP(A76,'BD UM'!A:A,'BD UM'!H:H) -> 0 | AH76: BAJA DENSIDAD | AI76: ABIERTA | AJ76: HOGAR | AK76: TMCB | AL76: 241405 | AM76: 65.42 | AN76: Villamaria | AO76: Bajo
A77: 50K7Y | B77: Norte | C77: Atlántico | D77: Barranquilla | E77: RIOMAR | F77: 4 | G77: Boulevard | H77: ND | I77: Esquinero | J77: 85.56 | K77: 1361 | L77: 980 | M77: 96 | N77: 46252 | O77: 18 | P77: 14 | Q77: 31 | R77: 0 | S77: 11.014346 | T77: -74.836238 | U77: =_xlfn.XLOOKUP(A77,'BD UM'!A:A,'BD UM'!B:B) -> 5262 | V77: =_xlfn.XLOOKUP(A77,'BD U6M'!A:A,'BD U6M'!B:B) -> 5262 | W77: =_xlfn.XLOOKUP(A77,'BD UM'!A:A,'BD UM'!C:C) -> 13128 | X77: =_xlfn.XLOOKUP(A77,'BD U6M'!A:A,'BD U6M'!C:C) -> 13128 | Y77: =_xlfn.XLOOKUP(A77,'BD UM'!A:A,'BD UM'!D:D) -> 69079.384 | Z77: =_xlfn.XLOOKUP(A77,'BD U6M'!A:A,'BD U6M'!D:D) -> 69079.384 | AA77: =_xlfn.XLOOKUP(A77,'BD UM'!A:A,'BD UM'!E:E) -> -5233.293 | AB77: =_xlfn.XLOOKUP(A77,'BD U6M'!A:A,'BD U6M'!E:E) -> -6223.3559 | AC77: =_xlfn.XLOOKUP(A77,'BD UM'!A:A,'BD UM'!F:F) -> 30947.612 | AD77: =_xlfn.XLOOKUP(A77,'BD U6M'!A:A,'BD U6M'!F:F) -> 30947.612 | AE77: =_xlfn.XLOOKUP(A77,'BD UM'!A:A,'BD UM'!G:G) -> 4303.533 | AF77: =_xlfn.XLOOKUP(A77,'BD U6M'!A:A,'BD U6M'!G:G) -> 4303.533 | AG77: =_xlfn.XLOOKUP(A77,'BD UM'!A:A,'BD UM'!H:H) -> 0 | AH77: COMERCIO/SERVICIO | AI77: ABIERTA | AJ77: BASE | AK77: TMCB | AL77: 232000 | AM77: 72.12 | AN77: PT | AO77: Medio
A78: 504B3 | B78: Centro Sur | C78: Distrito Capital | D78: Bogotá | E78: SANTA CECILIA | F78: 4 | G78: Boyaca 53 | H78: 0 | I78: Esquinero | J78: 104.72 | K78: 1343 | L78: 1029 | M78: 118 | N78: 45226 | O78: 27 | P78: 5 | Q78: 31 | R78: 34 | S78: 4.6716548 | T78: -74.106887 | U78: =_xlfn.XLOOKUP(A78,'BD UM'!A:A,'BD UM'!B:B) -> 16939 | V78: =_xlfn.XLOOKUP(A78,'BD U6M'!A:A,'BD U6M'!B:B) -> 15717.5 | W78: =_xlfn.XLOOKUP(A78,'BD UM'!A:A,'BD UM'!C:C) -> 10770.3 | X78: =_xlfn.XLOOKUP(A78,'BD U6M'!A:A,'BD U6M'!C:C) -> 11072.5 | Y78: =_xlfn.XLOOKUP(A78,'BD UM'!A:A,'BD UM'!D:D) -> 182438.56 | Z78: =_xlfn.XLOOKUP(A78,'BD U6M'!A:A,'BD U6M'!D:D) -> 174031.52 | AA78: =_xlfn.XLOOKUP(A78,'BD UM'!A:A,'BD UM'!E:E) -> 7166.822 | AB78: =_xlfn.XLOOKUP(A78,'BD U6M'!A:A,'BD U6M'!E:E) -> 215.98831 | AC78: =_xlfn.XLOOKUP(A78,'BD UM'!A:A,'BD UM'!F:F) -> 64997.225 | AD78: =_xlfn.XLOOKUP(A78,'BD U6M'!A:A,'BD U6M'!F:F) -> 56878.79 | AE78: =_xlfn.XLOOKUP(A78,'BD UM'!A:A,'BD UM'!G:G) -> 12622.069 | AF78: =_xlfn.XLOOKUP(A78,'BD U6M'!A:A,'BD U6M'!G:G) -> 12746.995 | AG78: =_xlfn.XLOOKUP(A78,'BD UM'!A:A,'BD UM'!H:H) -> 0 | AH78: COMERCIO/SERVICIO | AI78: ABIERTA | AJ78: BASE | AK78: TMCB | AL78: 232000 | AM78: 120.53 | AN78: Quirigua | AO78: Medio
A79: 50CPF | B79: Centro Sur | C79: Distrito Capital | D79: Bogotá | E79: BOYACA REAL | F79: 3 | G79: Boyacá Parque | H79: PLAY ZONE ENTERTAINMENT S.A.S | I79: Esquinero | J79: 137.53 | K79: 1334 | L79: 1547 | M79: 56 | N79: 45673 | O79: 16 | P79: 16 | Q79: 31 | R79: 19 | S79: 4.6868018 | T79: -74.097759 | U79: =_xlfn.XLOOKUP(A79,'BD UM'!A:A,'BD UM'!B:B) -> 14631 | V79: =_xlfn.XLOOKUP(A79,'BD U6M'!A:A,'BD U6M'!B:B) -> 14057 | W79: =_xlfn.XLOOKUP(A79,'BD UM'!A:A,'BD UM'!C:C) -> 11709.9 | X79: =_xlfn.XLOOKUP(A79,'BD U6M'!A:A,'BD U6M'!C:C) -> 10802.2 | Y79: =_xlfn.XLOOKUP(A79,'BD UM'!A:A,'BD UM'!D:D) -> 171326.85 | Z79: =_xlfn.XLOOKUP(A79,'BD U6M'!A:A,'BD U6M'!D:D) -> 151846.73 | AA79: =_xlfn.XLOOKUP(A79,'BD UM'!A:A,'BD UM'!E:E) -> 7187.294 | AB79: =_xlfn.XLOOKUP(A79,'BD U6M'!A:A,'BD U6M'!E:E) -> 4592.5921 | AC79: =_xlfn.XLOOKUP(A79,'BD UM'!A:A,'BD UM'!F:F) -> 56955.051 | AD79: =_xlfn.XLOOKUP(A79,'BD U6M'!A:A,'BD U6M'!F:F) -> 50331.588 | AE79: =_xlfn.XLOOKUP(A79,'BD UM'!A:A,'BD UM'!G:G) -> 7364 | AF79: =_xlfn.XLOOKUP(A79,'BD U6M'!A:A,'BD U6M'!G:G) -> 7444.8365 | AG79: =_xlfn.XLOOKUP(A79,'BD UM'!A:A,'BD UM'!H:H) -> 0 | AH79: COMERCIO/SERVICIO | AI79: ABIERTA | AJ79: BASE | AK79: EXP 2025 | AL79: 204160 | AM79: 53.54 | AN79: Parque Restrepo | AO79: Medio
A80: 50PC5 | B80: Centro Norte | C80: Distrito Capital | D80: Bogotá | E80: CHICO LAGO | F80: 6 | G80: Bridge 93 | H80: GRUPO OPTICO ANDES SAS | I80: Esquinero | J80: 117.25 | K80: 1601 | L80: 2335 | M80: 215 | N80: 45737 | O80: 21 | P80: 11 | Q80: 31 | R80: 17 | S80: 4.678617 | T80: -74.055254 | U80: =_xlfn.XLOOKUP(A80,'BD UM'!A:A,'BD UM'!B:B) -> 26037 | V80: =_xlfn.XLOOKUP(A80,'BD U6M'!A:A,'BD U6M'!B:B) -> 26319 | W80: =_xlfn.XLOOKUP(A80,'BD UM'!A:A,'BD UM'!C:C) -> 10276.5 | X80: =_xlfn.XLOOKUP(A80,'BD U6M'!A:A,'BD U6M'!C:C) -> 10604.3 | Y80: =_xlfn.XLOOKUP(A80,'BD UM'!A:A,'BD UM'!D:D) -> 267568.18 | Z80: =_xlfn.XLOOKUP(A80,'BD U6M'!A:A,'BD U6M'!D:D) -> 279093.87 | AA80: =_xlfn.XLOOKUP(A80,'BD UM'!A:A,'BD UM'!E:E) -> 38538.994 | AB80: =_xlfn.XLOOKUP(A80,'BD U6M'!A:A,'BD U6M'!E:E) -> 44513.203 | AC80: =_xlfn.XLOOKUP(A80,'BD UM'!A:A,'BD UM'!F:F) -> 111202.83 | AD80: =_xlfn.XLOOKUP(A80,'BD U6M'!A:A,'BD U6M'!F:F) -> 116005.47 | AE80: =_xlfn.XLOOKUP(A80,'BD UM'!A:A,'BD UM'!G:G) -> 12612 | AF80: =_xlfn.XLOOKUP(A80,'BD U6M'!A:A,'BD U6M'!G:G) -> 12736.842 | AG80: =_xlfn.XLOOKUP(A80,'BD UM'!A:A,'BD UM'!H:H) -> 1.8017 | AH80: ADMINISTRATIVO | AI80: ABIERTA | AJ80: BASE | AK80: EXP 2025 | AL80: 232000 | AM80: 107.57 | AN80: Fijar 93 | AO80: Alto
A81: 50IZL | B81: Occidente | C81: Valle del Cauca | D81: Cali | E81: COMUNA 2 | F81: 4 | G81: Brisas De La Sexta | H81: 0 | I81: Esquinero | J81: 105.66 | K81: 1092 | L81: 2097 | M81: 105 | N81: 45377 | O81: 26 | P81: 6 | Q81: 31 | R81: 29 | S81: 3.4592351 | T81: -76.532133 | U81: =_xlfn.XLOOKUP(A81,'BD UM'!A:A,'BD UM'!B:B) -> 17836 | V81: =_xlfn.XLOOKUP(A81,'BD U6M'!A:A,'BD U6M'!B:B) -> 17314.5 | W81: =_xlfn.XLOOKUP(A81,'BD UM'!A:A,'BD UM'!C:C) -> 11696.5 | X81: =_xlfn.XLOOKUP(A81,'BD U6M'!A:A,'BD U6M'!C:C) -> 11605.8 | Y81: =_xlfn.XLOOKUP(A81,'BD UM'!A:A,'BD UM'!D:D) -> 208617.95 | Z81: =_xlfn.XLOOKUP(A81,'BD U6M'!A:A,'BD U6M'!D:D) -> 200948.94 | AA81: =_xlfn.XLOOKUP(A81,'BD UM'!A:A,'BD UM'!E:E) -> 4870.147 | AB81: =_xlfn.XLOOKUP(A81,'BD U6M'!A:A,'BD U6M'!E:E) -> 8791.2983 | AC81: =_xlfn.XLOOKUP(A81,'BD UM'!A:A,'BD UM'!F:F) -> 82179.229 | AD81: =_xlfn.XLOOKUP(A81,'BD U6M'!A:A,'BD U6M'!F:F) -> 76721.711 | AE81: =_xlfn.XLOOKUP(A81,'BD UM'!A:A,'BD UM'!G:G) -> 13267.374 | AF81: =_xlfn.XLOOKUP(A81,'BD U6M'!A:A,'BD U6M'!G:G) -> 13398.09 | AG81: =_xlfn.XLOOKUP(A81,'BD UM'!A:A,'BD UM'!H:H) -> 0 | AH81: COMERCIO/SERVICIO | AI81: ABIERTA | AJ81: RECESO | AK81: TMCB | AL81: 204160 | AM81: 125.57 | AN81: Cabecera | AO81: Alto
A82: 502SG | B82: Centro Sur | C82: Distrito Capital | D82: Bogotá | E82: GRAN BRITALIA | F82: 3 | G82: Britalia | H82: 0 | I82: Esquinero | J82: 98.96 | K82: 1859 | L82: 266 | M82: 0 | N82: 44390 | O82: 13 | P82: 19 | Q82: 31 | R82: 60 | S82: 4.6185017 | T82: -74.169601 | U82: =_xlfn.XLOOKUP(A82,'BD UM'!A:A,'BD UM'!B:B) -> 15418 | V82: =_xlfn.XLOOKUP(A82,'BD U6M'!A:A,'BD U6M'!B:B) -> 15186.333 | W82: =_xlfn.XLOOKUP(A82,'BD UM'!A:A,'BD UM'!C:C) -> 13822.1 | X82: =_xlfn.XLOOKUP(A82,'BD U6M'!A:A,'BD U6M'!C:C) -> 16447 | Y82: =_xlfn.XLOOKUP(A82,'BD UM'!A:A,'BD UM'!D:D) -> 213109.79 | Z82: =_xlfn.XLOOKUP(A82,'BD U6M'!A:A,'BD U6M'!D:D) -> 249769.46 | AA82: =_xlfn.XLOOKUP(A82,'BD UM'!A:A,'BD UM'!E:E) -> 11959.359 | AB82: =_xlfn.XLOOKUP(A82,'BD U6M'!A:A,'BD U6M'!E:E) -> 16048.709 | AC82: =_xlfn.XLOOKUP(A82,'BD UM'!A:A,'BD UM'!F:F) -> 65204.376 | AD82: =_xlfn.XLOOKUP(A82,'BD U6M'!A:A,'BD U6M'!F:F) -> 74538.179 | AE82: =_xlfn.XLOOKUP(A82,'BD UM'!A:A,'BD UM'!G:G) -> 6784.833 | AF82: =_xlfn.XLOOKUP(A82,'BD U6M'!A:A,'BD U6M'!G:G) -> 6677.2561 | AG82: =_xlfn.XLOOKUP(A82,'BD UM'!A:A,'BD UM'!H:H) -> 0 | AH82: ESTACION DE SERVICIO | AI82: ABIERTA | AJ82: RECESO | AK82: TMCB | AL82: 204160 | AM82: 110.78 | AN82: PT | AO82: Alto
A83: 50NIL | B83: Centro Norte | C83: Distrito Capital | D83: Bogotá | E83: BRITALIA | F83: 3 | G83: Britalia Norte | H83: GERMAN URIBE VELEZ | I83: Esquinero | J83: 96.98 | K83: 3595 | L83: 210 | M83: 84 | N83: 45517 | O83: 13 | P83: 19 | Q83: 31 | R83: 24 | S83: 4.7455767 | T83: -74.050357 | U83: =_xlfn.XLOOKUP(A83,'BD UM'!A:A,'BD UM'!B:B) -> 16944 | V83: =_xlfn.XLOOKUP(A83,'BD U6M'!A:A,'BD U6M'!B:B) -> 16326.667 | W83: =_xlfn.XLOOKUP(A83,'BD UM'!A:A,'BD UM'!C:C) -> 14019.4 | X83: =_xlfn.XLOOKUP(A83,'BD U6M'!A:A,'BD U6M'!C:C) -> 14656.1 | Y83: =_xlfn.XLOOKUP(A83,'BD UM'!A:A,'BD UM'!D:D) -> 237543.98 | Z83: =_xlfn.XLOOKUP(A83,'BD U6M'!A:A,'BD U6M'!D:D) -> 239286.01 | AA83: =_xlfn.XLOOKUP(A83,'BD UM'!A:A,'BD UM'!E:E) -> 26245.964 | AB83: =_xlfn.XLOOKUP(A83,'BD U6M'!A:A,'BD U6M'!E:E) -> 23177.213 | AC83: =_xlfn.XLOOKUP(A83,'BD UM'!A:A,'BD UM'!F:F) -> 82777.479 | AD83: =_xlfn.XLOOKUP(A83,'BD U6M'!A:A,'BD U6M'!F:F) -> 80342.658 | AE83: =_xlfn.XLOOKUP(A83,'BD UM'!A:A,'BD UM'!G:G) -> 8201.009 | AF83: =_xlfn.XLOOKUP(A83,'BD U6M'!A:A,'BD U6M'!G:G) -> 8005.826 | AG83: =_xlfn.XLOOKUP(A83,'BD UM'!A:A,'BD UM'!H:H) -> 0 | AH83: ALTA DENSIDAD | AI83: ABIERTA | AJ83: HOGAR | AK83: EXP 2024 | AL83: 241405 | AM83: 80.46 | AN83: Reserva De Colina | AO83: Medio
A84: 50RBT | B84: Centro Norte | C84: Distrito Capital | D84: Bogotá | E84: NIZA | F84: 5 | G84: Britania | H84: 0 | I84: Esquinero | J84: 147.09 | K84: 265 | L84: 4718 | M84: 84 | N84: 40072 | O84: 16 | P84: 15 | Q84: 30 | R84: 114 | S84: 4.7222153 | T84: -74.066814 | U84: =_xlfn.XLOOKUP(A84,'BD UM'!A:A,'BD UM'!B:B) -> 15346 | V84: =_xlfn.XLOOKUP(A84,'BD U6M'!A:A,'BD U6M'!B:B) -> 14324.667 | W84: =_xlfn.XLOOKUP(A84,'BD UM'!A:A,'BD UM'!C:C) -> 14302.1 | X84: =_xlfn.XLOOKUP(A84,'BD U6M'!A:A,'BD U6M'!C:C) -> 15681.9 | Y84: =_xlfn.XLOOKUP(A84,'BD UM'!A:A,'BD UM'!D:D) -> 219479.37 | Z84: =_xlfn.XLOOKUP(A84,'BD U6M'!A:A,'BD U6M'!D:D) -> 224637.83 | AA84: =_xlfn.XLOOKUP(A84,'BD UM'!A:A,'BD UM'!E:E) -> 2006.263 | AB84: =_xlfn.XLOOKUP(A84,'BD U6M'!A:A,'BD U6M'!E:E) -> 5134.5533 | AC84: =_xlfn.XLOOKUP(A84,'BD UM'!A:A,'BD UM'!F:F) -> 77974.062 | AD84: =_xlfn.XLOOKUP(A84,'BD U6M'!A:A,'BD U6M'!F:F) -> 78009.189 | AE84: =_xlfn.XLOOKUP(A84,'BD UM'!A:A,'BD UM'!G:G) -> 15134.801 | AF84: =_xlfn.XLOOKUP(A84,'BD U6M'!A:A,'BD U6M'!G:G) -> 15031.769 | AG84: =_xlfn.XLOOKUP(A84,'BD UM'!A:A,'BD UM'!H:H) -> 0 | AH84: COMERCIO/SERVICIO | AI84: ABIERTA | AJ84: BASE | AK84: TMCB | AL84: 232000 | AM84: 95.1 | AN84: PT | AO84: Alto
A85: 50BLE | B85: Oriente | C85: Santander | D85: Bucaramanga | E85: CABECERA DEL LLANO | F85: 5 | G85: Bucara Play | H85: 0 | I85: Esquinero | J85: 256.13 | K85: 944 | L85: 1105 | M85: 145 | N85: 45199 | O85: 30 | P85: 1 | Q85: 30 | R85: 35 | S85: 7.1166636 | T85: -73.109974 | U85: =_xlfn.XLOOKUP(A85,'BD UM'!A:A,'BD UM'!B:B) -> 28719 | V85: =_xlfn.XLOOKUP(A85,'BD U6M'!A:A,'BD U6M'!B:B) -> 26980.833 | W85: =_xlfn.XLOOKUP(A85,'BD UM'!A:A,'BD UM'!C:C) -> 9478.4 | X85: =_xlfn.XLOOKUP(A85,'BD U6M'!A:A,'BD U6M'!C:C) -> 9830.1 | Y85: =_xlfn.XLOOKUP(A85,'BD UM'!A:A,'BD UM'!D:D) -> 272209.67 | Z85: =_xlfn.XLOOKUP(A85,'BD U6M'!A:A,'BD U6M'!D:D) -> 265223.58 | AA85: =_xlfn.XLOOKUP(A85,'BD UM'!A:A,'BD UM'!E:E) -> 31278.135 | AB85: =_xlfn.XLOOKUP(A85,'BD U6M'!A:A,'BD U6M'!E:E) -> 32137.743 | AC85: =_xlfn.XLOOKUP(A85,'BD UM'!A:A,'BD UM'!F:F) -> 107724.51 | AD85: =_xlfn.XLOOKUP(A85,'BD U6M'!A:A,'BD U6M'!F:F) -> 103191.68 | AE85: =_xlfn.XLOOKUP(A85,'BD UM'!A:A,'BD UM'!G:G) -> 13290.822 | AF85: =_xlfn.XLOOKUP(A85,'BD U6M'!A:A,'BD U6M'!G:G) -> 12878.498 | AG85: =_xlfn.XLOOKUP(A85,'BD UM'!A:A,'BD UM'!H:H) -> 0 | AH85: COMERCIO/SERVICIO | AI85: ABIERTA | AJ85: BASE | AK85: TMCB | AL85: 232000 | AM85: 49.37 | AN85: Cabecera | AO85: Medio
A86: 502Z0 | B86: Occidente | C86: Antioquia | D86: Medellín | E86: LAURELES | F86: 4 | G86: Bulevar 70 | H86: CAROLINA GIRON BORJA | I86: Medianero | J86: 89.16 | K86: 254 | L86: 2850 | M86: 44 | N86: 45747 | O86: 31 | P86: 1 | Q86: 31 | R86: 17 | S86: 6.2524729 | T86: -75.58786 | U86: =_xlfn.XLOOKUP(A86,'BD UM'!A:A,'BD UM'!B:B) -> 22719 | V86: =_xlfn.XLOOKUP(A86,'BD U6M'!A:A,'BD U6M'!B:B) -> 20412.833 | W86: =_xlfn.XLOOKUP(A86,'BD UM'!A:A,'BD UM'!C:C) -> 11470.1 | X86: =_xlfn.XLOOKUP(A86,'BD U6M'!A:A,'BD U6M'!C:C) -> 12088.1 | Y86: =_xlfn.XLOOKUP(A86,'BD UM'!A:A,'BD UM'!D:D) -> 260590.13 | Z86: =_xlfn.XLOOKUP(A86,'BD U6M'!A:A,'BD U6M'!D:D) -> 246752.01 | AA86: =_xlfn.XLOOKUP(A86,'BD UM'!A:A,'BD UM'!E:E) -> 32011.684 | AB86: =_xlfn.XLOOKUP(A86,'BD U6M'!A:A,'BD U6M'!E:E) -> 24182.056 | AC86: =_xlfn.XLOOKUP(A86,'BD UM'!A:A,'BD UM'!F:F) -> 96660.776 | AD86: =_xlfn.XLOOKUP(A86,'BD U6M'!A:A,'BD U6M'!F:F) -> 90973.024 | AE86: =_xlfn.XLOOKUP(A86,'BD UM'!A:A,'BD UM'!G:G) -> 13137.5 | AF86: =_xlfn.XLOOKUP(A86,'BD U6M'!A:A,'BD U6M'!G:G) -> 13219.695 | AG86: =_xlfn.XLOOKUP(A86,'BD UM'!A:A,'BD UM'!H:H) -> 2.031 | AH86: COMERCIO/SERVICIO | AI86: ABIERTA | AJ86: RECESO | AK86: EXP 2025 | AL86: 204160 | AM86: 147.35 | AN86: Cabecera | AO86: Medio
A87: 50WFX | B87: Centro Sur | C87: Distrito Capital | D87: Bogotá | E87: CAPELLANIA | F87: 4 | G87: Buro 24 Ii | H87: FIDEICOMISO P.A BURO 24 | I87: Medianero | J87: 134.68 | K87: 1343 | L87: 8600 | M87: 156 | N87: 45502 | O87: 29 | P87: 3 | Q87: 31 | R87: 25 | S87: 4.6724228 | T87: -74.126288 | U87: =_xlfn.XLOOKUP(A87,'BD UM'!A:A,'BD UM'!B:B) -> 28041 | V87: =_xlfn.XLOOKUP(A87,'BD U6M'!A:A,'BD U6M'!B:B) -> 28273.833 | W87: =_xlfn.XLOOKUP(A87,'BD UM'!A:A,'BD UM'!C:C) -> 10941.6 | X87: =_xlfn.XLOOKUP(A87,'BD U6M'!A:A,'BD U6M'!C:C) -> 11131.6 | Y87: =_xlfn.XLOOKUP(A87,'BD UM'!A:A,'BD UM'!D:D) -> 306812.46 | Z87: =_xlfn.XLOOKUP(A87,'BD U6M'!A:A,'BD U6M'!D:D) -> 314733.92 | AA87: =_xlfn.XLOOKUP(A87,'BD UM'!A:A,'BD UM'!E:E) -> 35028.5 | AB87: =_xlfn.XLOOKUP(A87,'BD U6M'!A:A,'BD U6M'!E:E) -> 39137.967 | AC87: =_xlfn.XLOOKUP(A87,'BD UM'!A:A,'BD UM'!F:F) -> 115913.45 | AD87: =_xlfn.XLOOKUP(A87,'BD U6M'!A:A,'BD U6M'!F:F) -> 116144.37 | AE87: =_xlfn.XLOOKUP(A87,'BD UM'!A:A,'BD UM'!G:G) -> 13129.478 | AF87: =_xlfn.XLOOKUP(A87,'BD U6M'!A:A,'BD U6M'!G:G) -> 12913.407 | AG87: =_xlfn.XLOOKUP(A87,'BD UM'!A:A,'BD UM'!H:H) -> 0 | AH87: ADMINISTRATIVO | AI87: ABIERTA | AJ87: BASE | AK87: EXP 2024 | AL87: 232000 | AM87: 93.83 | AN87: El Dorado | AO87: Alto
A88: 50DQQ | B88: Centro Sur | C88: Distrito Capital | D88: Bogotá | E88: CAPELLANIA | F88: 4 | G88: Buro 25 | H88: FIDEICOMISO P.A. BURO 25 | I88: Medianero | J88: 123 | K88: 0 | L88: 0 | M88: 159 | N88: 46172 | O88: 30 | P88: 2 | Q88: 31 | R88: 3 | S88: 4.6826916 | T88: -74.124213 | U88: =_xlfn.XLOOKUP(A88,'BD UM'!A:A,'BD UM'!B:B) -> 32735 | V88: =_xlfn.XLOOKUP(A88,'BD U6M'!A:A,'BD U6M'!B:B) -> 25511.5 | W88: =_xlfn.XLOOKUP(A88,'BD UM'!A:A,'BD UM'!C:C) -> 9563.1 | X88: =_xlfn.XLOOKUP(A88,'BD U6M'!A:A,'BD U6M'!C:C) -> 10049.8 | Y88: =_xlfn.XLOOKUP(A88,'BD UM'!A:A,'BD UM'!D:D) -> 313046.88 | Z88: =_xlfn.XLOOKUP(A88,'BD U6M'!A:A,'BD U6M'!D:D) -> 256384.55 | AA88: =_xlfn.XLOOKUP(A88,'BD UM'!A:A,'BD UM'!E:E) -> 63190.54 | AB88: =_xlfn.XLOOKUP(A88,'BD U6M'!A:A,'BD U6M'!E:E) -> 54875.224 | AC88: =_xlfn.XLOOKUP(A88,'BD UM'!A:A,'BD UM'!F:F) -> 135649.93 | AD88: =_xlfn.XLOOKUP(A88,'BD U6M'!A:A,'BD U6M'!F:F) -> 110314.57 | AE88: =_xlfn.XLOOKUP(A88,'BD UM'!A:A,'BD UM'!G:G) -> 13000.27 | AF88: =_xlfn.XLOOKUP(A88,'BD U6M'!A:A,'BD U6M'!G:G) -> 6999.0994 | AG88: =_xlfn.XLOOKUP(A88,'BD UM'!A:A,'BD UM'!H:H) -> 2.2787 | AH88: EDUCACION | AI88: ABIERTA | AJ88: BASE | AK88: TMCB | AL88: 232000 | AM88: 200.99 | AN88: PT | AO88: Medio
A89: 50Z1X | B89: Oriente | C89: Santander | D89: Bucaramanga | E89: CABECERA DEL LLANO | F89: 5 | G89: Cabecera | H89: 0 | I89: Esquinero | J89: 131.3 | K89: 347 | L89: 2158 | M89: 0 | N89: 42551 | O89: 30 | P89: 1 | Q89: 30 | R89: 115 | S89: 7.1133 | U89: =_xlfn.XLOOKUP(A89,'BD UM'!A:A,'BD UM'!B:B) -> 27518 | V89: =_xlfn.XLOOKUP(A89,'BD U6M'!A:A,'BD U6M'!B:B) -> 25634.667 | W89: =_xlfn.XLOOKUP(A89,'BD UM'!A:A,'BD UM'!C:C) -> 9420.4 | X89: =_xlfn.XLOOKUP(A89,'BD U6M'!A:A,'BD U6M'!C:C) -> 10221.7 | Y89: =_xlfn.XLOOKUP(A89,'BD UM'!A:A,'BD UM'!D:D) -> 259231.56 | Z89: =_xlfn.XLOOKUP(A89,'BD U6M'!A:A,'BD U6M'!D:D) -> 262029.73 | AA89: =_xlfn.XLOOKUP(A89,'BD UM'!A:A,'BD UM'!E:E) -> 19190.469 | AB89: =_xlfn.XLOOKUP(A89,'BD U6M'!A:A,'BD U6M'!E:E) -> 32210.654 | AC89: =_xlfn.XLOOKUP(A89,'BD UM'!A:A,'BD UM'!F:F) -> 102043.84 | AD89: =_xlfn.XLOOKUP(A89,'BD U6M'!A:A,'BD U6M'!F:F) -> 103538.05 | AE89: =_xlfn.XLOOKUP(A89,'BD UM'!A:A,'BD UM'!G:G) -> 13147.348 | AF89: =_xlfn.XLOOKUP(A89,'BD U6M'!A:A,'BD U6M'!G:G) -> 13276.679 | AG89: =_xlfn.XLOOKUP(A89,'BD UM'!A:A,'BD UM'!H:H) -> 0 | AH89: ALTA DENSIDAD | AI89: ABIERTA | AJ89: HOGAR | AK89: TMCB | AL89: 241405 | AM89: 103.33 | AN89: PT | AO89: Medio
A90: 509MH | B90: Oriente | C90: Santander | D90: Bucaramanga | E90: CABECERA DEL LLANO | F90: 4 | G90: Cacique Plaza | H90: 0 | I90: Esquinero | J90: 140.9 | K90: 1676 | L90: 378 | M90: 130 | N90: 45136 | O90: 29 | P90: 3 | Q90: 31 | R90: 37 | S90: 7.098288 | U90: =_xlfn.XLOOKUP(A90,'BD UM'!A:A,'BD UM'!B:B) -> 21844 | V90: =_xlfn.XLOOKUP(A90,'BD U6M'!A:A,'BD U6M'!B:B) -> 19892.667 | W90: =_xlfn.XLOOKUP(A90,'BD UM'!A:A,'BD UM'!C:C) -> 12447.3 | X90: =_xlfn.XLOOKUP(A90,'BD U6M'!A:A,'BD U6M'!C:C) -> 12983.8 | Y90: =_xlfn.XLOOKUP(A90,'BD UM'!A:A,'BD UM'!D:D) -> 271899.9 | Z90: =_xlfn.XLOOKUP(A90,'BD U6M'!A:A,'BD U6M'!D:D) -> 258283.26 | AA90: =_xlfn.XLOOKUP(A90,'BD UM'!A:A,'BD UM'!E:E) -> 32919.641 | AB90: =_xlfn.XLOOKUP(A90,'BD U6M'!A:A,'BD U6M'!E:E) -> 31693.94 | AC90: =_xlfn.XLOOKUP(A90,'BD UM'!A:A,'BD UM'!F:F) -> 101572.26 | AD90: =_xlfn.XLOOKUP(A90,'BD U6M'!A:A,'BD U6M'!F:F) -> 95064.324 | AE90: =_xlfn.XLOOKUP(A90,'BD UM'!A:A,'BD UM'!G:G) -> 7720.759 | AF90: =_xlfn.XLOOKUP(A90,'BD U6M'!A:A,'BD U6M'!G:G) -> 7597.8042 | AG90: =_xlfn.XLOOKUP(A90,'BD UM'!A:A,'BD UM'!H:H) -> 0 | AH90: BAJA DENSIDAD | AI90: ABIERTA | AJ90: BASE | AK90: TMCB | AL90: 232000 | AM90: 67.56 | AN90: 0 | AO90: Bajo
A91: 50IS1 | B91: Centro Sur | C91: Tolima | D91: Ibagué | E91: ESTADIO (10) | F91: 3 | G91: Cadiz 34 | H91: JOSE I. DIAZ M. Y CIA. DIAGROTOL S. EN C. | I91: Esquinero | J91: 167.64 | K91: 506 | L91: 1780 | M91: 127 | N91: 45836 | O91: 28 | P91: 3 | Q91: 30 | R91: 14 | S91: 4.5978 | U91: =_xlfn.XLOOKUP(A91,'BD UM'!A:A,'BD UM'!B:B) -> 18227 | V91: =_xlfn.XLOOKUP(A91,'BD U6M'!A:A,'BD U6M'!B:B) -> 16827 | W91: =_xlfn.XLOOKUP(A91,'BD UM'!A:A,'BD UM'!C:C) -> 10590.2 | X91: =_xlfn.XLOOKUP(A91,'BD U6M'!A:A,'BD U6M'!C:C) -> 11108.5 | Y91: =_xlfn.XLOOKUP(A91,'BD UM'!A:A,'BD UM'!D:D) -> 193027.12 | Z91: =_xlfn.XLOOKUP(A91,'BD U6M'!A:A,'BD U6M'!D:D) -> 186922.25 | AA91: =_xlfn.XLOOKUP(A91,'BD UM'!A:A,'BD UM'!E:E) -> 9236.978 | AB91: =_xlfn.XLOOKUP(A91,'BD U6M'!A:A,'BD U6M'!E:E) -> 13179.927 | AC91: =_xlfn.XLOOKUP(A91,'BD UM'!A:A,'BD UM'!F:F) -> 79798.278 | AD91: =_xlfn.XLOOKUP(A91,'BD U6M'!A:A,'BD U6M'!F:F) -> 75252.639 | AE91: =_xlfn.XLOOKUP(A91,'BD UM'!A:A,'BD UM'!G:G) -> 9459 | AF91: =_xlfn.XLOOKUP(A91,'BD U6M'!A:A,'BD U6M'!G:G) -> 9316.8989 | AG91: =_xlfn.XLOOKUP(A91,'BD UM'!A:A,'BD UM'!H:H) -> 1.3159 | AH91: BAJA DENSIDAD | AI91: ABIERTA | AJ91: HOGAR | AK91: TMCB | AL91: 241405 | AM91: 54.09 | AN91: Tatika | AO91: Medio
A92: 50M7H | B92: Centro Norte | C92: Cundinamarca | D92: Cajicá | E92: CAJICA | F92: 3 | G92: Cajica El Eden | H92: 0 | I92: EDS Interurbana | J92: 100.86 | K92: 785 | L92: 310 | M92: 44 | N92: 45260 | O92: 30 | P92: 1 | Q92: 30 | R92: 33 | S92: 4.905747 | U92: =_xlfn.XLOOKUP(A92,'BD UM'!A:A,'BD UM'!B:B) -> 12472 | V92: =_xlfn.XLOOKUP(A92,'BD U6M'!A:A,'BD U6M'!B:B) -> 12456.333 | W92: =_xlfn.XLOOKUP(A92,'BD UM'!A:A,'BD UM'!C:C) -> 16216.5 | X92: =_xlfn.XLOOKUP(A92,'BD U6M'!A:A,'BD U6M'!C:C) -> 16313.4 | Y92: =_xlfn.XLOOKUP(A92,'BD UM'!A:A,'BD UM'!D:D) -> 202251.7 | Z92: =_xlfn.XLOOKUP(A92,'BD U6M'!A:A,'BD U6M'!D:D) -> 203205.66 | AA92: =_xlfn.XLOOKUP(A92,'BD UM'!A:A,'BD UM'!E:E) -> 21362.147 | AB92: =_xlfn.XLOOKUP(A92,'BD U6M'!A:A,'BD U6M'!E:E) -> 23823.567 | AC92: =_xlfn.XLOOKUP(A92,'BD UM'!A:A,'BD UM'!F:F) -> 81926.574 | AD92: =_xlfn.XLOOKUP(A92,'BD U6M'!A:A,'BD U6M'!F:F) -> 80150.628 | AE92: =_xlfn.XLOOKUP(A92,'BD UM'!A:A,'BD UM'!G:G) -> 8162.342 | AF92: =_xlfn.XLOOKUP(A92,'BD U6M'!A:A,'BD U6M'!G:G) -> 8249.8727 | AG92: =_xlfn.XLOOKUP(A92,'BD UM'!A:A,'BD UM'!H:H) -> 0 | AH92: COMERCIO/SERVICIO | AI92: ABIERTA | AJ92: RECESO | AK92: EXP 2025 | AL92: 204160 | AM92: 56.15 | AN92: La Samaria | AO92: Alto
A93: 50YZY | B93: Centro Norte | C93: Cundinamarca | D93: Cajicá | E93: CAJICA | F93: 5 | G93: Cajica Fontana Comer | H93: 0 | I93: Esquinero | J93: 114.57 | K93: 1250 | L93: 70 | M93: 98 | N93: 45075 | O93: 29 | P93: 3 | Q93: 31 | R93: 39 | S93: 4.9236 | U93: =_xlfn.XLOOKUP(A93,'BD UM'!A:A,'BD UM'!B:B) -> 14085 | V93: =_xlfn.XLOOKUP(A93,'BD U6M'!A:A,'BD U6M'!B:B) -> 14550.833 | W93: =_xlfn.XLOOKUP(A93,'BD UM'!A:A,'BD UM'!C:C) -> 14416.2 | X93: =_xlfn.XLOOKUP(A93,'BD U6M'!A:A,'BD U6M'!C:C) -> 15045 | Y93: =_xlfn.XLOOKUP(A93,'BD UM'!A:A,'BD UM'!D:D) -> 203052.75 | Z93: =_xlfn.XLOOKUP(A93,'BD U6M'!A:A,'BD U6M'!D:D) -> 218917.48 | AA93: =_xlfn.XLOOKUP(A93,'BD UM'!A:A,'BD UM'!E:E) -> 14235.167 | AB93: =_xlfn.XLOOKUP(A93,'BD U6M'!A:A,'BD U6M'!E:E) -> 15404.69 | AC93: =_xlfn.XLOOKUP(A93,'BD UM'!A:A,'BD UM'!F:F) -> 70273.354 | AD93: =_xlfn.XLOOKUP(A93,'BD U6M'!A:A,'BD U6M'!F:F) -> 73195.001 | AE93: =_xlfn.XLOOKUP(A93,'BD UM'!A:A,'BD UM'!G:G) -> 6041.283 | AF93: =_xlfn.XLOOKUP(A93,'BD U6M'!A:A,'BD U6M'!G:G) -> 6039.6581 | AG93: =_xlfn.XLOOKUP(A93,'BD UM'!A:A,'BD UM'!H:H) -> 0 | AH93: ESTACION DE SERVICIO | AI93: ABIERTA | AJ93: BASE | AK93: TMCB | AL93: 232000 | AM93: 80.92 | AN93: Eds Wellnwaa Hotel | AO93: Alto
A94: 50EKU | B94: Centro Norte | C94: Distrito Capital | D94: Bogotá | E94: NIZA | F94: 5 | G94: Calatrava | H94: 0 | I94: Esquinero | J94: 186.24 | K94: 867 | L94: 2044 | M94: 0 | N94: 40961 | O94: 22 | P94: 8 | Q94: 29 | R94: 115 | S94: 4.7141 | U94: =_xlfn.XLOOKUP(A94,'BD UM'!A:A,'BD UM'!B:B) -> 19523 | V94: =_xlfn.XLOOKUP(A94,'BD U6M'!A:A,'BD U6M'!B:B) -> 19482.833 | W94: =_xlfn.XLOOKUP(A94,'BD UM'!A:A,'BD UM'!C:C) -> 15157.4 | X94: =_xlfn.XLOOKUP(A94,'BD U6M'!A:A,'BD U6M'!C:C) -> 15072.9 | Y94: =_xlfn.XLOOKUP(A94,'BD UM'!A:A,'BD UM'!D:D) -> 295917.04 | Z94: =_xlfn.XLOOKUP(A94,'BD U6M'!A:A,'BD U6M'!D:D) -> 293662.55 | AA94: =_xlfn.XLOOKUP(A94,'BD UM'!A:A,'BD UM'!E:E) -> 34709.739 | AB94: =_xlfn.XLOOKUP(A94,'BD U6M'!A:A,'BD U6M'!E:E) -> 29380.516 | AC94: =_xlfn.XLOOKUP(A94,'BD UM'!A:A,'BD UM'!F:F) -> 107617.71 | AD94: =_xlfn.XLOOKUP(A94,'BD U6M'!A:A,'BD U6M'!F:F) -> 108545.32 | AE94: =_xlfn.XLOOKUP(A94,'BD UM'!A:A,'BD UM'!G:G) -> 18140.55 | AF94: =_xlfn.XLOOKUP(A94,'BD U6M'!A:A,'BD U6M'!G:G) -> 17649.096 | AG94: =_xlfn.XLOOKUP(A94,'BD UM'!A:A,'BD UM'!H:H) -> 0 | AH94: BAJA DENSIDAD | AI94: ABIERTA | AJ94: HOGAR | AK94: TMCB | AL94: 241405 | AM94: 52.73 | AN94: Bonavista | AO94: Medio
A95: 50YC0 | B95: Centro Norte | C95: Cundinamarca | D95: La Calera | E95: CALERA | F95: 3 | G95: Calera Cra 3 | H95: 0 | I95: Esquinero | J95: 140 | K95: 761 | L95: 600 | M95: 58 | N95: 44803 | O95: 30 | P95: 2 | Q95: 31 | R95: 48 | S95: 4.718756 | U95: =_xlfn.XLOOKUP(A95,'BD UM'!A:A,'BD UM'!B:B) -> 19154 | V95: =_xlfn.XLOOKUP(A95,'BD U6M'!A:A,'BD U6M'!B:B) -> 19764.667 | W95: =_xlfn.XLOOKUP(A95,'BD UM'!A:A,'BD UM'!C:C) -> 13129 | X95: =_xlfn.XLOOKUP(A95,'BD U6M'!A:A,'BD U6M'!C:C) -> 13091.4 | Y95: =_xlfn.XLOOKUP(A95,'BD UM'!A:A,'BD UM'!D:D) -> 251473.32 | Z95: =_xlfn.XLOOKUP(A95,'BD U6M'!A:A,'BD U6M'!D:D) -> 258748.03 | AA95: =_xlfn.XLOOKUP(A95,'BD UM'!A:A,'BD UM'!E:E) -> 25222.177 | AB95: =_xlfn.XLOOKUP(A95,'BD U6M'!A:A,'BD U6M'!E:E) -> 25909.131 | AC95: =_xlfn.XLOOKUP(A95,'BD UM'!A:A,'BD UM'!F:F) -> 89405.043 | AD95: =_xlfn.XLOOKUP(A95,'BD U6M'!A:A,'BD U6M'!F:F) -> 89835.694 | AE95: =_xlfn.XLOOKUP(A95,'BD UM'!A:A,'BD UM'!G:G) -> 11070.916 | AF95: =_xlfn.XLOOKUP(A95,'BD U6M'!A:A,'BD U6M'!G:G) -> 10822.215 | AG95: =_xlfn.XLOOKUP(A95,'BD UM'!A:A,'BD UM'!H:H) -> 0 | AH95: ND | AI95: ABIERTA | AJ95: RECESO | AK95: EXP 2026 | AL95: 204160 | AM95: $ - | AN95: #N/A | AO95: Alto
A96: 509HC | B96: Centro Norte | C96: Cundinamarca | D96: La Calera | E96: CALERA | F96: 3 | G96: Calera Hills | H96: 0 | I96: Esquinero | J96: 124.64 | K96: 759 | L96: 400 | M96: 40 | N96: 44923 | O96: 28 | P96: 4 | Q96: 31 | R96: 44 | S96: 4.7209 | U96: =_xlfn.XLOOKUP(A96,'BD UM'!A:A,'BD UM'!B:B) -> 17310 | V96: =_xlfn.XLOOKUP(A96,'BD U6M'!A:A,'BD U6M'!B:B) -> 16400.167 | W96: =_xlfn.XLOOKUP(A96,'BD UM'!A:A,'BD UM'!C:C) -> 13241.7 | X96: =_xlfn.XLOOKUP(A96,'BD U6M'!A:A,'BD U6M'!C:C) -> 13641.2 | Y96: =_xlfn.XLOOKUP(A96,'BD UM'!A:A,'BD UM'!D:D) -> 229213.96 | Z96: =_xlfn.XLOOKUP(A96,'BD U6M'!A:A,'BD U6M'!D:D) -> 223718.37 | AA96: =_xlfn.XLOOKUP(A96,'BD UM'!A:A,'BD UM'!E:E) -> 25292.867 | AB96: =_xlfn.XLOOKUP(A96,'BD U6M'!A:A,'BD U6M'!E:E) -> 21138.446 | AC96: =_xlfn.XLOOKUP(A96,'BD UM'!A:A,'BD UM'!F:F) -> 86909.655 | AD96: =_xlfn.XLOOKUP(A96,'BD U6M'!A:A,'BD U6M'!F:F) -> 82831.044 | AE96: =_xlfn.XLOOKUP(A96,'BD UM'!A:A,'BD UM'!G:G) -> 12260.182 | AF96: =_xlfn.XLOOKUP(A96,'BD U6M'!A:A,'BD U6M'!G:G) -> 12413.396 | AG96: =_xlfn.XLOOKUP(A96,'BD UM'!A:A,'BD UM'!H:H) -> 0 | AH96: BAJA DENSIDAD | AI96: ABIERTA | AJ96: HOGAR | AK96: TMCB | AL96: 241405 | AM96: 68.11 | AN96: PT | AO96: Medio
A97: 50C7J | B97: Centro Sur | C97: Distrito Capital | D97: Bogotá | E97: LA SABANA | F97: 4 | G97: Calima | H97: 0 | I97: Medianero | J97: 97.43 | K97: 56 | L97: 4030 | M97: 134 | N97: 43703 | O97: 26 | P97: 6 | Q97: 31 | R97: 81 | S97: 4.6187 | U97: =_xlfn.XLOOKUP(A97,'BD UM'!A:A,'BD UM'!B:B) -> 31153 | V97: =_xlfn.XLOOKUP(A97,'BD U6M'!A:A,'BD U6M'!B:B) -> 31620.333 | W97: =_xlfn.XLOOKUP(A97,'BD UM'!A:A,'BD UM'!C:C) -> 9002 | X97: =_xlfn.XLOOKUP(A97,'BD U6M'!A:A,'BD U6M'!C:C) -> 9132.9 | Y97: =_xlfn.XLOOKUP(A97,'BD UM'!A:A,'BD UM'!D:D) -> 280438.87 | Z97: =_xlfn.XLOOKUP(A97,'BD U6M'!A:A,'BD U6M'!D:D) -> 288784.8 | AA97: =_xlfn.XLOOKUP(A97,'BD UM'!A:A,'BD UM'!E:E) -> 57557.019 | AB97: =_xlfn.XLOOKUP(A97,'BD U6M'!A:A,'BD U6M'!E:E) -> 57595.036 | AC97: =_xlfn.XLOOKUP(A97,'BD UM'!A:A,'BD UM'!F:F) -> 116444.43 | AD97: =_xlfn.XLOOKUP(A97,'BD U6M'!A:A,'BD U6M'!F:F) -> 117880.88 | AE97: =_xlfn.XLOOKUP(A97,'BD UM'!A:A,'BD UM'!G:G) -> 10237.673 | AF97: =_xlfn.XLOOKUP(A97,'BD U6M'!A:A,'BD U6M'!G:G) -> 10138.128 | AG97: =_xlfn.XLOOKUP(A97,'BD UM'!A:A,'BD UM'!H:H) -> 0 | AH97: COMERCIO/SERVICIO | AI97: ABIERTA | AJ97: BASE | AK97: TMCB | AL97: 232000 | AM97: 75.24 | AN97: Santa Matilde | AO97: Medio
A98: 50G73 | B98: Centro Norte | C98: Distrito Capital | D98: Bogotá | E98: LOS ANDES | F98: 5 | G98: Calle 100 | H98: 0 | I98: Esquinero | J98: 178.05 | K98: 2847 | L98: 1445 | M98: 57 | N98: 44089 | O98: 15 | P98: 16 | Q98: 30 | R98: 75 | S98: 4.6876 | U98: =_xlfn.XLOOKUP(A98,'BD UM'!A:A,'BD UM'!B:B) -> 26220 | V98: =_xlfn.XLOOKUP(A98,'BD U6M'!A:A,'BD U6M'!B:B) -> 26145.667 | W98: =_xlfn.XLOOKUP(A98,'BD UM'!A:A,'BD UM'!C:C) -> 9749.6 | X98: =_xlfn.XLOOKUP(A98,'BD U6M'!A:A,'BD U6M'!C:C) -> 10091.7 | Y98: =_xlfn.XLOOKUP(A98,'BD UM'!A:A,'BD UM'!D:D) -> 255634.7 | Z98: =_xlfn.XLOOKUP(A98,'BD U6M'!A:A,'BD U6M'!D:D) -> 263854.59 | AA98: =_xlfn.XLOOKUP(A98,'BD UM'!A:A,'BD UM'!E:E) -> 28447.685 | AB98: =_xlfn.XLOOKUP(A98,'BD U6M'!A:A,'BD U6M'!E:E) -> 34290.691 | AC98: =_xlfn.XLOOKUP(A98,'BD UM'!A:A,'BD UM'!F:F) -> 105633.44 | AD98: =_xlfn.XLOOKUP(A98,'BD U6M'!A:A,'BD U6M'!F:F) -> 105215.36 | AE98: =_xlfn.XLOOKUP(A98,'BD UM'!A:A,'BD UM'!G:G) -> 17909.857 | AF98: =_xlfn.XLOOKUP(A98,'BD U6M'!A:A,'BD U6M'!G:G) -> 18066.94 | AG98: =_xlfn.XLOOKUP(A98,'BD UM'!A:A,'BD UM'!H:H) -> 0 | AH98: COMERCIO/SERVICIO | AI98: ABIERTA | AJ98: BASE | AK98: TMCB | AL98: 204160 | AM98: 95.96 | AN98: Heroes | AO98: Medio
A99: 50IAH | B99: Centro Norte | C99: Distrito Capital | D99: Bogotá | E99: SANTA BARBARA | F99: 4 | G99: Calle 116 | H99: 0 | I99: Esquinero | J99: 87.08 | K99: 958 | L99: 937 | M99: 0 | N99: 44174 | O99: 9 | P99: 23 | Q99: 31 | R99: 68 | S99: 4.6981 | U99: =_xlfn.XLOOKUP(A99,'BD UM'!A:A,'BD UM'!B:B) -> 19685 | V99: =_xlfn.XLOOKUP(A99,'BD U6M'!A:A,'BD U6M'!B:B) -> 20110.833 | W99: =_xlfn.XLOOKUP(A99,'BD UM'!A:A,'BD UM'!C:C) -> 11676.3 | X99: =_xlfn.XLOOKUP(A99,'BD U6M'!A:A,'BD U6M'!C:C) -> 11751.4 | Y99: =_xlfn.XLOOKUP(A99,'BD UM'!A:A,'BD UM'!D:D) -> 229847.87 | Z99: =_xlfn.XLOOKUP(A99,'BD U6M'!A:A,'BD U6M'!D:D) -> 236330.9 | AA99: =_xlfn.XLOOKUP(A99,'BD UM'!A:A,'BD UM'!E:E) -> 21665.065 | AB99: =_xlfn.XLOOKUP(A99,'BD U6M'!A:A,'BD U6M'!E:E) -> 22191.855 | AC99: =_xlfn.XLOOKUP(A99,'BD UM'!A:A,'BD UM'!F:F) -> 86647.024 | AD99: =_xlfn.XLOOKUP(A99,'BD U6M'!A:A,'BD U6M'!F:F) -> 87266.729 | AE99: =_xlfn.XLOOKUP(A99,'BD UM'!A:A,'BD UM'!G:G) -> 11863.078 | AF99: =_xlfn.XLOOKUP(A99,'BD U6M'!A:A,'BD U6M'!G:G) -> 11981.64 | AG99: =_xlfn.XLOOKUP(A99,'BD UM'!A:A,'BD UM'!H:H) -> 0 | AH99: NICHO | AI99: ABIERTA | AJ99: RECESO | AK99: TMCB | AL99: 204160 | AM99: 102.06 | AN99: Primavera | AO99: Alto
A100: 50VBQ | B100: Centro Norte | C100: Distrito Capital | D100: Bogotá | E100: NIZA | F100: 5 | G100: Calle 138 | H100: 0 | I100: Esquinero | J100: 157.98 | K100: 1403 | L100: 451 | M100: 0 | N100: 44559 | O100: 29 | P100: 3 | Q100: 31 | R100: 56 | S100: 4.7275 | U100: =_xlfn.XLOOKUP(A100,'BD UM'!A:A,'BD UM'!B:B) -> 24457 | V100: =_xlfn.XLOOKUP(A100,'BD U6M'!A:A,'BD U6M'!B:B) -> 24975.667 | W100: =_xlfn.XLOOKUP(A100,'BD UM'!A:A,'BD UM'!C:C) -> 14097.8 | X100: =_xlfn.XLOOKUP(A100,'BD U6M'!A:A,'BD U6M'!C:C) -> 13641.8 | Y100: =_xlfn.XLOOKUP(A100,'BD UM'!A:A,'BD UM'!D:D) -> 344789 | Z100: =_xlfn.XLOOKUP(A100,'BD U6M'!A:A,'BD U6M'!D:D) -> 340713.78 | AA100: =_xlfn.XLOOKUP(A100,'BD UM'!A:A,'BD UM'!E:E) -> 48992.237 | AB100: =_xlfn.XLOOKUP(A100,'BD U6M'!A:A,'BD U6M'!E:E) -> 43079.746 | AC100: =_xlfn.XLOOKUP(A100,'BD UM'!A:A,'BD UM'!F:F) -> 121508.91 | AD100: =_xlfn.XLOOKUP(A100,'BD U6M'!A:A,'BD U6M'!F:F) -> 117637.2 | AE100: =_xlfn.XLOOKUP(A100,'BD UM'!A:A,'BD UM'!G:G) -> 11053.879 | AF100: =_xlfn.XLOOKUP(A100,'BD U6M'!A:A,'BD U6M'!G:G) -> 11165.656 | AG100: =_xlfn.XLOOKUP(A100,'BD UM'!A:A,'BD UM'!H:H) -> 0 | AH100: COMERCIO/SERVICIO | AI100: ABIERTA | AJ100: RECESO | AK100: TMCB | AL100: 204160 | AM100: 100.51 | AN100: Santa Margarita | AO100: Alto
...

Sheet HISTORICO VENTAS
A2: Tienda 2026 | B2: (Varios elementos)
A3: Mes | B3: (Varios elementos)
A5: $ Ventas Operativas Prom. Tienda | B5: Etiquetas de columna
A6: Etiquetas de fila | B6: ene 17 | C6: feb 17 | D6: mar 17 | E6: abr 17 | F6: may 17 | G6: jun 17 | H6: jul 17 | I6: ago 17 | J6: sep 17 | K6: oct 17 | L6: nov 17 | M6: ene 18 | N6: feb 18 | O6: mar 18 | P6: abr 18 | Q6: may 18 | R6: jun 18 | S6: jul 18 | T6: ago 18 | U6: sep 18 | V6: oct 18 | W6: nov 18 | X6: ene 19 | Y6: feb 19 | Z6: mar 19 | AA6: abr 19 | AB6: may 19 | AC6: jun 19 | AD6: jul 19 | AE6: ago 19 | AF6: sep 19 | AG6: oct 19 | AH6: nov 19 | AI6: ene 20 | AJ6: feb 20 | AK6: mar 20 | AL6: abr 20 | AM6: may 20 | AN6: jun 20 | AO6: jul 20 | AP6: ago 20 | AQ6: sep 20 | AR6: oct 20 | AS6: nov 20 | AT6: ene 21 | AU6: feb 21 | AV6: mar 21 | AW6: abr 21 | AX6: may 21 | AY6: jun 21 | AZ6: jul 21 | BA6: ago 21 | BB6: sep 21 | BC6: oct 21 | BD6: nov 21 | BE6: ene 22 | BF6: feb 22 | BG6: mar 22 | BH6: abr 22 | BI6: may 22 | BJ6: jun 22 | BK6: jul 22 | BL6: ago 22 | BM6: sep 22 | BN6: oct 22 | BO6: nov 22 | BP6: ene 23 | BQ6: feb 23 | BR6: mar 23 | BS6: abr 23 | BT6: may 23 | BU6: jun 23 | BV6: jul 23 | BW6: ago 23 | BX6: sep 23 | BY6: oct 23 | BZ6: nov 23 | CA6: ene 24 | CB6: feb 24 | CC6: mar 24 | CD6: abr 24 | CE6: may 24 | CF6: jun 24 | CG6: jul 24 | CH6: ago 24 | CI6: sep 24 | CJ6: oct 24 | CK6: nov 24 | CL6: ene 25 | CM6: feb 25 | CN6: mar 25 | CO6: abr 25 | CP6: may 25 | CQ6: jun 25 | CR6: jul 25 | CS6: ago 25 | CT6: sep 25 | CU6: oct 25 | CV6: nov 25 | CW6: ene 26 | CX6: feb 26 | CY6: mar 26 | CZ6: abr 26 | DA6: may 26 | DB6: jun 26 | DC6: jul 26 | DD6: ago 26 | DE6: Total general
A7: 5002I | CK7: 7892.3915 | CL7: 133622.78 | CM7: 130162.6 | CN7: 165446.71 | CO7: 155130.55 | CP7: 168167.91 | CQ7: 180130.21 | CR7: 158749.31 | CS7: 168918.3 | CT7: 164454.68 | CU7: 190613.36 | CV7: 190541.74 | CW7: 172193.18 | CX7: 154072.74 | CY7: 197528.5 | CZ7: 195420.18 | DA7: 205164.95 | DB7: 198609.13 | DC7: 211442.47 | DD7: 211069.4 | DE7: 167966.55
A8: 5003A | BB8: 50668.778 | BC8: 140328.39 | BD8: 133315.78 | BE8: 190114.56 | BF8: 168804.24 | BG8: 177242.48 | BH8: 198958.6 | BI8: 207040.82 | BJ8: 197291.25 | BK8: 225744.63 | BL8: 198939.39 | BM8: 195737.7 | BN8: 216992.6 | BO8: 199838.52 | BP8: 203381.58 | BQ8: 189512.27 | BR8: 200283.46 | BS8: 217666.11 | BT8: 200524.65 | BU8: 202229.44 | BV8: 201901.59 | BW8: 191294.39 | BX8: 190140.85 | BY8: 183013.32 | BZ8: 182385.76 | CA8: 209076.3 | CB8: 185759.85 | CC8: 211464.33 | CD8: 182464.31 | CE8: 197493.88 | CF8: 207410.27 | CG8: 208027.5 | CH8: 194879.82 | CI8: 199568.34 | CJ8: 195803.52 | CK8: 183300.27 | CL8: 197029.26 | CM8: 172415.02 | CN8: 210226.66 | CO8: 205551.14 | CP8: 218773.41 | CQ8: 235846.61 | CR8: 206631.75 | CS8: 221718.5 | CT8: 230111.47 | CU8: 235436.57 | CV8: 227967.45 | CW8: 245276.62 | CX8: 206461.05 | CY8: 233543.09 | CZ8: 235413.98 | DA8: 271873.71 | DB8: 253178.1 | DC8: 248638.54 | DD8: 244865.41 | DE8: 202537.42
A9: 500A9 | CJ9: 114078.9 | CK9: 164358.66 | CL9: 135670.76 | CM9: 160283.53 | CN9: 177793.06 | CO9: 161036.69 | CP9: 194796.53 | CQ9: 176396.33 | CR9: 171695.77 | CS9: 190048.01 | CT9: 189928.55 | CU9: 207196.67 | CV9: 200204.54 | CW9: 161908.51 | CX9: 210818.66 | CY9: 227107.24 | CZ9: 222331.84 | DA9: 293910.75 | DB9: 279441.32 | DC9: 281701.81 | DD9: 320179.63 | DE9: 201947.04
A10: 500D4 | CA10: 107238.14 | CB10: 114128.89 | CC10: 129323.21 | CD10: 123750.08 | CE10: 131176.14 | CF10: 125240.71 | CG10: 129284.36 | CH10: 141262.31 | CI10: 143678.62 | CJ10: 148219.3 | CK10: 142200.34 | CL10: 131677.27 | CM10: 131557.68 | CN10: 148080.96 | CO10: 140917.48 | CP10: 156665.82 | CQ10: 142310.44 | CR10: 144614.62 | CS10: 147306.41 | CT10: 151463.37 | CU10: 150869.37 | CV10: 147642.4 | CW10: 135419.79 | CX10: 143252.23 | CY10: 164923.3 | CZ10: 156850.3 | DA10: 188341.37 | DB10: 160249.25 | DC10: 165807.31 | DD10: 165247.04 | DE10: 143623.28
A11: 500DU | CC11: 24871.007 | CD11: 153230.83 | CE11: 182793.1 | CF11: 178884.52 | CG11: 200416.46 | CH11: 183272.96 | CI11: 181430.41 | CJ11: 178115.84 | CK11: 155672.88 | CL11: 172746.93 | CM11: 159685.58 | CN11: 169570.62 | CO11: 160220.31 | CP11: 174903.03 | CQ11: 176470.58 | CR11: 178174.74 | CS11: 178007.49 | CT11: 178069.58 | CU11: 195585.43 | CV11: 182605.21 | CW11: 202282.68 | CX11: 202989.71 | CY11: 207705.57 | CZ11: 184818.22 | DA11: 213160.65 | DB11: 191609.84 | DC11: 197453.08 | DD11: 202683.25 | DE11: 177408.23
A12: 500E2 | BW12: 4662.265 | BX12: 125649.25 | BY12: 130288.21 | BZ12: 142021.17 | CA12: 162277.15 | CB12: 150360.78 | CC12: 200222.58 | CD12: 172431.94 | CE12: 182770.3 | CF12: 182938.85 | CG12: 190993.34 | CH12: 188955.26 | CI12: 194591.23 | CJ12: 193533.05 | CK12: 221926.96 | CL12: 210366.89 | CM12: 167307.47 | CN12: 190983.47 | CO12: 192360.33 | CP12: 203919.11 | CQ12: 209477.22 | CR12: 216117.85 | CS12: 226459.03 | CT12: 209281.56 | CU12: 217987.67 | CV12: 212096.59 | CW12: 227914.78 | CX12: 198374.95 | CY12: 210230.82 | CZ12: 194039.16 | DA12: 206644.85 | DB12: 204492.04 | DC12: 203435.58 | DD12: 62530.599 | DE12: 182577.71
A13: 500EZ | AG13: 68487.677 | AH13: 149361.4 | AI13: 174304.01 | AJ13: 187006.81 | AK13: 154580.92 | AL13: 79700.254 | AM13: 98108.449 | AN13: 124392.84 | AO13: 141868.59 | AP13: 139039.94 | AQ13: 165688.17 | AR13: 178379.08 | AS13: 178327.26 | AT13: 151065.42 | AU13: 182933.31 | AV13: 204110.55 | AW13: 177507.47 | AX13: 206251.06 | AY13: 213692.9 | AZ13: 226793.65 | BA13: 220256.73 | BB13: 234097.22 | BC13: 247325 | BD13: 251894.92 | BE13: 247496.87 | BF13: 243757.97 | BG13: 276137.87 | BH13: 253508.94 | BI13: 271323.82 | BJ13: 266730.33 | BK13: 277241.36 | BL13: 273287.21 | BM13: 284702.63 | BN13: 271479.03 | BO13: 262321.8 | BP13: 238905.61 | BQ13: 240799.14 | BR13: 263610.32 | BS13: 242163.73 | BT13: 250279.72 | BU13: 244480.49 | BV13: 248801.2 | BW13: 237669.85 | BX13: 260128.46 | BY13: 224690.01 | BZ13: 229947.77 | CA13: 230494.12 | CB13: 227468.95 | CC13: 236416.75 | CD13: 224007.03 | CE13: 240819.11 | CF13: 245449.01 | CG13: 259111.11 | CH13: 267259.69 | CI13: 266133.37 | CJ13: 276380.33 | CK13: 270483.58 | CL13: 263334.41 | CM13: 260663.12 | CN13: 277754.81 | CO13: 260112.92 | CP13: 275445.9 | CQ13: 265077.16 | CR13: 281995.65 | CS13: 276805.88 | CT13: 280306.69 | CU13: 283014.78 | CV13: 260785.15 | CW13: 249512.44 | CX13: 241364.94 | CY13: 271245.05 | CZ13: 251183.79 | DA13: 284157.01 | DB13: 269734.7 | DC13: 271519.59 | DD13: 244645.55 | DE13: 231280.53
A14: 500GV | CT14: 4168.7846 | CU14: 115449.47 | CV14: 133040.36 | CW14: 147083.65 | CX14: 123879.5 | CY14: 153360.86 | CZ14: 166911.66 | DA14: 202898.05 | DB14: 183338.04 | DC14: 179954.76 | DD14: 197691.66 | DE14: 146161.53
A15: 500TU | BU15: 20011.482 | BV15: 109106.42 | BW15: 116643.91 | BX15: 108853.08 | BY15: 122619.3 | BZ15: 127519.2 | CA15: 112262.48 | CB15: 123904.95 | CC15: 135707 | CD15: 120680.09 | CE15: 126049.38 | CF15: 120470.76 | CG15: 108217.94 | CH15: 139466.05 | CI15: 146164.09 | CJ15: 166687.26 | CK15: 180443.8 | CL15: 170618.25 | CM15: 174744.92 | CN15: 213293.45 | CO15: 190074.42 | CP15: 220307.31 | CQ15: 212999.38 | CR15: 196251.39 | CS15: 221776.04 | CT15: 218797.89 | CU15: 225907.73 | CV15: 224423.94 | CW15: 213096.94 | CX15: 210779.66 | CY15: 245758.87 | CZ15: 252417.28 | DA15: 274470.46 | DB15: 259570.47 | DC15: 264839.41 | DD15: 272910.75 | DE15: 176329.05
A16: 500WO | CL16: 128363.14 | CM16: 130180.16 | CN16: 169604.79 | CO16: 172515.19 | CP16: 196092.96 | CQ16: 184880.15 | CR16: 167320.47 | CS16: 191208.88 | CT16: 191643.76 | CU16: 190925.52 | CV16: 193549.17 | CW16: 186393.45 | CX16: 189138.84 | CY16: 214988.72 | CZ16: 220529.67 | DA16: 247422 | DB16: 204476.26 | DC16: 217850.69 | DD16: 224122.54 | DE16: 190589.81
A17: 500XK | BN17: 103365.89 | BO17: 148877.73 | BP17: 143467.52 | BQ17: 152084 | BR17: 158969.41 | BS17: 148548.28 | BT17: 150078.32 | BU17: 160103.16 | BV17: 155679.58 | BW17: 160966.25 | BX17: 161281.26 | BY17: 147601.67 | BZ17: 155420.81 | CA17: 149414.91 | CB17: 151349.22 | CC17: 172776.13 | CD17: 160011.8 | CE17: 169246.88 | CF17: 163851.57 | CG17: 183225.85 | CH17: 187673.54 | CI17: 173247.74 | CJ17: 184623.07 | CK17: 178484.92 | CL17: 174751.57 | CM17: 169978.91 | CN17: 186817.96 | CO17: 176513.44 | CP17: 189185.47 | CQ17: 173762.38 | CR17: 187895.59 | CS17: 193075.39 | CT17: 194212.99 | CU17: 202798.52 | CV17: 193496.78 | CW17: 179904.98 | CX17: 175191.12 | CY17: 205193.27 | CZ17: 190145.72 | DA17: 210567.52 | DB17: 203010.61 | DC17: 215997.44 | DD17: 204906.11 | DE17: 173203.61
A18: 5015G | BY18: 7934.4645 | BZ18: 151284.17 | CA18: 234889.97 | CB18: 126584.43 | CC18: 229708.21 | CD18: 109780.37 | CE18: 128348.23 | CF18: 256467.77 | CG18: 182064.67 | CH18: 228660.03 | CI18: 162778.67 | CJ18: 213185.79 | CK18: 213401.5 | CL18: 287713.12 | CM18: 157057.99 | CN18: 204029.41 | CO18: 277257.37 | CP18: 214172.08 | CQ18: 362498.1 | CR18: 248090.55 | CS18: 313488.36 | CT18: 228600.6 | CU18: 318624.36 | CV18: 294322.06 | CW18: 420850.09 | CX18: 186297.34 | CY18: 291684.78 | CZ18: 288845.32 | DA18: 300024.85 | DB18: 384743.27 | DC18: 328299.01 | DD18: 343769.78 | DE18: 240483.02
A19: 5015P | CD19: 35310.728 | CE19: 147774 | CF19: 157089.76 | CG19: 160397.82 | CH19: 167896.88 | CI19: 174215.6 | CJ19: 183250.71 | CK19: 189296.71 | CL19: 171151.63 | CM19: 150754.59 | CN19: 181747.48 | CO19: 178324.04 | CP19: 186140.39 | CQ19: 204679.09 | CR19: 191204.21 | CS19: 204587.14 | CT19: 185500.2 | CU19: 213552.94 | CV19: 205571.52 | CW19: 205197.68 | CX19: 180622.85 | CY19: 207091.79 | CZ19: 220003 | DA19: 276384.95 | DB19: 227610.13 | DC19: 223666.3 | DD19: 246171.3 | DE19: 187970.13
A20: 50162 | CI20: 5358.7767 | CJ20: 149928.42 | CK20: 159083.79 | CL20: 183018.39 | CM20: 179122.84 | CN20: 203930.32 | CO20: 183904.11 | CP20: 191349.25 | CQ20: 197697.5 | CR20: 194227.32 | CS20: 223224.25 | CT20: 222716.08 | CU20: 236298.11 | CV20: 236783.72 | CW20: 262939.49 | CX20: 247209.19 | CY20: 264157.84 | CZ20: 255543.02 | DA20: 310940.79 | DB20: 295887.25 | DC20: 286465.03 | DD20: 301174.18 | DE20: 217770.89
A21: 5016I | B21: 49478.937 | C21: 49060.068 | D21: 61088.428 | E21: 69378.974 | F21: 64643.273 | G21: 67977.242 | H21: 78424.498 | I21: 75920.409 | J21: 86526.606 | K21: 92957.589 | L21: 87829.028 | M21: 94917.446 | N21: 92416.92 | O21: 112462.37 | P21: 108038.64 | Q21: 109202.92 | R21: 108302.04 | S21: 114970.27 | T21: 115077.35 | U21: 124462.48 | V21: 117361.3 | W21: 131191.31 | X21: 134118.05 | Y21: 128447.96 | Z21: 149542.59 | AA21: 142371.16 | AB21: 145120.97 | AC21: 138504.88 | AD21: 133214.29 | AE21: 153249.31 | AF21: 163539.5 | AG21: 154665.56 | AH21: 159754.68 | AI21: 146655.51 | AJ21: 160943.24 | AK21: 129295.2 | AL21: 33768.29 | AM21: 45719.986 | AN21: 72485.853 | AO21: 91765.513 | AP21: 91085.548 | AQ21: 108748.46 | AR21: 149206.43 | AS21: 134167.14 | AT21: 120838.83 | AU21: 127320.3 | AV21: 137075.52 | AW21: 126900.23 | AX21: 152675.02 | AY21: 161587.18 | AZ21: 137355.52 | BA21: 163763.82 | BB21: 168736.61 | BC21: 215491.18 | BD21: 184481.62 | BE21: 184434.36 | BF21: 176869.07 | BG21: 190650.94 | BH21: 178648.21 | BI21: 189014.42 | BJ21: 178043.16 | BK21: 184224.58 | BL21: 189386.37 | BM21: 238805.9 | BN21: 236093.44 | BO21: 236562.44 | BP21: 145150.11 | BQ21: 149043.21 | BR21: 162550.02 | BS21: 173354.23 | BT21: 183993.31 | BU21: 178060.15 | BV21: 173882.69 | BW21: 168518.55 | BX21: 193137.98 | BY21: 139241.12 | BZ21: 131078.07 | CA21: 132197.96 | CB21: 123943.04 | CC21: 148370.52 | CD21: 125077.58 | CE21: 123625.46 | CF21: 138503.99 | CG21: 126387.4 | CH21: 134429.18 | CI21: 147770.58 | CJ21: 158566.26 | CK21: 140937.34 | CL21: 145946.54 | CM21: 126214.6 | CN21: 147968.25 | CO21: 141161.27 | CP21: 150398.41 | CQ21: 137844.31 | CR21: 133361.1 | CS21: 136888.61 | CT21: 141779.78 | CU21: 140475.62 | CV21: 144430.84 | CW21: 134464 | CX21: 127076.08 | CY21: 154111.46 | CZ21: 143662.53 | DA21: 178528.94 | DB21: 145463.07 | DC21: 147263.33 | DD21: 158652.75 | DE21: 137294.65
A22: 5017O | CA22: 3003.2935 | CB22: 96742.996 | CC22: 137164.56 | CD22: 119798.36 | CE22: 125883.74 | CF22: 133218.13 | CG22: 145016.42 | CH22: 146571.16 | CI22: 135337.56 | CJ22: 136873.14 | CK22: 143971.91 | CL22: 154170.33 | CM22: 118493.14 | CN22: 140318.02 | CO22: 146262.9 | CP22: 148968.24 | CQ22: 157334.65 | CR22: 156757.28 | CS22: 176986.35 | CT22: 163378.47 | CU22: 155406.02 | CV22: 164540.63 | CW22: 183079.63 | CX22: 145652.81 | CY22: 190486.46 | CZ22: 193067.58 | DA22: 214139.81 | DB22: 196866.64 | DC22: 204967.06 | DD22: 220152.28 | DE22: 151820.32
A23: 50184 | BW23: 6383.2805 | BX23: 157481.26 | BY23: 184340.93 | BZ23: 169730.68 | CA23: 279415.06 | CB23: 150393.22 | CC23: 238932.54 | CD23: 132348.74 | CE23: 152690.88 | CF23: 240113.43 | CG23: 196794.08 | CH23: 227862.75 | CI23: 201744.03 | CJ23: 285268.23 | CK23: 276948.7 | CL23: 394201.48 | CM23: 193801.74 | CN23: 236382.41 | CO23: 283219.63 | CP23: 241643.83 | CQ23: 360670.27 | CR23: 284763.95 | CS23: 312932.36 | CT23: 235439.1 | CU23: 344471.34 | CV23: 316463.96 | CW23: 428950.11 | CX23: 208238.85 | CY23: 301662.55 | CZ23: 284429.39 | DA23: 293503.81 | DB23: 363524.63 | DC23: 358890.72 | DD23: 344739.25 | DE23: 255540.51
A24: 501CC | BM24: 13705.722 | BN24: 129858.42 | BO24: 128432.05 | BP24: 153660.46 | BQ24: 152582.12 | BR24: 161469.71 | BS24: 154068.14 | BT24: 150560.62 | BU24: 161192.14 | BV24: 170366.68 | BW24: 159245.59 | BX24: 169053 | BY24: 162927.57 | BZ24: 169219.14 | CA24: 172180.56 | CB24: 160247.72 | CC24: 189023.06 | CD24: 168213.33 | CE24: 169862.84 | CF24: 174477.14 | CG24: 165020.74 | CH24: 171453.3 | CI24: 175811.6 | CJ24: 178721.27 | CK24: 173152.85 | CL24: 158626.55 | CM24: 147390.56 | CN24: 163973.12 | CO24: 152731.84 | CP24: 172412.13 | CQ24: 165549.22 | CR24: 153683.07 | CS24: 160334.9 | CT24: 161416.23 | CU24: 187047.84 | CV24: 179111.29 | CW24: 174086.06 | CX24: 155178.71 | CY24: 175782.62 | CZ24: 158745.47 | DA24: 174228.62 | DB24: 168591.88 | DC24: 176334.06 | DD24: 176985.86 | DE24: 161289
A25: 501H3 | BY25: 41266.123 | BZ25: 103568.14 | CA25: 107756.35 | CB25: 94414.292 | CC25: 124726.26 | CD25: 102696.61 | CE25: 110843.29 | CF25: 119634.25 | CG25: 123104.55 | CH25: 121504.6 | CI25: 124324.12 | CJ25: 124953.36 | CK25: 128494.37 | CL25: 123618.73 | CM25: 110577.55 | CN25: 133442.46 | CO25: 126810.52 | CP25: 131408.26 | CQ25: 141593.38 | CR25: 136736.77 | CS25: 143633.56 | CT25: 136129.43 | CU25: 142623.22 | CV25: 143264.15 | CW25: 141800.76 | CX25: 126859.99 | CY25: 154536.94 | CZ25: 147677.13 | DA25: 157486.7 | DB25: 157405.36 | DC25: 147847.12 | DD25: 149349.52 | DE25: 127502.75
A26: 501H8 | BJ26: 91901.696 | BK26: 194270.38 | BL26: 221446.18 | BM26: 258505.6 | BN26: 252257.94 | BO26: 281758.32 | BP26: 177131.61 | BQ26: 181403.8 | BR26: 172151.52 | BS26: 174100.12 | BT26: 212945.54 | BU26: 205771.71 | BV26: 143270.83 | BW26: 131672.97 | BX26: 167454.79 | BY26: 136431.59 | BZ26: 118597 | CA26: 269891.23 | CB26: 173576.3 | CC26: 203111.64 | CD26: 160389.58 | CE26: 137568.42 | CF26: 147164.09 | CG26: 146632.82 | CH26: 145567.51 | CI26: 144381.97 | CJ26: 154045.06 | CK26: 173175.89 | CL26: 174419.54 | CM26: 150663.28 | CN26: 177417.33 | CO26: 176577.43 | CP26: 192672.6 | CQ26: 191057.52 | CR26: 178241.62 | CS26: 192707.72 | CT26: 176837.45 | CU26: 186096.8 | CV26: 200106.75 | CW26: 199881.45 | CX26: 171702.93 | CY26: 208429.09 | CZ26: 202257.97 | DA26: 243586.02 | DB26: 214196.4 | DC26: 209606.91 | DD26: 209619.38 | DE26: 183673.5
A27: 501HT | BS27: 47830.17 | BT27: 138308.23 | BU27: 137208.97 | BV27: 153256 | BW27: 127722.62 | BX27: 133937.04 | BY27: 134515.5 | BZ27: 135736.28 | CA27: 154614.23 | CB27: 139024.3 | CC27: 166918.44 | CD27: 138983.51 | CE27: 156408.44 | CF27: 162154.88 | CG27: 164241.16 | CH27: 167722.77 | CI27: 160370.04 | CJ27: 161500.2 | CK27: 168648.77 | CL27: 156536.94 | CM27: 146613.85 | CN27: 169942.86 | CO27: 153858.3 | CP27: 169298.47 | CQ27: 165734.52 | CR27: 153793.72 | CS27: 170312.73 | CT27: 151700.11 | CU27: 160872.81 | CV27: 158318.83 | CW27: 167827.22 | CX27: 145564.82 | CY27: 163587.49 | CZ27: 165209.92 | DA27: 179202.69 | DB27: 170792.35 | DC27: 165660.28 | DD27: 168388.22 | DE27: 153482.04
A28: 501KA | BR28: 39516.128 | BS28: 146164.07 | BT28: 136139.74 | BU28: 156963.2 | BV28: 161440.56 | BW28: 136532.79 | BX28: 135836.61 | BY28: 148545.36 | BZ28: 143468.74 | CA28: 181294.63 | CB28: 121848.35 | CC28: 159903.62 | CD28: 107501.71 | CE28: 117344.66 | CF28: 147972 | CG28: 143824.21 | CH28: 143591.26 | CI28: 157298.21 | CJ28: 191422.66 | CK28: 164439.12 | CL28: 195078.08 | CM28: 128142.72 | CN28: 151011.59 | CO28: 154703.84 | CP28: 147248.66 | CQ28: 187085.73 | CR28: 156870.87 | CS28: 170166.93 | CT28: 152310.86 | CU28: 194352.69 | CV28: 161812.6 | CW28: 209363.45 | CX28: 133737.99 | CY28: 173106.06 | CZ28: 167908.62 | DA28: 176631.11 | DB28: 190434.32 | DC28: 188980.28 | DD28: 185738.29 | DE28: 155531.6
A29: 501M6 | CM29: 7084.7855 | CN29: 127861.72 | CO29: 119910.83 | CP29: 132805.35 | CQ29: 147331.75 | CR29: 155975.89 | CS29: 166660.87 | CT29: 173059.22 | CU29: 171499.51 | CV29: 193860.73 | CW29: 203537.01 | CX29: 195521.21 | CY29: 201992.44 | CZ29: 193932.58 | DA29: 219181.42 | DB29: 205743.32 | DC29: 213806.97 | DD29: 214562.36 | DE29: 169129.33
A30: 501UG | AI30: 70497.082 | AJ30: 211920.34 | AK30: 188396.2 | AL30: 83439.338 | AM30: 101272.72 | AN30: 116647.59 | AO30: 128336.96 | AP30: 126367.79 | AQ30: 128932.81 | AR30: 148367.04 | AS30: 122288.45 | AT30: 101891 | AU30: 128845.86 | AV30: 149158.97 | AW30: 130087.83 | AX30: 131350.88 | AY30: 149771.24 | AZ30: 169431.52 | BA30: 178519.87 | BB30: 198149.26 | BC30: 222476.93 | BD30: 222440.84 | BE30: 210356.73 | BF30: 223156.32 | BG30: 275399.04 | BH30: 248991.48 | BI30: 276374.3 | BJ30: 277100.21 | BK30: 290796.65 | BL30: 304289.4 | BM30: 339608.52 | BN30: 332414.91 | BO30: 339653.34 | BP30: 318708.2 | BQ30: 330034.23 | BR30: 375051 | BS30: 343072.57 | BT30: 358703.03 | BU30: 354761.5 | BV30: 352974.53 | BW30: 376012.36 | BX30: 372034.14 | BY30: 358365.94 | BZ30: 361095.12 | CA30: 353367.03 | CB30: 370511.3 | CC30: 415243.15 | CD30: 385551.52 | CE30: 416860.02 | CF30: 378684.5 | CG30: 412734.45 | CH30: 398125.7 | CI30: 375566.95 | CJ30: 379452.24 | CK30: 317458.44 | CL30: 321588.15 | CM30: 320778.92 | CN30: 363157.15 | CO30: 356365.13 | CP30: 368019.29 | CQ30: 346481.68 | CR30: 375320.84 | CS30: 356704.56 | CT30: 379080.06 | CU30: 379912.13 | CV30: 352463.87 | CW30: 323881.32 | CX30: 303031.84 | CY30: 345640.03 | CZ30: 326907.44 | DA30: 358201.09 | DB30: 327131.21 | DC30: 313444 | DD30: 353354.26 | DE30: 283818.41
A31: 501WG | CB31: 2200.7683 | CC31: 117921.32 | CD31: 112630.17 | CE31: 130321.8 | CF31: 138613.68 | CG31: 133234.07 | CH31: 131933.12 | CI31: 132108.27 | CJ31: 148677.04 | CK31: 149705.42 | CL31: 135779.48 | CM31: 122794.39 | CN31: 144203.36 | CO31: 136796.51 | CP31: 149020.58 | CQ31: 148528.9 | CR31: 151388.87 | CS31: 170046.61 | CT31: 158545.27 | CU31: 163245.06 | CV31: 181431.21 | CW31: 174236.4 | CX31: 164721.66 | CY31: 193657.47 | CZ31: 190533.57 | DA31: 226509.84 | DB31: 200429.57 | DC31: 213168.62 | DD31: 77714.497 | DE31: 148279.23
A32: 501WX | AX32: 32653.182 | AY32: 135409.58 | AZ32: 171481.61 | BA32: 186711.28 | BB32: 223813.09 | BC32: 239853.23 | BD32: 235854.24 | BE32: 232350.94 | BF32: 239051.94 | BG32: 303423.05 | BH32: 265821.44 | BI32: 307001.04 | BJ32: 286623.57 | BK32: 301652.3 | BL32: 309695.33 | BM32: 337437.44 | BN32: 318302.94 | BO32: 310529.78 | BP32: 257497.97 | BQ32: 275017.94 | BR32: 312673.33 | BS32: 276395.84 | BT32: 309323.2 | BU32: 290786.64 | BV32: 298537.24 | BW32: 295782.95 | BX32: 327348.26 | BY32: 308782.45 | BZ32: 299781.63 | CA32: 275936.89 | CB32: 288917.49 | CC32: 330024.41 | CD32: 290273.13 | CE32: 325601.97 | CF32: 289355.13 | CG32: 320340.9 | CH32: 336194.63 | CI32: 342809.84 | CJ32: 337791.99 | CK32: 339342.44 | CL32: 296975.36 | CM32: 301720.56 | CN32: 338312.3 | CO32: 317194.21 | CP32: 337728.64 | CQ32: 312474.72 | CR32: 335713.69 | CS32: 331674.99 | CT32: 374991.83 | CU32: 363023.39 | CV32: 322348.34 | CW32: 287935.37 | CX32: 308419.36 | CY32: 361355.79 | CZ32: 330406.81 | DA32: 388511.61 | DB32: 333600.45 | DC32: 353195.64 | DD32: 347961.85 | DE32: 296775.04
A33: 501YH | Z33: 67421.609 | AA33: 96430.314 | AB33: 120145.71 | AC33: 139532.48 | AD33: 145235.52 | AE33: 155809.43 | AF33: 157334.49 | AG33: 155403.11 | AH33: 156309.38 | AI33: 157100.2 | AJ33: 156681.88 | AK33: 146904.87 | AL33: 122828.99 | AM33: 147309.29 | AN33: 93751.276 | AO33: 116002.56 | AP33: 135225.15 | AQ33: 120530.52 | AR33: 155487.55 | AS33: 147081.88 | AT33: 114855.73 | AU33: 138798.65 | AV33: 150269.04 | AW33: 135874.31 | AX33: 151832.41 | AY33: 173697.18 | AZ33: 185819.35 | BA33: 190279.28 | BB33: 195669.94 | BC33: 223048.58 | BD33: 208584.5 | BE33: 247006.87 | BF33: 231493.65 | BG33: 242408.82 | BH33: 232602.8 | BI33: 234520.98 | BJ33: 214029.29 | BK33: 260791.94 | BL33: 227566.71 | BM33: 234695.76 | BN33: 247219.11 | BO33: 221757.68 | BP33: 245973.09 | BQ33: 249587.88 | BR33: 244300.24 | BS33: 252821.88 | BT33: 247537.81 | BU33: 239697.72 | BV33: 256822.07 | BW33: 239526.15 | BX33: 244894.35 | BY33: 235656.54 | BZ33: 233626.11 | CA33: 235016.58 | CB33: 226227.54 | CC33: 245351.95 | CD33: 200090.81 | CE33: 227694 | CF33: 251194.51 | CG33: 259151.86 | CH33: 261895.59 | CI33: 242545.7 | CJ33: 268001.02 | CK33: 256834.44 | CL33: 232773.25 | CM33: 207281.11 | CN33: 232474.11 | CO33: 217981.6 | CP33: 238560.97 | CQ33: 241312.08 | CR33: 217266.09 | CS33: 209529.73 | CT33: 205242.83 | CU33: 205910.1 | CV33: 195270.54 | CW33: 192251.53 | CX33: 177365.19 | CY33: 199155.64 | CZ33: 190835.62 | DA33: 205660.91 | DB33: 214228.52 | DC33: 221322.81 | DD33: 211202.33 | DE33: 199221.95
A34: 501Z1 | CQ34: 11491.739 | CR34: 129424.41 | CS34: 163418.37 | CT34: 162199.04 | CU34: 172886.32 | CV34: 192960.88 | CW34: 212509.7 | CX34: 194360.16 | CY34: 228280.27 | CZ34: 232426.9 | DA34: 278206.72 | DB34: 265488.41 | DC34: 298674.2 | DD34: 318810.28 | DE34: 204366.96
A35: 50206 | DD35: 1595.284 | DE35: 1595.284
A36: 5023G | CI36: 6339.8464 | CJ36: 127438.68 | CK36: 95753.659 | CL36: 124414.25 | CM36: 87603.63 | CN36: 117354.33 | CO36: 120195.96 | CP36: 120781.73 | CQ36: 162504.48 | CR36: 149617.09 | CS36: 167076.93 | CT36: 158210.36 | CU36: 160850.78 | CV36: 155553.75 | CW36: 178188.28 | CX36: 137254.11 | CY36: 165909.68 | CZ36: 177057.43 | DA36: 188203.29 | DB36: 206370.68 | DC36: 180321.02 | DD36: 179760.22 | DE36: 143943.64
A37: 5024U | DA37: 27233.571 | DB37: 201753.34 | DC37: 202937.4 | DD37: 207254.82 | DE37: 159794.78
A38: 5026R | CJ38: 17055.139 | CK38: 192922.69 | CL38: 175891.02 | CM38: 172037.28 | CN38: 204844.6 | CO38: 202376.27 | CP38: 223563.07 | CQ38: 228139.38 | CR38: 207386.02 | CS38: 231190.93 | CT38: 225939.18 | CU38: 223000.53 | CV38: 233339.14 | CW38: 243077.12 | CX38: 232856.13 | CY38: 266953.04 | CZ38: 244737.11 | DA38: 279496.38 | DB38: 265141.97 | DC38: 267275.51 | DD38: 268883.99 | DE38: 219338.4
A39: 5028T | BQ39: 21812 | BR39: 138486.26 | BS39: 143499.19 | BT39: 155999.53 | BU39: 147383.6 | BV39: 150825.97 | BW39: 159927.02 | BX39: 162005.23 | BY39: 165232.42 | BZ39: 162959.35 | CA39: 154733.65 | CB39: 140998.59 | CC39: 164919.32 | CD39: 144171.19 | CE39: 146285.96 | CF39: 152938.7 | CG39: 163662.8 | CH39: 160991.24 | CI39: 158821.96 | CJ39: 173412.72 | CK39: 170058.25 | CL39: 143066.64 | CM39: 139967.34 | CN39: 158192.78 | CO39: 148836.92 | CP39: 164446.06 | CQ39: 157296.04 | CR39: 160936.16 | CS39: 170953.98 | CT39: 172969.28 | CU39: 177543.73 | CV39: 181757.51 | CW39: 174218.26 | CX39: 165807.05 | CY39: 184836.56 | CZ39: 184376.73 | DA39: 209722.32 | DB39: 204634.5 | DC39: 210789.97 | DD39: 203413.3 | DE39: 161322.25
A40: 5028Z | DA40: 11199.858 | DB40: 143993.05 | DC40: 155317.38 | DD40: 187249.79 | DE40: 124440.02
A41: 5029F | AE41: 10600.701 | AF41: 85532.572 | AG41: 94823.111 | AH41: 93239.481 | AI41: 105227.45 | AJ41: 106997.52 | AK41: 90474.707 | AL41: 50659.294 | AM41: 77391.819 | AN41: 84835.799 | AO41: 98908.052 | AP41: 105760.51 | AQ41: 116019.19 | AR41: 133651.68 | AS41: 132228.23 | AT41: 122732.5 | AU41: 122877.57 | AV41: 135519.7 | AW41: 123257.69 | AX41: 142212.45 | AY41: 175904.55 | AZ41: 149816.28 | BA41: 160463.58 | BB41: 181434.38 | BC41: 205891.92 | BD41: 190733.43 | BE41: 190830.94 | BF41: 174995.89 | BG41: 193668.13 | BH41: 202081.28 | BI41: 186783.38 | BJ41: 181323.21 | BK41: 205401.1 | BL41: 203883.29 | BM41: 243650.35 | BN41: 267428.89 | BO41: 316952.51 | BP41: 196719.5 | BQ41: 183562.22 | BR41: 201233.68 | BS41: 216968.09 | BT41: 221055.63 | BU41: 214975.55 | BV41: 273112.99 | BW41: 262461.32 | BX41: 239409.42 | BY41: 226592.61 | BZ41: 467364.93 | CA41: 320389.59 | CB41: 198606.99 | CC41: 211319.87 | CD41: 184868.77 | CE41: 188906.95 | CF41: 198788.96 | CG41: 196612.11 | CH41: 195753.91 | CI41: 197254.27 | CJ41: 205213.6 | CK41: 195781.79 | CL41: 190795.15 | CM41: 163320.31 | CN41: 206290.56 | CO41: 191068.03 | CP41: 191868.58 | CQ41: 200768.71 | CR41: 188674.51 | CS41: 217065.49 | CT41: 197781.87 | CU41: 199866.69 | CV41: 212499.15 | CW41: 205062 | CX41: 183853.06 | CY41: 218204.33 | CZ41: 206879.76 | DA41: 228324.6 | DB41: 200035.3 | DC41: 208043.12 | DD41: 221118.28 | DE41: 183239.3
A42: 502B0 | CE42: 4700.0627 | CF42: 112519.72 | CG42: 118698.87 | CH42: 125459.49 | CI42: 133720.35 | CJ42: 134474.69 | CK42: 136995.11 | CL42: 181695.63 | CM42: 142547.61 | CN42: 169677.41 | CO42: 174866.25 | CP42: 176845.71 | CQ42: 191237.57 | CR42: 187065.07 | CS42: 193022.4 | CT42: 193273.08 | CU42: 206417.13 | CV42: 206045.26 | CW42: 231115.62 | CX42: 193781.64 | CY42: 267720.69 | CZ42: 237780.85 | DA42: 263619.21 | DB42: 256711.82 | DC42: 257024.63 | DD42: 307286.2 | DE42: 184780.85
A43: 502B7 | BL43: 79477.092 | BM43: 163957.85 | BN43: 182138.96 | BO43: 176321.09 | BP43: 190533.43 | BQ43: 169398.59 | BR43: 188232.41 | BS43: 181609.69 | BT43: 175479.64 | BU43: 160211.11 | BV43: 151453.26 | BW43: 142093.46 | BX43: 135240.46 | BY43: 146120.72 | BZ43: 143424.26 | CA43: 155837.63 | CB43: 155065.81 | CC43: 181852.4 | CD43: 158431.91 | CE43: 169105.96 | CF43: 181563.42 | CG43: 177946.4 | CH43: 192686.71 | CI43: 190456.56 | CJ43: 192745.87 | CK43: 188709.09 | CL43: 193322.22 | CM43: 178017.15 | CN43: 205353.28 | CO43: 196026.27 | CP43: 214034.15 | CQ43: 197416.27 | CR43: 194985.19 | CS43: 210614.9 | CT43: 199640.99 | CU43: 235536.2 | CV43: 240710.6 | CW43: 224865.47 | CX43: 205076.57 | CY43: 246915.65 | CZ43: 248006.88 | DA43: 270129.54 | DB43: 263795.32 | DC43: 256181.57 | DD43: 261146.06 | DE43: 190485.96
A44: 502D5 | CA44: 102508.83 | CB44: 105309.19 | CC44: 126567.64 | CD44: 111291.72 | CE44: 115977.54 | CF44: 118573.23 | CG44: 114992.24 | CH44: 119273.52 | CI44: 123228.72 | CJ44: 129099.24 | CK44: 130499.08 | CL44: 136290.15 | CM44: 126787.6 | CN44: 141379.04 | CO44: 134356.22 | CP44: 144917.74 | CQ44: 144341.87 | CR44: 143185.04 | CS44: 151792.04 | CT44: 149094.91 | CU44: 160739.9 | CV44: 164796.85 | CW44: 161664.48 | CX44: 143033.01 | CY44: 164509.71 | CZ44: 160192.28 | DA44: 185007.56 | DB44: 169618.18 | DC44: 163812.65 | DD44: 167625.36 | DE44: 140348.85
A45: 502EL | CX45: 28470.528 | CY45: 190451.46 | CZ45: 210471.35 | DA45: 240978.93 | DB45: 241840.7 | DC45: 250006.11 | DD45: 200073.61 | DE45: 194613.24
A46: 502FE | CC46: 23908.624 | CD46: 79174.826 | CE46: 85122.127 | CF46: 95553.166 | CG46: 100902.92 | CH46: 108941.36 | CI46: 119304.02 | CJ46: 117854.03 | CK46: 125475.13 | CL46: 131956.03 | CM46: 119212.03 | CN46: 141034.02 | CO46: 139042.99 | CP46: 143754.73 | CQ46: 149914.55 | CR46: 154418.48 | CS46: 161790.01 | CT46: 154887.69 | CU46: 155315.28 | CV46: 167317.27 | CW46: 181566.48 | CX46: 163238.01 | CY46: 192295.3 | CZ46: 199001.42 | DA46: 210693.1 | DB46: 199547.96 | DC46: 197230.95 | DD46: 200794.17 | DE46: 143544.52
A47: 502IH | BX47: 19747.092 | BY47: 139189.68 | BZ47: 138646.47 | CA47: 161939.01 | CB47: 138262.43 | CC47: 162696.95 | CD47: 145634.97 | CE47: 167754.92 | CF47: 177228.3 | CG47: 176736.65 | CH47: 174413.19 | CI47: 166612.13 | CJ47: 170371.42 | CK47: 148472.22 | CL47: 166998.7 | CM47: 149098.82 | CN47: 177306.32 | CO47: 172285.88 | CP47: 181723.51 | CQ47: 189190.9 | CR47: 172619.25 | CS47: 181224.63 | CT47: 177644.19 | CU47: 176155.2 | CV47: 186986.82 | CW47: 195991.34 | CX47: 169214.04 | CY47: 213836.32 | CZ47: 198324.04 | DA47: 244948.03 | DB47: 212260.85 | DC47: 210506.61 | DD47: 205456.98 | DE47: 171802.36
A48: 502JA | BH48: 107723.83 | BI48: 155427.68 | BJ48: 156369.13 | BK48: 190372.33 | BL48: 182378.37 | BM48: 190667.51 | BN48: 212294.63 | BO48: 204356.2 | BP48: 200930.51 | BQ48: 197279.97 | BR48: 213910.22 | BS48: 221529.02 | BT48: 219539.21 | BU48: 223121.57 | BV48: 229003.01 | BW48: 218556.72 | BX48: 239182.18 | BY48: 217743.49 | BZ48: 229720.77 | CA48: 247424.08 | CB48: 241266.03 | CC48: 260973.74 | CD48: 232889.58 | CE48: 252609.03 | CF48: 260052.2 | CG48: 274131.91 | CH48: 266253.98 | CI48: 261991.94 | CJ48: 266160.55 | CK48: 261933.55 | CL48: 242423.47 | CM48: 227095.26 | CN48: 266631.63 | CO48: 262249.04 | CP48: 280813.8 | CQ48: 283736.22 | CR48: 271152.72 | CS48: 287838.73 | CT48: 278948.6 | CU48: 283866.3 | CV48: 297583.43 | CW48: 264336.89 | CX48: 240757.25 | CY48: 283917.97 | CZ48: 281000.23 | DA48: 304773.63 | DB48: 291960.92 | DC48: 271084.41 | DD48: 268866.55 | DE48: 241323.06
A49: 502NP | BE49: 146989.95 | BF49: 126485.57 | BG49: 135134.76 | BH49: 148816.53 | BI49: 145854.48 | BJ49: 143355.53 | BK49: 180113.89 | BL49: 163125.35 | BM49: 168072.72 | BN49: 183529.25 | BO49: 172620.75 | BP49: 181004.16 | BQ49: 179040.04 | BR49: 201403.48 | BS49: 219285.68 | BT49: 192075.76 | BU49: 195548.08 | BV49: 196049.73 | BW49: 184100.69 | BX49: 190113.19 | BY49: 183954.7 | BZ49: 176331.52 | CA49: 196785.78 | CB49: 181805.2 | CC49: 237676.68 | CD49: 193094.5 | CE49: 205641.54 | CF49: 208965.76 | CG49: 214167.73 | CH49: 213748.39 | CI49: 211808.6 | CJ49: 235834.77 | CK49: 240652.55 | CL49: 227908.46 | CM49: 194047.41 | CN49: 212422.7 | CO49: 200568.72 | CP49: 215914.15 | CQ49: 227770.22 | CR49: 209058.83 | CS49: 227852.36 | CT49: 218448.14 | CU49: 227696.8 | CV49: 219355.43 | CW49: 230951.45 | CX49: 205298.62 | CY49: 246779.52 | CZ49: 251178.54 | DA49: 286758.63 | DB49: 242344.97 | DC49: 252836.56 | DD49: 240873.88 | DE49: 201754.86
A50: 502P7 | BZ50: 24245.707 | CA50: 131816.01 | CB50: 118905.11 | CC50: 137529.26 | CD50: 122360.67 | CE50: 138976.06 | CF50: 142670.39 | CG50: 138950.24 | CH50: 158975.12 | CI50: 153020.54 | CJ50: 166779.67 | CK50: 166041.34 | CL50: 167811.34 | CM50: 148949.36 | CN50: 175773.32 | CO50: 177063.92 | CP50: 187506.39 | CQ50: 187606.89 | CR50: 172458.38 | CS50: 191459.69 | CT50: 175603.88 | CU50: 184654.34 | CV50: 183383.37 | CW50: 195075.4 | CX50: 168097.84 | CY50: 193620.83 | CZ50: 188820.12 | DA50: 229744.8 | DB50: 196467.43 | DC50: 201801.96 | DD50: 205393.79 | DE50: 165534.3
A51: 502SG | BA51: 42355.028 | BB51: 97779.108 | BC51: 128554.43 | BD51: 119223.67 | BE51: 174681.17 | BF51: 166330.42 | BG51: 178373.73 | BH51: 191671.35 | BI51: 193167.95 | BJ51: 185704.46 | BK51: 206145.47 | BL51: 182916.11 | BM51: 199416.68 | BN51: 232851.38 | BO51: 223645.22 | BP51: 221570.03 | BQ51: 252655.15 | BR51: 220135.55 | BS51: 225009.83 | BT51: 194520.83 | BU51: 351437.4 | BV51: 484801.85 | BW51: 743082.42 | BX51: 519386.63 | BY51: 290714.33 | BZ51: 407111.35 | CA51: 242722.66 | CB51: 374894.63 | CC51: 427805.83 | CD51: 369715.89 | CE51: 257280.89 | CF51: 238901.54 | CG51: 342229.76 | CH51: 479299.15 | CI51: 503579.2 | CJ51: 364126.98 | CK51: 272402.58 | CL51: 251376.92 | CM51: 224923.17 | CN51: 181948.75 | CO51: 175990.68 | CP51: 186127.74 | CQ51: 201038.74 | CR51: 452701.02 | CS51: 277263.11 | CT51: 179661.31 | CU51: 206132.61 | CV51: 211995.66 | CW51: 229506.97 | CX51: 202362.43 | CY51: 236770.45 | CZ51: 280620.02 | DA51: 320296.97 | DB51: 226077.73 | DC51: 221741.8 | DD51: 213109.79 | DE51: 264032.97
A52: 502SM | BW52: 7025.5424 | BX52: 137129.66 | BY52: 110458.06 | BZ52: 105132 | CA52: 109511.31 | CB52: 95339.548 | CC52: 121547.23 | CD52: 117683.69 | CE52: 119097.78 | CF52: 129141.48 | CG52: 122837.03 | CH52: 123347.53 | CI52: 131977.01 | CJ52: 141695.69 | CK52: 172558.98 | CL52: 158686.41 | CM52: 148649.49 | CN52: 170467.72 | CO52: 161308.07 | CP52: 169963.93 | CQ52: 169456.86 | CR52: 166596.4 | CS52: 177450.91 | CT52: 172954 | CU52: 192329.8 | CV52: 192163.71 | CW52: 190698.32 | CX52: 161399.98 | CY52: 193671.5 | CZ52: 185113.39 | DA52: 217107.57 | DB52: 191209.07 | DC52: 200537.42 | DD52: 199581.3 | DE52: 151877.31
A53: 502T9 | CA53: 2842.6223 | CB53: 72730.164 | CC53: 101464.07 | CD53: 84134.851 | CE53: 95752.143 | CF53: 95301.558 | CG53: 101127.22 | CH53: 106885.57 | CI53: 115695.66 | CJ53: 104634.27 | CK53: 106622.33 | CL53: 109323.32 | CM53: 98642.97 | CN53: 123189.85 | CO53: 113765.61 | CP53: 121405.18 | CQ53: 115996.33 | CR53: 122001.19 | CS53: 142015.7 | CT53: 128117.21 | CU53: 138721.7 | CV53: 134919.28 | CW53: 144119.81 | CX53: 138785.03 | CY53: 172841.48 | CZ53: 162784.09 | DA53: 192284.27 | DB53: 179323.1 | DC53: 172584.46 | DD53: 204592.1 | DE53: 123420.1
A54: 502TX | CJ54: 9092.5867 | CK54: 202804.07 | CL54: 187587.62 | CM54: 182107.44 | CN54: 195217.1 | CO54: 194305.58 | CP54: 212281.35 | CQ54: 204089.94 | CR54: 204231.63 | CS54: 195893.39 | CT54: 199434.59 | CU54: 204932.2 | CV54: 209111.74 | CW54: 200391.46 | CX54: 192406.62 | CY54: 209819.82 | CZ54: 195935.56 | DA54: 214655.3 | DB54: 205081.96 | DC54: 213888.53 | DD54: 207544.5 | DE54: 192419.67
A55: 502XT | CD55: 4531.362 | CE55: 140576.87 | CF55: 150407.35 | CG55: 181887.91 | CH55: 191193.62 | CI55: 179012.47 | CJ55: 183380.5 | CK55: 186935.47 | CL55: 157281.12 | CM55: 162526.89 | CN55: 180207.71 | CO55: 173905.8 | CP55: 191695.93 | CQ55: 171247.5 | CR55: 178445.2 | CS55: 199499.69 | CT55: 192184.12 | CU55: 195603.24 | CV55: 189344.78 | CW55: 188890.31 | CX55: 187420.21 | CY55: 212958.28 | CZ55: 208331.61 | DA55: 231062.13 | DB55: 206785.47 | DC55: 207127.11 | DD55: 219624.63 | DE55: 180446.94
A56: 502Z0 | CN56: 1927.5332 | CO56: 156382.26 | CP56: 183284.76 | CQ56: 203532.51 | CR56: 187476.12 | CS56: 243924.72 | CT56: 213370.52 | CU56: 233580.67 | CV56: 272813.11 | CW56: 299475.89 | CX56: 206268.13 | CY56: 222447.54 | CZ56: 252631.94 | DA56: 252341.66 | DB56: 247248.95 | DC56: 245251.88 | DD56: 260590.13 | DE56: 216620.49
A57: 5031E | CF57: 10081.81 | CG57: 159270.06 | CH57: 180523.37 | CI57: 175790.23 | CJ57: 176514.14 | CK57: 160021.13 | CL57: 175081.54 | CM57: 144680.76 | CN57: 182404.79 | CO57: 175636.27 | CP57: 178635.25 | CQ57: 171271.69 | CR57: 182594.24 | CS57: 193353.43 | CT57: 191952.14 | CU57: 198725.13 | CV57: 196715.04 | CW57: 217560.55 | CX57: 188800.02 | CY57: 190132.53 | CZ57: 180976.11 | DA57: 216364.35 | DB57: 207056.3 | DC57: 218891.75 | DD57: 225040.38 | DE57: 179922.92
A58: 50335 | CU58: 16589.998 | CV58: 114134.8 | CW58: 103879.77 | CX58: 123715.23 | CY58: 121559.87 | CZ58: 115005.05 | DA58: 124201.88 | DB58: 119542.22 | DC58: 125865.01 | DD58: 131762.61 | DE58: 109625.64
A59: 50337 | BQ59: 22188.497 | BR59: 105511.35 | BS59: 121044.19 | BT59: 130685.53 | BU59: 119594.11 | BV59: 115446.81 | BW59: 118563.21 | BX59: 121197.85 | BY59: 132570.67 | BZ59: 138179.8 | CA59: 146419.28 | CB59: 153201.98 | CC59: 181675.08 | CD59: 163572.15 | CE59: 174473.26 | CF59: 174971.58 | CG59: 177200.56 | CH59: 185247.98 | CI59: 176969.79 | CJ59: 175143.08 | CK59: 188225.61 | CL59: 182430.63 | CM59: 173409.5 | CN59: 201622.9 | CO59: 187345.37 | CP59: 213907.73 | CQ59: 202909.22 | CR59: 197944.55 | CS59: 206206.07 | CT59: 197103.23 | CU59: 197825.23 | CV59: 208326.56 | CW59: 196607.53 | CX59: 178448.18 | CY59: 194654.55 | CZ59: 202161.65 | DA59: 220024.62 | DB59: 207123.22 | DC59: 200334.47 | DD59: 213881.25 | DE59: 170108.72
A60: 5034C | BU60: 9752.79 | BV60: 127117.94 | BW60: 141744.34 | BX60: 174021.97 | BY60: 167368.02 | BZ60: 174106.63 | CA60: 174481.94 | CB60: 202657.28 | CC60: 204652.83 | CD60: 204068.16 | CE60: 207348.55 | CF60: 187567.06 | CG60: 221201.3 | CH60: 221522.36 | CI60: 223122.09 | CJ60: 230777.76 | CK60: 218166.75 | CL60: 203340.62 | CM60: 220112.96 | CN60: 232055.15 | CO60: 212628.25 | CP60: 224416.54 | CQ60: 209470.65 | CR60: 253495.11 | CS60: 222339.63 | CT60: 256624.7 | CU60: 250669.3 | CV60: 228096.83 | CW60: 224176.51 | CX60: 229481.84 | CY60: 262112.89 | CZ60: 245852.99 | DA60: 262454.39 | DB60: 246430.32 | DC60: 266275.98 | DD60: 234654.69 | DE60: 210399.09
A61: 5037C | BU61: 6346.9172 | BV61: 75028.234 | BW61: 82464.745 | BX61: 89656.394 | BY61: 102210.84 | BZ61: 103737.84 | CA61: 129833.38 | CB61: 122605.1 | CC61: 141803.49 | CD61: 118283.77 | CE61: 135170.95 | CF61: 121430.04 | CG61: 139654.74 | CH61: 147463.32 | CI61: 145786.02 | CJ61: 157592.82 | CK61: 169262.86 | CL61: 153750.63 | CM61: 137632.85 | CN61: 159635.21 | CO61: 152388.76 | CP61: 160125.34 | CQ61: 162339.71 | CR61: 162387.68 | CS61: 169071.83 | CT61: 159396.85 | CU61: 186828.01 | CV61: 157438.45 | CW61: 154119.25 | CX61: 136528.86 | CY61: 159975.01 | CZ61: 155672.42 | DA61: 178983.77 | DB61: 167272.24 | DC61: 167823.5 | DD61: 161353.67 | DE61: 139751.54
A62: 5037F | BR62: 14497.587 | BS62: 122242.31 | BT62: 126481.7 | BU62: 127651.45 | BV62: 141869.42 | BW62: 135107.61 | BX62: 147707.81 | BY62: 149595.06 | BZ62: 160696.38 | CA62: 181024.28 | CB62: 173806.74 | CC62: 202761.59 | CD62: 166473.62 | CE62: 175373.89 | CF62: 185833.11 | CG62: 193087.35 | CH62: 191439.67 | CI62: 192551.76 | CJ62: 195909.64 | CK62: 190121.44 | CL62: 192602.62 | CM62: 163989.18 | CN62: 188434.73 | CO62: 190144.37 | CP62: 201790.37 | CQ62: 203192.98 | CR62: 186399.15 | CS62: 205687.87 | CT62: 183180.73 | CU62: 180988.02 | CV62: 184762.79 | CW62: 224320.15 | CX62: 192174.3 | CY62: 221821.86 | CZ62: 212716.4 | DA62: 244095.45 | DB62: 232521.18 | DC62: 231564.73 | DD62: 235265.01 | DE62: 180766.26
A63: 503E4 | AD63: 77786.394 | AE63: 212955.28 | AF63: 226544.77 | AG63: 245419.81 | AH63: 253067.5 | AI63: 278629.37 | AJ63: 291858.58 | AK63: 253118.36 | AL63: 134892.07 | AM63: 164631.44 | AN63: 168868.46 | AO63: 139055.95 | AP63: 138203.88 | AQ63: 155293.33 | AR63: 185838.02 | AS63: 166474.61 | AT63: 163189.02 | AU63: 172209.73 | AV63: 185695.55 | AW63: 172680.62 | AX63: 153905.26 | AY63: 174628.47 | AZ63: 191848.22 | BA63: 206593.93 | BB63: 235404.22 | BC63: 259988.04 | BD63: 268741.04 | BE63: 247659.69 | BF63: 246008.5 | BG63: 320530.98 | BH63: 336634.69 | BI63: 359513.04 | BJ63: 368337.73 | BK63: 384857.27 | BL63: 370679.38 | BM63: 382990.2 | BN63: 362551.98 | BO63: 341000.72 | BP63: 361304.05 | BQ63: 344874.92 | BR63: 369179.13 | BS63: 362901.3 | BT63: 368094.28 | BU63: 358155.99 | BV63: 363461.35 | BW63: 353056.6 | BX63: 363156.52 | BY63: 320452.85 | BZ63: 307461.09 | CA63: 318856.64 | CB63: 333751.28 | CC63: 371396.86 | CD63: 340624.32 | CE63: 356404.66 | CF63: 343195.5 | CG63: 347921.96 | CH63: 345759.04 | CI63: 318244.54 | CJ63: 323589.92 | CK63: 324388.15 | CL63: 323785.82 | CM63: 295913.27 | CN63: 325376.05 | CO63: 333440.94 | CP63: 373783.38 | CQ63: 373085.31 | CR63: 342071.59 | CS63: 326122.94 | CT63: 229259.07 | CU63: 228754.13 | CV63: 223695.13 | CW63: 256486.83 | CX63: 245127.75 | CY63: 256787.87 | CZ63: 235078.29 | DA63: 270618.58 | DB63: 266456.75 | DC63: 269095.5 | DD63: 252560.44 | DE63: 278759.71
A64: 503EZ | BP64: 51726.107 | BQ64: 106930.55 | BR64: 124346.54 | BS64: 138046.4 | BT64: 144861.73 | BU64: 154070.64 | BV64: 163603.02 | BW64: 163495.08 | BX64: 180157.72 | BY64: 180803.41 | BZ64: 167267.01 | CA64: 187441.33 | CB64: 170969.32 | CC64: 204621.17 | CD64: 169711.04 | CE64: 174376.12 | CF64: 175140.47 | CG64: 171055.45 | CH64: 170815.01 | CI64: 173378.46 | CJ64: 189976.19 | CK64: 185562.59 | CL64: 184132.22 | CM64: 171168.44 | CN64: 193580.78 | CO64: 180893.29 | CP64: 184328.51 | CQ64: 185731.44 | CR64: 182429.92 | CS64: 202569.44 | CT64: 175401.3 | CU64: 197199.78 | CV64: 186879.39 | CW64: 188590.23 | CX64: 169477.81 | CY64: 199841.05 | CZ64: 198617.21 | DA64: 235453.53 | DB64: 211169.84 | DC64: 211430.05 | DD64: 223886.96 | DE64: 176369.18
A65: 503FT | BO65: 2179.338 | BP65: 60989.439 | BQ65: 62053.71 | BR65: 88921.434 | BS65: 88361.815 | BT65: 83303.327 | BU65: 88949.728 | BV65: 92174.059 | BW65: 90700.362 | BX65: 100204.49 | BY65: 108584.27 | BZ65: 106733.15 | CA65: 117102.01 | CB65: 111468.87 | CC65: 125620.32 | CD65: 119667.99 | CE65: 135786.01 | CF65: 149114.71 | CG65: 146609.77 | CH65: 143143.68 | CI65: 141817.55 | CJ65: 155397.14 | CK65: 157933.13 | CL65: 157552.46 | CM65: 151289.07 | CN65: 173229.22 | CO65: 168720 | CP65: 177928.01 | CQ65: 177812.74 | CR65: 167010.07 | CS65: 178588.72 | CT65: 173146.48 | CU65: 184717.73 | CV65: 189432.64 | CW65: 192350.81 | CX65: 179064.69 | CY65: 202033.7 | CZ65: 191200.64 | DA65: 218837.08 | DB65: 203316.96 | DC65: 209556.07 | DD65: 212938.11 | DE65: 142512.89
A66: 503FW | DC66: 3665.6238 | DD66: 92152.962 | DE66: 47909.293
A67: 503IG | BF67: 35112.709 | BG67: 201444.41 | BH67: 201715.69 | BI67: 219558.01 | BJ67: 221096.85 | BK67: 245050.47 | BL67: 237643.94 | BM67: 260019.95 | BN67: 256518.93 | BO67: 264661.75 | BP67: 199975.64 | BQ67: 200480.45 | BR67: 218247.34 | BS67: 218309.72 | BT67: 210728.93 | BU67: 185551.52 | BV67: 194690.44 | BW67: 175500.86 | BX67: 212117.74 | BY67: 164702.75 | BZ67: 149165.64 | CA67: 152523.82 | CB67: 139844.83 | CC67: 163222.49 | CD67: 144180.89 | CE67: 144999.7 | CF67: 186159.01 | CG67: 153695.89 | CH67: 154988.32 | CI67: 164981.44 | CJ67: 178422.07 | CK67: 188435.11 | CL67: 165358.33 | CM67: 163600.39 | CN67: 186867.21 | CO67: 175356.14 | CP67: 182681.63 | CQ67: 172510.83 | CR67: 168088.56 | CS67: 179525.53 | CT67: 176263.28 | CU67: 176492.3 | CV67: 183222.48 | CW67: 171445.64 | CX67: 163113.46 | CY67: 196819.21 | CZ67: 181451.73 | DA67: 223271.84 | DB67: 193895.17 | DC67: 187649.46 | DD67: 199671.56 | DE67: 186098.67
A68: 503K5 | W68: 105022.67 | X68: 156137.82 | Y68: 158766.43 | Z68: 176449.1 | AA68: 168562.77 | AB68: 182038.35 | AC68: 180996.67 | AD68: 193202.24 | AE68: 195638.55 | AF68: 204195.59 | AG68: 202197.07 | AH68: 198591.16 | AI68: 206640.68 | AJ68: 204617.78 | AK68: 185374.52 | AL68: 90763.588 | AM68: 129760.9 | AN68: 139596.16 | AO68: 144003.41 | AP68: 151670.45 | AQ68: 154676.63 | AR68: 201615.44 | AS68: 194818.14 | AT68: 175849.86 | AU68: 184707.77 | AV68: 215754.06 | AW68: 197333.92 | AX68: 220844.99 | AY68: 250299.76 | AZ68: 227739.22 | BA68: 259587.32 | BB68: 275131.25 | BC68: 307903.15 | BD68: 283052.29 | BE68: 315387.76 | BF68: 283857.87 | BG68: 344966.79 | BH68: 312244.76 | BI68: 327745.26 | BJ68: 323852.71 | BK68: 331375.63 | BL68: 322330.78 | BM68: 348252.67 | BN68: 353270.52 | BO68: 439179.03 | BP68: 276809.89 | BQ68: 318588.94 | BR68: 303869.59 | BS68: 354520.42 | BT68: 354901.64 | BU68: 311865.01 | BV68: 330440.61 | BW68: 327716.73 | BX68: 380054.01 | BY68: 432863.33 | BZ68: 461269.46 | CA68: 333379.25 | CB68: 290633.82 | CC68: 333589.93 | CD68: 232013.59 | CE68: 233117.62 | CF68: 217066.45 | CG68: 224597.86 | CH68: 221345.6 | CI68: 226842.27 | CJ68: 224412.54 | CK68: 217171.14 | CL68: 217944.89 | CM68: 209074.3 | CN68: 224444.82 | CO68: 212733.88 | CP68: 228683 | CQ68: 208754.41 | CR68: 229595.17 | CS68: 223157.74 | CT68: 233330.07 | CU68: 233054.15 | CV68: 224450.41 | CW68: 236622.7 | CX68: 225975.69 | CY68: 258544.95 | CZ68: 243354.58 | DA68: 277244.96 | DB68: 245846.53 | DC68: 254936.64 | DD68: 258496.3 | DE68: 247433.93
A69: 503KR | CB69: 57688.923 | CC69: 222086.59 | CD69: 188301.26 | CE69: 197422.55 | CF69: 221665.88 | CG69: 239291.92 | CH69: 263248.84 | CI69: 261755.87 | CJ69: 270166.09 | CK69: 271624.62 | CL69: 238505.93 | CM69: 222159.2 | CN69: 261045.18 | CO69: 256146.28 | CP69: 280969.46 | CQ69: 277750.13 | CR69: 276661.73 | CS69: 315884.67 | CT69: 293925.12 | CU69: 300530.99 | CV69: 318795.66 | CW69: 314344.18 | CX69: 266085.4 | CY69: 331668.02 | CZ69: 329352.49 | DA69: 381903.32 | DB69: 363531.64 | DC69: 356735.22 | DD69: 344745.2 | DE69: 273241.12
A70: 503L9 | BT70: 91665.593 | BU70: 138888.68 | BV70: 139179.38 | BW70: 158690.12 | BX70: 170282.19 | BY70: 174182.19 | BZ70: 188752.96 | CA70: 203180.25 | CB70: 189749.49 | CC70: 240750.69 | CD70: 212825.05 | CE70: 228846.25 | CF70: 244540.09 | CG70: 236121.1 | CH70: 263622.69 | CI70: 262056.6 | CJ70: 252230.74 | CK70: 245684.16 | CL70: 218386.78 | CM70: 200042.7 | CN70: 235595.51 | CO70: 221998.74 | CP70: 228797.81 | CQ70: 239333.21 | CR70: 236794.33 | CS70: 264180.4 | CT70: 258820.05 | CU70: 251496.4 | CV70: 267344.52 | CW70: 265906.6 | CX70: 238156.19 | CY70: 283708.84 | CZ70: 273489.77 | DA70: 359561.85 | DB70: 299585.2 | DC70: 290205.18 | DD70: 295782.08 | DE70: 231633.36
A71: 503P8 | CA71: 101034.25 | CB71: 109320.53 | CC71: 127720 | CD71: 121045.91 | CE71: 125676.34 | CF71: 142957.48 | CG71: 151017.39 | CH71: 156051.72 | CI71: 162065.03 | CJ71: 166218.6 | CK71: 175198 | CL71: 155777.06 | CM71: 147142.4 | CN71: 171563.77 | CO71: 160310.17 | CP71: 176735.26 | CQ71: 171818.18 | CR71: 172551.18 | CS71: 176378.36 | CT71: 169321.08 | CU71: 179934.09 | CV71: 181392.71 | CW71: 179138.03 | CX71: 169818.01 | CY71: 192370.62 | CZ71: 177406.63 | DA71: 218636.64 | DB71: 198615.02 | DC71: 210041.3 | DD71: 210258.06 | DE71: 165250.46
A72: 503QV | DB72: 64748.731 | DC72: 151909.74 | DD72: 173285.09 | DE72: 129981.19
A73: 503RV | BW73: 6879.2072 | BX73: 115595.55 | BY73: 121916.65 | BZ73: 111286.64 | CA73: 127538.87 | CB73: 128990.32 | CC73: 145472.48 | CD73: 133183.01 | CE73: 149477.68 | CF73: 142621.5 | CG73: 146616 | CH73: 152526.4 | CI73: 164294.06 | CJ73: 166775.68 | CK73: 154468.2 | CL73: 148345.15 | CM73: 159679.82 | CN73: 170261.68 | CO73: 160772.16 | CP73: 174882.9 | CQ73: 166682.63 | CR73: 160309.24 | CS73: 159438.31 | CT73: 168628.07 | CU73: 173777.16 | CV73: 167622.84 | CW73: 150349.84 | CX73: 159841.29 | CY73: 179493.07 | CZ73: 172563.91 | DA73: 183129.71 | DB73: 178371.84 | DC73: 183358.27 | DD73: 166563.88 | DE73: 151521
A74: 503T3 | CC74: 25207.4 | CD74: 157797.45 | CE74: 176863.59 | CF74: 175310.22 | CG74: 196504.6 | CH74: 210949.57 | CI74: 240501.66 | CJ74: 294355.47 | CK74: 223550.08 | CL74: 239885.87 | CM74: 232064.48 | CN74: 230011.66 | CO74: 217011.64 | CP74: 238589.44 | CQ74: 236291.07 | CR74: 260280.88 | CS74: 265410.72 | CT74: 237425.68 | CU74: 246271.2 | CV74: 220657.24 | CW74: 219456.03 | CX74: 220375.56 | CY74: 241108.4 | CZ74: 231604.32 | DA74: 252566.37 | DB74: 236055.54 | DC74: 253948.27 | DD74: 230032.64 | DE74: 221788.82
A75: 503Z7 | CC75: 9764.6309 | CD75: 82596.203 | CE75: 90982.938 | CF75: 105492.01 | CG75: 98492.558 | CH75: 100713.7 | CI75: 90738.592 | CJ75: 113490.26 | CK75: 113145.07 | CL75: 127896.73 | CM75: 112851.9 | CN75: 136407.94 | CO75: 126144.86 | CP75: 131038.98 | CQ75: 148655.36 | CR75: 133776.81 | CS75: 141583.18 | CT75: 125202.39 | CU75: 146973.73 | CV75: 137065.61 | CW75: 133784.9 | CX75: 112289.37 | CY75: 135924.52 | CZ75: 135524.43 | DA75: 183229.18 | DB75: 128032.81 | DC75: 132455.95 | DD75: 142838.67 | DE75: 120610.47
A76: 50417 | CJ76: 8929.2658 | CK76: 119479.55 | CL76: 119745.95 | CM76: 119296.97 | CN76: 137759.81 | CO76: 126450.54 | CP76: 136819.81 | CQ76: 137724.01 | CR76: 134740.72 | CS76: 143887.78 | CT76: 147055.26 | CU76: 162517.64 | CV76: 159522.38 | CW76: 155650.88 | CX76: 152020.54 | CY76: 172400.17 | CZ76: 166474.36 | DA76: 195097.55 | DB76: 169784.75 | DC76: 180565.41 | DD76: 179203.72 | DE76: 144053.67
A77: 5041V | BT77: 13631.111 | BU77: 92949.479 | BV77: 104963.45 | BW77: 112661.84 | BX77: 123310.73 | BY77: 130275.15 | BZ77: 123812.39 | CA77: 149390.32 | CB77: 142248.49 | CC77: 163913.7 | CD77: 141690.93 | CE77: 152918.12 | CF77: 161313.46 | CG77: 160348.11 | CH77: 164603.31 | CI77: 159924.78 | CJ77: 178437.52 | CK77: 177934.5 | CL77: 171459.79 | CM77: 150591.96 | CN77: 177600.54 | CO77: 170904.07 | CP77: 182628.86 | CQ77: 181074.21 | CR77: 169124.64 | CS77: 168039.81 | CT77: 155756.26 | CU77: 167352.87 | CV77: 169205.61 | CW77: 187990.92 | CX77: 178178.13 | CY77: 201093.7 | CZ77: 192558.42 | DA77: 213339.25 | DB77: 204964.84 | DC77: 208308.11 | DD77: 208607.39 | DE77: 159813.7
A78: 50469 | BS78: 24808.091 | BT78: 111318.17 | BU78: 116489.63 | BV78: 121273.63 | BW78: 123016.35 | BX78: 131868.11 | BY78: 132479.85 | BZ78: 130761.28 | CA78: 122149.63 | CB78: 110702.08 | CC78: 133421.02 | CD78: 119238.57 | CE78: 132236.11 | CF78: 141539.14 | CG78: 149941.5 | CH78: 148084.19 | CI78: 162185.5 | CJ78: 166507.21 | CK78: 162425.23 | CL78: 149174.65 | CM78: 139387.61 | CN78: 168055.7 | CO78: 155857.46 | CP78: 155372.02 | CQ78: 143504.46 | CR78: 147064.27 | CS78: 153621.12 | CT78: 148363.85 | CU78: 146958.71 | CV78: 137564.04 | CW78: 139444.41 | CX78: 125567.77 | CY78: 145206.96 | CZ78: 153113.86 | DA78: 168598.1 | DB78: 154309.07 | DC78: 157118.94 | DD78: 161213.48 | DE78: 139208.99
A79: 5047E | CQ79: 16588.968 | CR79: 129287.23 | CS79: 133608.09 | CT79: 133028.76 | CU79: 140641.46 | CV79: 143473.33 | CW79: 187495.09 | CX79: 130055.85 | CY79: 163973.26 | CZ79: 166594.25 | DA79: 183427.37 | DB79: 169991.55 | DC79: 177251.1 | DD79: 143667.89 | DE79: 144220.3
A80: 50487 | CM80: 68017.816 | CN80: 115511.85 | CO80: 119908.19 | CP80: 143614.49 | CQ80: 137726.71 | CR80: 144794.77 | CS80: 149653.76 | CT80: 156871.52 | CU80: 163340.72 | CV80: 153929.01 | CW80: 164376.74 | CX80: 163473.2 | CY80: 178387.07 | CZ80: 181085.7 | DA80: 206163.38 | DB80: 198513.69 | DC80: 222145.27 | DD80: 198934.53 | DE80: 159247.13
A81: 504B3 | BY81: 17948.816 | BZ81: 93003.759 | CA81: 112907.72 | CB81: 120591.32 | CC81: 152305.47 | CD81: 141390.07 | CE81: 150257.74 | CF81: 160903.5 | CG81: 171572.13 | CH81: 184328.84 | CI81: 174476.8 | CJ81: 159368.66 | CK81: 157934 | CL81: 130531.61 | CM81: 139282.51 | CN81: 161291.11 | CO81: 149692.59 | CP81: 150044.65 | CQ81: 153574.89 | CR81: 146044.67 | CS81: 161046.33 | CT81: 164781.88 | CU81: 175765.32 | CV81: 171422.17 | CW81: 163643.83 | CX81: 147445.5 | CY81: 164267.42 | CZ81: 162623.04 | DA81: 197164.27 | DB81: 167413.53 | DC81: 170282.31 | DD81: 182438.56 | DE81: 151742.03
A82: 504EU | X82: 195368.59 | Y82: 216023.63 | Z82: 249254.31 | AA82: 229489.18 | AB82: 269651.42 | AC82: 254102.32 | AD82: 275023.34 | AE82: 277718.29 | AF82: 309131.14 | AG82: 300028.79 | AH82: 288411.56 | AI82: 288409.05 | AJ82: 298321.25 | AK82: 265032.65 | AL82: 176817.81 | AM82: 214347.11 | AN82: 223450.22 | AO82: 230134.74 | AP82: 213623.72 | AQ82: 224342.41 | AR82: 252123.68 | AS82: 235920.88 | AT82: 200590.56 | AU82: 233627.47 | AV82: 275603.18 | AW82: 228187.49 | AX82: 253318.42 | AY82: 262954.57 | AZ82: 282379.71 | BA82: 296680.44 | BB82: 308169.89 | BC82: 326973.88 | BD82: 315269.65 | BE82: 298746.54 | BF82: 309505.54 | BG82: 373136.83 | BH82: 350251.36 | BI82: 396105.49 | BJ82: 362232.16 | BK82: 380309.36 | BL82: 393811.74 | BM82: 433619.86 | BN82: 399210.69 | BO82: 384613.51 | BP82: 353267.4 | BQ82: 355355.12 | BR82: 390213.42 | BS82: 356598.05 | BT82: 371906.09 | BU82: 345902.86 | BV82: 345955.5 | BW82: 333813.76 | BX82: 374127.31 | BY82: 349544.41 | BZ82: 347758.01 | CA82: 343003.18 | CB82: 353296.98 | CC82: 364795.21 | CD82: 367099.33 | CE82: 373682.48 | CF82: 351088.93 | CG82: 372517.39 | CH82: 362008.49 | CI82: 368644.24 | CJ82: 377904.07 | CK82: 366920 | CL82: 383282.22 | CM82: 382946.03 | CN82: 419629.51 | CO82: 403397.26 | CP82: 435822.93 | CQ82: 398394.42 | CR82: 411585.05 | CS82: 399830.31 | CT82: 429408.31 | CU82: 418280.18 | CV82: 397240.2 | CW82: 378104.35 | CX82: 376497.88 | CY82: 419726.38 | CZ82: 406266.52 | DA82: 471863.29 | DB82: 404117.47 | DC82: 422632.66 | DD82: 393626.4 | DE82: 332118.57
A83: 504F9 | B83: 65624.093 | C83: 52719.645 | D83: 59673.878 | E83: 72976.274 | F83: 75929.358 | G83: 76176.564 | H83: 81412.43 | I83: 76923.198 | J83: 82202.636 | K83: 91602.426 | L83: 90532.681 | M83: 101049.9 | N83: 89755.92 | O83: 120842.26 | P83: 108576.98 | Q83: 112126.08 | R83: 133809.46 | S83: 144651.68 | T83: 143195.33 | U83: 147816.57 | V83: 147472.85 | W83: 158366.87 | X83: 185453.39 | Y83: 146966.78 | Z83: 166621.31 | AA83: 162921.35 | AB83: 168356.64 | AC83: 184073.9 | AD83: 178772.32 | AE83: 171010.58 | AF83: 199033.52 | AG83: 196733.51 | AH83: 198950 | AI83: 218759.27 | AJ83: 193382.75 | AK83: 174997.58 | AL83: 113891.31 | AM83: 185763.47 | AN83: 160379.77 | AO83: 151229.87 | AP83: 177809.85 | AQ83: 142550.5 | AR83: 152522.21 | AS83: 164697.81 | AT83: 152860.3 | AU83: 161545.7 | AV83: 178295.32 | AW83: 169732.91 | AX83: 229951.7 | AY83: 225506.96 | AZ83: 204100.61 | BA83: 223797.15 | BB83: 228333.92 | BC83: 317523.37 | BD83: 271781.06 | BE83: 253788.35 | BF83: 236742.3 | BG83: 251044.35 | BH83: 295573.25 | BI83: 269973.3 | BJ83: 282219.74 | BK83: 309354.63 | BL83: 304826.04 | BM83: 322815.99 | BN83: 331518.66 | BO83: 365873.22 | BP83: 244405.29 | BQ83: 252845.88 | BR83: 254405.48 | BS83: 284779.31 | BT83: 259091.3 | BU83: 317644.92 | BV83: 304214.11 | BW83: 274623.65 | BX83: 317293.31 | BY83: 303386.22 | BZ83: 344498.07 | CA83: 476905.58 | CB83: 339124.45 | CC83: 396818.39 | CD83: 254112.13 | CE83: 214654.81 | CF83: 234478.37 | CG83: 223532.14 | CH83: 228370.86 | CI83: 227802.77 | CJ83: 230224.35 | CK83: 229164.23 | CL83: 226286.51 | CM83: 204799.29 | CN83: 241679.57 | CO83: 235377.32 | CP83: 242812.51 | CQ83: 255124.74 | CR83: 234046.1 | CS83: 255924.88 | CT83: 237070.78 | CU83: 247054.11 | CV83: 271611.21 | CW83: 271038.16 | CX83: 237605.23 | CY83: 288783.71 | CZ83: 285582.61 | DA83: 340950.71 | DB83: 286680.89 | DC83: 290640.59 | DD83: 285023.45 | DE83: 212765.81
A84: 504I1 | BT84: 4250.6841 | BU84: 91152.533 | BV84: 100608.62 | BW84: 100749.92 | BX84: 109539.41 | BY84: 108167.95 | BZ84: 105275.09 | CA84: 123690.87 | CB84: 107468.59 | CC84: 126313.71 | CD84: 110576 | CE84: 118599 | CF84: 136035.91 | CG84: 142853.72 | CH84: 142210.14 | CI84: 149723.64 | CJ84: 142695.78 | CK84: 151806.13 | CL84: 162174.57 | CM84: 133119.22 | CN84: 167104.04 | CO84: 150790 | CP84: 155419.52 | CQ84: 163570.96 | CR84: 160507.08 | CS84: 170699.66 | CT84: 159815.72 | CU84: 163816.24 | CV84: 170293.38 | CW84: 182430.78 | CX84: 151008.22 | CY84: 173603.83 | CZ84: 172187.98 | DA84: 197309.86 | DB84: 192649.51 | DC84: 199984.39 | DD84: 63442.469 | DE84: 139503.92
A85: 504KL | CA85: 83565.186 | CB85: 85930.214 | CC85: 111064.6 | CD85: 110587.92 | CE85: 119942.89 | CF85: 120229.23 | CG85: 125107.69 | CH85: 133134.62 | CI85: 137037.09 | CJ85: 136678.08 | CK85: 136621.35 | CL85: 134087.52 | CM85: 125409.01 | CN85: 142710.07 | CO85: 142979.54 | CP85: 145210.7 | CQ85: 152185.68 | CR85: 155381.22 | CS85: 154099.65 | CT85: 146783.89 | CU85: 152549.7 | CV85: 158648.7 | CW85: 167717.07 | CX85: 151385.79 | CY85: 171752.16 | CZ85: 170043.07 | DA85: 185001.71 | DB85: 173569.19 | DC85: 183251.89 | DD85: 174364.25 | DE85: 142900.99
A86: 504KO | BJ86: 71445.611 | BK86: 110972.99 | BL86: 128312.44 | BM86: 146986.35 | BN86: 155364.63 | BO86: 145769.85 | BP86: 154153.1 | BQ86: 149071.66 | BR86: 173519.12 | BS86: 173257.38 | BT86: 170679.61 | BU86: 159896.86 | BV86: 157825.51 | BW86: 155135.75 | BX86: 155889.15 | BY86: 140818.05 | BZ86: 147767.39 | CA86: 154220.24 | CB86: 150366.62 | CC86: 175333.78 | CD86: 163027.78 | CE86: 171358.5 | CF86: 180337.26 | CG86: 174293.05 | CH86: 180534.19 | CI86: 158166.32 | CJ86: 152835.73 | CK86: 157550.81 | CL86: 161629.11 | CM86: 154605.68 | CN86: 179785.75 | CO86: 172930.37 | CP86: 193832.94 | CQ86: 193418.65 | CR86: 183989.73 | CS86: 191554.35 | CT86: 187717.13 | CU86: 192399.91 | CV86: 191493.83 | CW86: 197202.4 | CX86: 182296.3 | CY86: 207225.14 | CZ86: 202131.96 | DA86: 233844.38 | DB86: 226752.82 | DC86: 232331.17 | DD86: 225865.16 | DE86: 170763.76
A87: 504TF | CW87: 25738.308 | CX87: 64577.796 | CY87: 78428.897 | CZ87: 87073.491 | DA87: 97707.895 | DB87: 89588.682 | DC87: 93896.337 | DD87: 98500.244 | DE87: 79438.956
A88: 504TM | DA88: 12045.891 | DB88: 118516.76 | DC88: 148858.06 | DD88: 147721.75 | DE88: 106785.61
A89: 504WD | CE89: 12771.145 | CF89: 105960.32 | CG89: 116936.5 | CH89: 123371.26 | CI89: 119826.8 | CJ89: 116759.02 | CK89: 124998.2 | CL89: 140361.87 | CM89: 112174.05 | CN89: 138115.63 | CO89: 128993.13 | CP89: 134703.72 | CQ89: 144567.16 | CR89: 141337.8 | CS89: 156947.29 | CT89: 142052.1 | CU89: 149770.28 | CV89: 152277.95 | CW89: 170698.82 | CX89: 137081.12 | CY89: 162208.41 | CZ89: 158975.14 | DA89: 174204.57 | DB89: 164236.91 | DC89: 171572.8 | DD89: 166566.91 | DE89: 137210.34
A90: 504XP | CX90: 24528.115 | CY90: 226470.98 | CZ90: 251322.53 | DA90: 300736.62 | DB90: 274716.69 | DC90: 299753.86 | DD90: 330733.16 | DE90: 244037.42
A91: 504XY | BP91: 104083.96 | BQ91: 119003.85 | BR91: 146490.47 | BS91: 133500.28 | BT91: 146455.24 | BU91: 154298.85 | BV91: 148697.86 | BW91: 141935.52 | BX91: 161712.91 | BY91: 154883.34 | BZ91: 156218.64 | CA91: 155042.99 | CB91: 182654.62 | CC91: 173948.3 | CD91: 158215.28 | CE91: 166477.07 | CF91: 161735.41 | CG91: 167821.42 | CH91: 177269.74 | CI91: 171156.29 | CJ91: 190124.84 | CK91: 174799.25 | CL91: 166740.11 | CM91: 162076.34 | CN91: 169858.47 | CO91: 167085.97 | CP91: 169656.12 | CQ91: 163500.44 | CR91: 179313.21 | CS91: 186424.6 | CT91: 189894.93 | CU91: 196541.19 | CV91: 181993.99 | CW91: 173968.23 | CX91: 180128.37 | CY91: 197638.14 | CZ91: 186147.53 | DA91: 207204.62 | DB91: 180610.81 | DC91: 191450.97 | DD91: 178455.64 | DE91: 167688.19
A92: 5053N | BG92: 41305.532 | BH92: 174279.5 | BI92: 179660.01 | BJ92: 169317.38 | BK92: 212874.51 | BL92: 205126.92 | BM92: 210786.11 | BN92: 223195.92 | BO92: 201191.99 | BP92: 188813.44 | BQ92: 198205.09 | BR92: 215184.1 | BS92: 228430.34 | BT92: 218030.9 | BU92: 215233.06 | BV92: 221176 | BW92: 206964.34 | BX92: 218052.95 | BY92: 200965.9 | BZ92: 208594.37 | CA92: 205479.89 | CB92: 195051.98 | CC92: 236019.35 | CD92: 200862.35 | CE92: 205908.5 | CF92: 204163.49 | CG92: 217864.12 | CH92: 216817.22 | CI92: 211914.75 | CJ92: 211311.88 | CK92: 199725.55 | CL92: 187633.16 | CM92: 177173.14 | CN92: 202232.57 | CO92: 191168.98 | CP92: 206911.29 | CQ92: 209881.12 | CR92: 217260.35 | CS92: 227290.77 | CT92: 213950.04 | CU92: 203338.76 | CV92: 213743.85 | CW92: 210073.44 | CX92: 188499.93 | CY92: 223942.78 | CZ92: 225435.44 | DA92: 243264.72 | DB92: 226534.75 | DC92: 226892.58 | DD92: 224571.66 | DE92: 205246.14
A93: 50554 | B93: 112587.42 | C93: 119688.96 | D93: 140551.54 | E93: 136896.21 | F93: 143302.18 | G93: 138979.04 | H93: 149861.06 | I93: 148794.22 | J93: 157808.09 | K93: 150194.2 | L93: 166946.96 | M93: 138872.08 | N93: 137819.54 | O93: 143941.5 | P93: 138373.88 | Q93: 148593.85 | R93: 135677.17 | S93: 139724.27 | T93: 145148.6 | U93: 162153.68 | V93: 155272.12 | W93: 146730.45 | X93: 149371.68 | Y93: 160214.31 | Z93: 170770.74 | AA93: 164315.94 | AB93: 184377.12 | AC93: 178342.72 | AD93: 196000.53 | AE93: 207948.23 | AF93: 213787.23 | AG93: 205420.12 | AH93: 199680.66 | AI93: 186315.49 | AJ93: 204928.46 | AK93: 150344.95 | AL93: 64206.774 | AM93: 81754.405 | AN93: 87578.264 | AO93: 80240.532 | AP93: 97551.884 | AQ93: 110663.5 | AR93: 134709.76 | AS93: 136717.59 | AT93: 106656.05 | AU93: 134087.46 | AV93: 156160.83 | AW93: 128007.62 | AX93: 141280 | AY93: 172882.69 | AZ93: 190641.14 | BA93: 201996.5 | BB93: 226635.89 | BC93: 247266.3 | BD93: 237605.84 | BE93: 226721.78 | BF93: 262401.99 | BG93: 322583.27 | BH93: 288909.01 | BI93: 320485.4 | BJ93: 302946.44 | BK93: 329463.07 | BL93: 336051.79 | BM93: 368406.79 | BN93: 341289.57 | BO93: 336651.05 | BP93: 304109.28 | BQ93: 319052.29 | BR93: 364267.08 | BS93: 316839.21 | BT93: 341975.98 | BU93: 324225.47 | BV93: 306873.04 | BW93: 314185.66 | BX93: 346304.48 | BY93: 306085.65 | BZ93: 308157.33 | CA93: 270211.29 | CB93: 288442.75 | CC93: 295763.2 | CD93: 169849.6 | CE93: 289918.98 | CF93: 281898.84 | CG93: 332904.5 | CH93: 320555.9 | CI93: 330182.43 | CJ93: 340739.63 | CK93: 313977.36 | CL93: 262906.85 | CM93: 258462.84 | CN93: 275299.67 | CO93: 275368.8 | CP93: 312527.09 | CQ93: 280864.28 | CR93: 308855.22 | CS93: 305703.88 | CT93: 333939.73 | CU93: 329335.22 | CV93: 311106.01 | CW93: 289259.16 | CX93: 292503.8 | CY93: 321204.78 | CZ93: 293526.79 | DA93: 332331.6 | DB93: 307107.75 | DC93: 332834.12 | DD93: 301491.02 | DE93: 228162.96
A94: 5057U | AO94: 11875.792 | AP94: 64834.222 | AQ94: 84462.772 | AR94: 102910.35 | AS94: 107366.9 | AT94: 94985.913 | AU94: 106185.35 | AV94: 126759.61 | AW94: 115202.57 | AX94: 137120.2 | AY94: 158740.83 | AZ94: 144536.34 | BA94: 158996.82 | BB94: 159183.3 | BC94: 216231.92 | BD94: 212546.03 | BE94: 190936.34 | BF94: 176091.28 | BG94: 200446.18 | BH94: 216906.28 | BI94: 212475.16 | BJ94: 213986.92 | BK94: 257644.5 | BL94: 245228.92 | BM94: 295406.04 | BN94: 314578.61 | BO94: 342726.78 | BP94: 238825.59 | BQ94: 225078.33 | BR94: 245905.13 | BS94: 272076.64 | BT94: 250739.18 | BU94: 259716.82 | BV94: 256580.49 | BW94: 238156.04 | BX94: 260146.93 | BY94: 257514.9 | BZ94: 225544.4 | CA94: 265968.45 | CB94: 222704.86 | CC94: 272828.27 | CD94: 213279.12 | CE94: 230357.49 | CF94: 256305 | CG94: 248440.04 | CH94: 242425.28 | CI94: 241722.67 | CJ94: 267619.28 | CK94: 295032.47 | CL94: 245390.27 | CM94: 211398.55 | CN94: 246534.19 | CO94: 237855.06 | CP94: 247648.4 | CQ94: 263744.32 | CR94: 229434.84 | CS94: 251037.84 | CT94: 229868.92 | CU94: 262092.55 | CV94: 275066.49 | CW94: 258934.73 | CX94: 222064.02 | CY94: 262344.49 | CZ94: 260520.07 | DA94: 320557.09 | DB94: 277608.39 | DC94: 267702.57 | DD94: 272566.29 | DE94: 220554.45
A95: 505A9 | AI95: 54002.232 | AJ95: 138142.69 | AK95: 137944.4 | AL95: 76822.382 | AM95: 107271.07 | AN95: 129357.47 | AO95: 129901.83 | AP95: 137044.44 | AQ95: 137509.84 | AR95: 158447.25 | AS95: 136969.98 | AT95: 115281.14 | AU95: 131428.13 | AV95: 158223.32 | AW95: 132124.96 | AX95: 139827.88 | AY95: 160756.77 | AZ95: 175588.96 | BA95: 182671.4 | BB95: 200445.52 | BC95: 219645.5 | BD95: 207029.1 | BE95: 198273 | BF95: 211449.5 | BG95: 240895.84 | BH95: 227481.09 | BI95: 249368.01 | BJ95: 233000.36 | BK95: 247729.62 | BL95: 257758.41 | BM95: 290954.27 | BN95: 288455.79 | BO95: 280827.87 | BP95: 244837.58 | BQ95: 248997.75 | BR95: 281138.84 | BS95: 248817.68 | BT95: 270914.61 | BU95: 249836.96 | BV95: 250952.15 | BW95: 251886.77 | BX95: 289757.74 | BY95: 261000.13 | BZ95: 255830.16 | CA95: 241774.25 | CB95: 258849.99 | CC95: 287379.39 | CD95: 274162.65 | CE95: 288090.14 | CF95: 274236.64 | CG95: 281252.4 | CH95: 286679.69 | CI95: 294123.89 | CJ95: 304464 | CK95: 267367.8 | CL95: 277578.06 | CM95: 269876.86 | CN95: 302433.86 | CO95: 277953.83 | CP95: 290894.35 | CQ95: 267476.7 | CR95: 283694.05 | CS95: 272587.99 | CT95: 285929.03 | CU95: 287072.07 | CV95: 272417.81 | CW95: 248801.64 | CX95: 249189.05 | CY95: 283649.52 | CZ95: 270641.08 | DA95: 317347.19 | DB95: 293255.64 | DC95: 291549.83 | DD95: 276415.76 | DE95: 231401.97
A96: 505BM | BZ96: 4018.0693 | CA96: 122410.99 | CB96: 99809.619 | CC96: 93479.496 | CD96: 110518.88 | CE96: 124623.5 | CF96: 141726.95 | CG96: 135265.59 | CH96: 142002.8 | CI96: 155640.35 | CJ96: 155558.19 | CK96: 152457.12 | CL96: 151970.96 | CM96: 137897.47 | CN96: 162868.68 | CO96: 153971.14 | CP96: 165490.93 | CQ96: 176497.45 | CR96: 165335.11 | CS96: 178003.84 | CT96: 172624.48 | CU96: 192829.4 | CV96: 191322.94 | CW96: 190845.5 | CX96: 167811.44 | CY96: 200540.86 | CZ96: 189921.79 | DA96: 226500.28 | DB96: 201173.46 | DC96: 204819.64 | DD96: 215762.42 | DE96: 157538.69
A97: 505CX | BW97: 7117.9454 | BX97: 176883.74 | BY97: 198296.38 | BZ97: 170679.55 | CA97: 159421.66 | CB97: 167417.99 | CC97: 194797.78 | CD97: 171661.6 | CE97: 177834.69 | CF97: 176431.71 | CG97: 177943.69 | CH97: 188316.2 | CI97: 183802.24 | CJ97: 191282.32 | CK97: 181428.72 | CL97: 165249.61 | CM97: 140474.49 | CN97: 167976.81 | CO97: 144698.75 | CP97: 152848.79 | CQ97: 148614.71 | CR97: 163347.74 | CS97: 180003.16 | CT97: 178332.78 | CU97: 184006.42 | CV97: 192761.45 | CW97: 186350.07 | CX97: 170596.12 | CY97: 199854.96 | CZ97: 195412.38 | DA97: 219494.98 | DB97: 188753.99 | DC97: 194454.28 | DD97: 196282.17 | DE97: 173318.53
A98: 505DL | AC98: 38060.03 | AD98: 85188.238 | AE98: 110918.3 | AF98: 118213.32 | AG98: 124596.67 | AH98: 115155.49 | AI98: 131425.51 | AJ98: 133136.58 | AK98: 123030.77 | AL98: 47345.113 | AM98: 93779.625 | AN98: 115218.55 | AO98: 131448.86 | AP98: 135365.76 | AQ98: 125630.15 | AR98: 137122.71 | AS98: 141529.52 | AT98: 119166.86 | AU98: 119476.5 | AV98: 140967.6 | AW98: 129807.28 | AX98: 153135.95 | AY98: 194308.88 | AZ98: 145956.68 | BA98: 170907.59 | BB98: 193806.44 | BC98: 228108.35 | BD98: 205374.8 | BE98: 215611.96 | BF98: 185433.79 | BG98: 206581.82 | BH98: 202978.54 | BI98: 208098.72 | BJ98: 196620.83 | BK98: 220323.14 | BL98: 210489.67 | BM98: 262314.96 | BN98: 242021.76 | BO98: 288485.11 | BP98: 174468.85 | BQ98: 182202.58 | BR98: 184101.98 | BS98: 173528.09 | BT98: 172057.41 | BU98: 174910.52 | BV98: 169661.47 | BW98: 156067.31 | BX98: 172929.16 | BY98: 164165.26 | BZ98: 153822.78 | CA98: 143234.22 | CB98: 138815.69 | CC98: 165059.23 | CD98: 143935.64 | CE98: 148572.78 | CF98: 154102.64 | CG98: 147442.74 | CH98: 149772.43 | CI98: 156268.57 | CJ98: 152461.76 | CK98: 155405.87 | CL98: 144760.97 | CM98: 135642 | CN98: 152762.73 | CO98: 144990.36 | CP98: 149484.99 | CQ98: 141231.86 | CR98: 140107.08 | CS98: 153108.72 | CT98: 150218.62 | CU98: 151531.36 | CV98: 147332.15 | CW98: 148568.33 | CX98: 136848.79 | CY98: 162221.11 | CZ98: 150970.96 | DA98: 175007.74 | DB98: 148467.05 | DC98: 151355.39 | DD98: 155994.16 | DE98: 156509.17
A99: 505J9 | CA99: 139692.88 | CB99: 123765.22 | CC99: 160653.64 | CD99: 126214.15 | CE99: 141803.83 | CF99: 158801.28 | CG99: 164561.98 | CH99: 194814.68 | CI99: 195478.24 | CJ99: 198044.8 | CK99: 233006.54 | CL99: 250172.89 | CM99: 206820.07 | CN99: 248642.07 | CO99: 240128.9 | CP99: 253561.48 | CQ99: 276630.52 | CR99: 250441.97 | CS99: 292733.13 | CT99: 262896.69 | CU99: 280020.71 | CV99: 276863.81 | CW99: 325126.07 | CX99: 253693.65 | CY99: 301033.4 | CZ99: 300303.59 | DA99: 364135.47 | DB99: 320755.46 | DC99: 331664.44 | DD99: 290680.11 | DE99: 238771.39
A100: 505L1 | CE100: 5808.1478 | CF100: 85959.365 | CG100: 104843.33 | CH100: 118554.56 | CI100: 120431.72 | CJ100: 126659.2 | CK100: 122317.45 | CL100: 129323.2 | CM100: 126841.14 | CN100: 142685.17 | CO100: 134350.31 | CP100: 144385.84 | CQ100: 151279.35 | CR100: 148920.32 | CS100: 150448.73 | CT100: 146813.07 | CU100: 146801.37 | CV100: 158823.32 | CW100: 158429.21 | CX100: 139771.22 | CY100: 163035.6 | CZ100: 158946.68 | DA100: 173056.15 | DB100: 148097.98 | DC100: 153380.71 | DD100: 172580.68 | DE100: 135867.07
A101: 505LP | BZ101: 5723.4531 | CA101: 133745.73 | CB101: 116989.55 | CC101: 131807.84 | CD101: 108989.01 | CE101: 122692.76 | CF101: 132139.7 | CG101: 139407.15 | CH101: 141412.2 | CI101: 142066.62 | CJ101: 143478.54 | CK101: 145769.74 | CL101: 148309.4 | CM101: 117620.84 | CN101: 142467.25 | CO101: 135997.27 | CP101: 143061.53 | CQ101: 143484.93 | CR101: 145380.55 | CS101: 155053.73 | CT101: 139249.84 | CU101: 143559.32 | CV101: 142564.85 | CW101: 165654.37 | CX101: 144287.47 | CY101: 172654.09 | CZ101: 143021.18 | DA101: 162379.69 | DB101: 152251.59 | DC101: 158395.66 | DD101: 197348 | DE101: 139256.9
A102: 505LR | BX102: 18922.976 | BY102: 110227.1 | BZ102: 148163.44 | CA102: 146621.76 | CB102: 168837.96 | CC102: 179304.23 | CD102: 174272.4 | CE102: 183373.54 | CF102: 177770.56 | CG102: 186622.56 | CH102: 205384.39 | CI102: 186295.11 | CJ102: 160729.89 | CK102: 179886.04 | CL102: 178272.31 | CM102: 177371.57 | CN102: 186936.51 | CO102: 177804.32 | CP102: 208552.6 | CQ102: 201581.23 | CR102: 214391.6 | CS102: 229157.26 | CT102: 206242.87 | CU102: 230187.31 | CV102: 227474.75 | CW102: 242900.81 | CX102: 227694.74 | CY102: 255210.77 | CZ102: 242580.67 | DA102: 277174.21 | DB102: 272832.27 | DC102: 269699.75 | DD102: 263348.8 | DE102: 197449.28
...

Sheet HISTORICO CON
A2: Tienda 2026 | B2: (Varios elementos)
A3: Mes | B3: (Varios elementos)
A5: $ Contribución Directa Prom. Tienda | B5: Etiquetas de columna
A6: Etiquetas de fila | B6: ene 17 | C6: feb 17 | D6: mar 17 | E6: abr 17 | F6: may 17 | G6: jun 17 | H6: jul 17 | I6: ago 17 | J6: sep 17 | K6: oct 17 | L6: nov 17 | M6: ene 18 | N6: feb 18 | O6: mar 18 | P6: abr 18 | Q6: may 18 | R6: jun 18 | S6: jul 18 | T6: ago 18 | U6: sep 18 | V6: oct 18 | W6: nov 18 | X6: ene 19 | Y6: feb 19 | Z6: mar 19 | AA6: abr 19 | AB6: may 19 | AC6: jun 19 | AD6: jul 19 | AE6: ago 19 | AF6: sep 19 | AG6: oct 19 | AH6: nov 19 | AI6: ene 20 | AJ6: feb 20 | AK6: mar 20 | AL6: abr 20 | AM6: may 20 | AN6: jun 20 | AO6: jul 20 | AP6: ago 20 | AQ6: sep 20 | AR6: oct 20 | AS6: nov 20 | AT6: ene 21 | AU6: feb 21 | AV6: mar 21 | AW6: abr 21 | AX6: may 21 | AY6: jun 21 | AZ6: jul 21 | BA6: ago 21 | BB6: sep 21 | BC6: oct 21 | BD6: nov 21 | BE6: ene 22 | BF6: feb 22 | BG6: mar 22 | BH6: abr 22 | BI6: may 22 | BJ6: jun 22 | BK6: jul 22 | BL6: ago 22 | BM6: sep 22 | BN6: oct 22 | BO6: nov 22 | BP6: ene 23 | BQ6: feb 23 | BR6: mar 23 | BS6: abr 23 | BT6: may 23 | BU6: jun 23 | BV6: jul 23 | BW6: ago 23 | BX6: sep 23 | BY6: oct 23 | BZ6: nov 23 | CA6: ene 24 | CB6: feb 24 | CC6: mar 24 | CD6: abr 24 | CE6: may 24 | CF6: jun 24 | CG6: jul 24 | CH6: ago 24 | CI6: sep 24 | CJ6: oct 24 | CK6: nov 24 | CL6: ene 25 | CM6: feb 25 | CN6: mar 25 | CO6: abr 25 | CP6: may 25 | CQ6: jun 25 | CR6: jul 25 | CS6: ago 25 | CT6: sep 25 | CU6: oct 25 | CV6: nov 25 | CW6: ene 26 | CX6: feb 26 | CY6: mar 26 | CZ6: abr 26 | DA6: may 26 | DB6: jun 26 | DC6: jul 26 | DD6: ago 26 | DE6: Total general
A7: 5002I | CK7: -9595.4431 | CL7: -324.53062 | CM7: -4048.7752 | CN7: 12195.985 | CO7: 5883.1668 | CP7: 4230.7664 | CQ7: 19931.799 | CR7: 4894.8755 | CS7: 8471.7974 | CT7: 12670.327 | CU7: 11151.208 | CV7: 17401.957 | CW7: 1548.9682 | CX7: 6127.2314 | CY7: 19765.133 | CZ7: 17463.584 | DA7: 15183.438 | DB7: 14149.99 | DC7: 16239.108 | DD7: 14453.236 | DE7: 9389.6911
A8: 5003A | BB8: 1908.384 | BC8: 7645.704 | BD8: 4138.6509 | BE8: 9115.4488 | BF8: 5008.3968 | BG8: 15719.339 | BH8: 11808.262 | BI8: 11589.647 | BJ8: 16077.011 | BK8: 22499.109 | BL8: 15364.751 | BM8: 7988.4705 | BN8: 34456.695 | BO8: 21008.922 | BP8: 8137.8702 | BQ8: 3667.9875 | BR8: 15751.774 | BS8: 19899.98 | BT8: 17218.736 | BU8: 15382.221 | BV8: -19550.427 | BW8: 2137.0499 | BX8: 2148.7976 | BY8: 7195.6405 | BZ8: 8413.6777 | CA8: 9603.9203 | CB8: 8609.9023 | CC8: 14463.682 | CD8: 11130.039 | CE8: 15973.956 | CF8: 19209.004 | CG8: 15774.527 | CH8: 9964.3962 | CI8: 10034.692 | CJ8: 12977.339 | CK8: 3609.9202 | CL8: 9751.4982 | CM8: 2374.5373 | CN8: 21391.419 | CO8: 11714.203 | CP8: 18968.626 | CQ8: 21480.529 | CR8: 13872.942 | CS8: 17921.207 | CT8: 20578.906 | CU8: 23363.424 | CV8: 21261.17 | CW8: 16663.447 | CX8: 6209.6272 | CY8: 15357.722 | CZ8: 10461.086 | DA8: 24396.274 | DB8: 17722.355 | DC8: 14726.895 | DD8: 18761.553 | DE8: 12778.759
A9: 500A9 | CJ9: 23074.987 | CK9: 21140.282 | CL9: -6513.6602 | CM9: 11296.611 | CN9: 12387.783 | CO9: 6748.2782 | CP9: 20331.648 | CQ9: 10687.035 | CR9: 15055.248 | CS9: 16392.299 | CT9: 17659.159 | CU9: 21533.992 | CV9: 24719.737 | CW9: -3384.9232 | CX9: 23698.344 | CY9: 27188.879 | CZ9: 27457.912 | DA9: 49073.733 | DB9: 38030.344 | DC9: 35741.747 | DD9: 52296.379 | DE9: 21172.182
A10: 500D4 | CA10: 8696.5967 | CB10: -7535.3167 | CC10: 11658.935 | CD10: 6876.4191 | CE10: -2810.8226 | CF10: -2309.0708 | CG10: 702.2044 | CH10: 9323.0404 | CI10: 7176.9496 | CJ10: 7721.3829 | CK10: 6434.5801 | CL10: -6878.908 | CM10: -4708.345 | CN10: 5700.2137 | CO10: -94.64227 | CP10: 7109.6919 | CQ10: 993.35234 | CR10: 6085.4481 | CS10: 757.4456 | CT10: 10814.537 | CU10: 7430.68 | CV10: 4614.6432 | CW10: -4177.4105 | CX10: 4920.4838 | CY10: 12676.86 | CZ10: 5475.6761 | DA10: 19200.183 | DB10: 5990.6526 | DC10: 5989.9865 | DD10: 2909.229 | DE10: 4358.1558
A11: 500DU | CC11: 6447.6521 | CD11: 46019.353 | CE11: 56257.668 | CF11: 52106.349 | CG11: 57707.237 | CH11: 55603.977 | CI11: 43353.837 | CJ11: 46364.867 | CK11: 38289.111 | CL11: 35120.347 | CM11: 31898.671 | CN11: 27294.815 | CO11: 23527.079 | CP11: 30959.108 | CQ11: 29235.922 | CR11: 31728.089 | CS11: 27944.257 | CT11: 23666.96 | CU11: 36033.907 | CV11: 32048.629 | CW11: 32063.479 | CX11: 37051.218 | CY11: 36880.317 | CZ11: 28720.835 | DA11: 36224.414 | DB11: 24040.651 | DC11: 21330.412 | DD11: 24683.318 | DE11: 34735.803
A12: 500E2 | BW12: 16967.638 | BX12: 15366.382 | BY12: -729.1238 | BZ12: 6397.7619 | CA12: -1823.1685 | CB12: -232.8701 | CC12: 16246.265 | CD12: 13053.743 | CE12: 14531.884 | CF12: 11706.039 | CG12: 17684.673 | CH12: 16315.969 | CI12: 20650.786 | CJ12: 18466.02 | CK12: 23414.542 | CL12: 13317.976 | CM12: 8939.8317 | CN12: 15864.671 | CO12: 18567.025 | CP12: 21839.532 | CQ12: 26750.205 | CR12: 28490.405 | CS12: 24922.587 | CT12: 21821.873 | CU12: 25382.753 | CV12: 30122.168 | CW12: 20228.557 | CX12: 22357.199 | CY12: 23290.581 | CZ12: 17626.533 | DA12: 18920.109 | DB12: 20228.907 | DC12: 15643.425 | DD12: -172751.17 | DE12: 11458.227
A13: 500EZ | AG13: -4743.6485 | AH13: 2134.9603 | AI13: 5397.6512 | AJ13: 5010.0736 | AK13: -4873.0192 | AL13: -13180.283 | AM13: -6817.8989 | AN13: -1015.3663 | AO13: -10864.402 | AP13: -6951.5407 | AQ13: 92.3533 | AR13: 7083.5989 | AS13: -15084.797 | AT13: -6751.6586 | AU13: 8182.0035 | AV13: 4699.1705 | AW13: -3712.5724 | AX13: 2262.7961 | AY13: 6491.8467 | AZ13: 12688.711 | BA13: 8878.842 | BB13: 12141.958 | BC13: 21816.896 | BD13: 12734.145 | BE13: 21236.879 | BF13: 14635.104 | BG13: 31882.662 | BH13: 23311.152 | BI13: 33286.861 | BJ13: 22159.815 | BK13: 32944.272 | BL13: 35729.559 | BM13: 16770.626 | BN13: 42733.096 | BO13: 33212.812 | BP13: 22380.18 | BQ13: 28032.287 | BR13: 36906.447 | BS13: 19805.74 | BT13: 33511.13 | BU13: 31867.729 | BV13: 32140.29 | BW13: 27827.542 | BX13: 27106.4 | BY13: 33638.508 | BZ13: 27621.166 | CA13: 24615.927 | CB13: 18412.374 | CC13: 23568.074 | CD13: 24304.799 | CE13: 28418.418 | CF13: 31411.055 | CG13: 35245.262 | CH13: 37917.634 | CI13: 36848.272 | CJ13: 42986.956 | CK13: 42269.17 | CL13: 26252.647 | CM13: 30206.473 | CN13: 35511.317 | CO13: 36065.114 | CP13: 34146.644 | CQ13: 31751.774 | CR13: 34154.544 | CS13: 34596.414 | CT13: 31456.71 | CU13: 38051.119 | CV13: 28555.585 | CW13: 20748.566 | CX13: 24257.137 | CY13: 27252.137 | CZ13: 20355.527 | DA13: 33624.364 | DB13: 32360.188 | DC13: 31342.591 | DD13: 26814.335 | DE13: 20892.911
A14: 500GV | CT14: -15671.716 | CU14: -912.871 | CV14: -1761.4206 | CW14: 621.13095 | CX14: -2887.5781 | CY14: 8921.8075 | CZ14: 13271.65 | DA14: 22840.513 | DB14: 14221.441 | DC14: 8982.1365 | DD14: 8689.405 | DE14: 4599.9757
A15: 500TU | BU15: -2599.3044 | BV15: -9794.5342 | BW15: -6254.3094 | BX15: -9088.0544 | BY15: 10192.363 | BZ15: 7676.0503 | CA15: 9336.0979 | CB15: -7317.6311 | CC15: 8661.6099 | CD15: -431.0847 | CE15: 95.677 | CF15: 187.3881 | CG15: -4849.2506 | CH15: 12627.966 | CI15: -69860.852 | CJ15: 10193.98 | CK15: 23279.271 | CL15: 9191.0235 | CM15: 8687.5638 | CN15: 22369.064 | CO15: 15643.097 | CP15: 17223.24 | CQ15: 19082.009 | CR15: 18841.057 | CS15: 18847.423 | CT15: 14406.436 | CU15: 24987.871 | CV15: 30277.227 | CW15: 8109.5905 | CX15: 12252.76 | CY15: 26897.937 | CZ15: 29564.371 | DA15: 35562.537 | DB15: 27269.281 | DC15: 29377.366 | DD15: 36475.407 | DE15: 10475.573
A16: 500WO | CL16: -11960.136 | CM16: 1119.6679 | CN16: 7623.7237 | CO16: 4630.4361 | CP16: 12196.869 | CQ16: 4857.9571 | CR16: 3234.9146 | CS16: 6183.9378 | CT16: 12376.905 | CU16: 11068.214 | CV16: 11792.389 | CW16: -1500.5732 | CX16: 8333.6729 | CY16: 18248.062 | CZ16: 17977.714 | DA16: 28685.057 | DB16: 5097.6593 | DC16: 15104.214 | DD16: 18852.853 | DE16: 9153.8704
A17: 500XK | BN17: 30401.67 | BO17: 3107.3605 | BP17: -3596.6819 | BQ17: -1564.0575 | BR17: 4815.1219 | BS17: -365.03546 | BT17: 5726.6003 | BU17: 6432.1094 | BV17: 902.4303 | BW17: -63.9489 | BX17: -527.9531 | BY17: 2269.1461 | BZ17: 4017.5885 | CA17: 4734.2949 | CB17: -9637.0659 | CC17: 4000.2379 | CD17: -2275.2956 | CE17: 2883.8841 | CF17: -6434.4278 | CG17: 15649.875 | CH17: 20699.281 | CI17: 8074.3445 | CJ17: 16449.687 | CK17: 9145.383 | CL17: 3672.0912 | CM17: 5992.7896 | CN17: -2918.067 | CO17: 10446.25 | CP17: 8996.88 | CQ17: 1572.9414 | CR17: 13389.44 | CS17: 13393.523 | CT17: 12610.887 | CU17: 14817.645 | CV17: 15344.86 | CW17: 168.02585 | CX17: 2733.4245 | CY17: 9591.0625 | CZ17: 10783.852 | DA17: 14634.896 | DB17: 9061.794 | DC17: 15366.86 | DD17: 16032.298 | DE17: 6742.398
A18: 5015G | BY18: 11204.28 | BZ18: 17215.007 | CA18: 34166.547 | CB18: 4507.6789 | CC18: 25756.926 | CD18: -15531.039 | CE18: -1386.3756 | CF18: 32416.373 | CG18: 8894.669 | CH18: 7602.691 | CI18: 14695.118 | CJ18: 23110.053 | CK18: 20477.749 | CL18: 22913.999 | CM18: -12825.88 | CN18: 12644.728 | CO18: 21252.853 | CP18: 9441.4894 | CQ18: 49522.848 | CR18: 18197.936 | CS18: 39896.564 | CT18: 9722.8182 | CU18: 32094.762 | CV18: 31951.432 | CW18: 48918.64 | CX18: 6804.5444 | CY18: 32383.471 | CZ18: 21433.291 | DA18: 35959.154 | DB18: 56755.475 | DC18: 37854.304 | DD18: 48600.956 | DE18: 22082.908
